Workbook

Sheet Cover & Instructions
B2: HOTEL FINANCIAL REPORTING TEMPLATES
B3: Uniform System of Accounts for the Lodging Industry (USALI) — 11th Revised Edition
B5: A complete, ready-to-use set of operating statements and departmental schedules formatted in conformity with the USALI standard adopted across the global hotel industry.
B8: How to use this workbook
B9: 1. Open "Setup & Assumptions" and enter your property name, period and currency.
B10: 2. Enter actual / budget / prior-year figures into the blue cells on each departmental schedule.
B11: 3. Departmental totals roll up automatically to the two Summary Operating Statements.
B12: 4. Review the "Operating Metrics & Ratios" sheet for auto-calculated KPIs (Occupancy, ADR, RevPAR, GOP, EBITDA).
B14: Colour legend
B15: Blue text | C15: Input cells — enter your figures here
B16: Black text | C16: Calculated totals and sub-totals — do not overwrite
B17: Green text | C17: Links pulling values from another worksheet
B19: Schedules included
B20: Summary Operating Statement | C20: For Operators (EBITDA less Replacement Reserve) and For Owners (Net Income)
B21: Schedule 1 | C21: Rooms
B22: Schedule 2 | C22: Food and Beverage
B23: Schedule 3 + 3-1/3-2/3-3/3-x/3-xx | C23: Other Operated Departments (Golf, Health Club/Spa, Parking, Generic, Minor)
B24: Schedule 4 | C24: Miscellaneous Income
B25: Schedule 5 | C25: Administrative and General
B26: Schedule 6 | C26: Information and Telecommunications Systems
B27: Schedule 7 | C27: Sales and Marketing
B28: Schedule 8 | C28: Property Operation and Maintenance
B29: Schedule 9 | C29: Utilities
B30: Schedule 10 | C30: Management Fees
B31: Schedule 11 | C31: Non-Operating Income and Expenses
... B35: Operating Metrics & Ratios | C35: Occupancy, ADR, RevPAR, Total RevPAR, GOP, GOPPAR, EBITDA and more
B37: This template is provided for financial-reporting convenience. It reproduces the line-item structure of the USALI 11th Revised Edition for practitioner use; it is not the copyrighted text of the standard. The USALI is published by the Hospitality Financial and Technology Professionals (HFTP) and the American Hotel & Lodging Association. Refer to the official publication for full account definitions and guidance.

Sheet Setup & Assumptions
A1: SETUP & ASSUMPTIONS
A3: Property Details
A4: Property / Hotel Name | B4: Enter property name
A5: Reporting Period / Year | B5: e.g. January 2026 / FY2026
A6: Reporting Currency | B6: INR
A7: Prepared By
A8: Date Prepared
A10: Notes on Use
A11: • The Property Name and Reporting Period entered above flow automatically to the header of every schedule.
A12: • Enter all amounts in the blue (input) cells only. Black figures are calculated; do not overwrite them.
A13: • Green figures are links pulling totals from other worksheets within this workbook.
A14: • Enter "Less: Allowances" and credit/recovery lines as positive numbers — the formulas subtract them.
A15: • The Replacement Reserve (Operators statement) and Interest / Depreciation / Amortization / Income Taxes
A16: (Owners statement) are entered directly on the respective Summary Operating Statement.
A17: • House Laundry (Sch 12) and Staff Dining (Sch 13) are allocated to operating departments and are not
A18: shown separately on the Summary Operating Statement.
A19: • You may delete line items that do not apply to your property. Do not add or rename approved USALI line
A20: items; instead create a supporting sub-account/sub-schedule that rolls into the appropriate line.

Sheet Summary Op Stmt (Operators)
A1: SUMMARY OPERATING STATEMENT [For Operators]
A2: Property: | B2: ='Setup & Assumptions'!$B$4 -> Enter property name | H2: Period / Year: | J2: ='Setup & Assumptions'!$B$5 -> e.g. January 2026 / FY2026
A3: Bottom line: EBITDA Less Replacement Reserve. Revenue/expense % is of Total Operating Revenue; departmental expense % is of departmental revenue.
B4: Current Period | H4: Year-To-Date
B5: Actual | D5: Forecast / Budget | F5: Prior Year | H5: Actual | J5: Forecast / Budget | L5: Prior Year
A6: Line Item | B6: $ | C6: % | D6: $ | E6: % | F6: $ | G6: % | H6: $ | I6: % | J6: $ | K6: % | L6: $ | M6: %
A7: Operating Statistics
A8: Rooms Available
A9: Rooms Sold
A10: Occupancy % | B10: =IF(B8=0,"",B9/B8) | D10: =IF(D8=0,"",D9/D8) | F10: =IF(F8=0,"",F9/F8) | H10: =IF(H8=0,"",H9/H8) | J10: =IF(J8=0,"",J9/J8) | L10: =IF(L8=0,"",L9/L8)
A11: ADR (Average Daily Rate) | B11: =IF(B9=0,"",B16/B9) | D11: =IF(D9=0,"",D16/D9) | F11: =IF(F9=0,"",F16/F9) | H11: =IF(H9=0,"",H16/H9) | J11: =IF(J9=0,"",J16/J9) | L11: =IF(L9=0,"",L16/L9)
A12: Rooms RevPAR | B12: =IF(B8=0,"",B16/B8) | D12: =IF(D8=0,"",D16/D8) | F12: =IF(F8=0,"",F16/F8) | H12: =IF(H8=0,"",H16/H8) | J12: =IF(J8=0,"",J16/J8) | L12: =IF(L8=0,"",L16/L8)
A13: Total RevPAR | B13: =IF(B8=0,"",B20/B8) | D13: =IF(D8=0,"",D20/D8) | F13: =IF(F8=0,"",F20/F8) | H13: =IF(H8=0,"",H20/H8) | J13: =IF(J8=0,"",J20/J8) | L13: =IF(L8=0,"",L20/L8)
A15: Operating Revenue
A16: Rooms | B16: ='Schedule 1 - Rooms'!B25 -> 0 | C16: =IF(OR('Summary Op Stmt (Operators)'!$B$20=0,'Summary Op Stmt (Operators)'!$B$20=""),"",B16/'Summary Op Stmt (Operators)'!$B$20) | D16: ='Schedule 1 - Rooms'!D25 -> 0 | E16: =IF(OR('Summary Op Stmt (Operators)'!$D$20=0,'Summary Op Stmt (Operators)'!$D$20=""),"",D16/'Summary Op Stmt (Operators)'!$D$20) | F16: ='Schedule 1 - Rooms'!F25 -> 0 | G16: =IF(OR('Summary Op Stmt (Operators)'!$F$20=0,'Summary Op Stmt (Operators)'!$F$20=""),"",F16/'Summary Op Stmt (Operators)'!$F$20) | H16: ='Schedule 1 - Rooms'!H25 -> 0 | I16: =IF(OR('Summary Op Stmt (Operators)'!$H$20=0,'Summary Op Stmt (Operators)'!$H$20=""),"",H16/'Summary Op Stmt (Operators)'!$H$20) | J16: ='Schedule 1 - Rooms'!J25 -> 0 | K16: =IF(OR('Summary Op Stmt (Operators)'!$J$20=0,'Summary Op Stmt (Operators)'!$J$20=""),"",J16/'Summary Op Stmt (Operators)'!$J$20) | L16: ='Schedule 1 - Rooms'!L25 -> 0 | M16: =IF(OR('Summary Op Stmt (Operators)'!$L$20=0,'Summary Op Stmt (Operators)'!$L$20=""),"",L16/'Summary Op Stmt (Operators)'!$L$20)
A17: Food and Beverage | B17: ='Schedule 2 - Food & Beverage'!B32 -> 0 | C17: =IF(OR('Summary Op Stmt (Operators)'!$B$20=0,'Summary Op Stmt (Operators)'!$B$20=""),"",B17/'Summary Op Stmt (Operators)'!$B$20) | D17: ='Schedule 2 - Food & Beverage'!D32 -> 0 | E17: =IF(OR('Summary Op Stmt (Operators)'!$D$20=0,'Summary Op Stmt (Operators)'!$D$20=""),"",D17/'Summary Op Stmt (Operators)'!$D$20) | F17: ='Schedule 2 - Food & Beverage'!F32 -> 0 | G17: =IF(OR('Summary Op Stmt (Operators)'!$F$20=0,'Summary Op Stmt (Operators)'!$F$20=""),"",F17/'Summary Op Stmt (Operators)'!$F$20) | H17: ='Schedule 2 - Food & Beverage'!H32 -> 0 | I17: =IF(OR('Summary Op Stmt (Operators)'!$H$20=0,'Summary Op Stmt (Operators)'!$H$20=""),"",H17/'Summary Op Stmt (Operators)'!$H$20) | J17: ='Schedule 2 - Food & Beverage'!J32 -> 0 | K17: =IF(OR('Summary Op Stmt (Operators)'!$J$20=0,'Summary Op Stmt (Operators)'!$J$20=""),"",J17/'Summary Op Stmt (Operators)'!$J$20) | L17: ='Schedule 2 - Food & Beverage'!L32 -> 0 | M17: =IF(OR('Summary Op Stmt (Operators)'!$L$20=0,'Summary Op Stmt (Operators)'!$L$20=""),"",L17/'Summary Op Stmt (Operators)'!$L$20)
A18: Other Operated Departments | B18: ='Schedule 3 - Other Op Depts'!B13 -> 0 | C18: =IF(OR('Summary Op Stmt (Operators)'!$B$20=0,'Summary Op Stmt (Operators)'!$B$20=""),"",B18/'Summary Op Stmt (Operators)'!$B$20) | D18: ='Schedule 3 - Other Op Depts'!D13 -> 0 | E18: =IF(OR('Summary Op Stmt (Operators)'!$D$20=0,'Summary Op Stmt (Operators)'!$D$20=""),"",D18/'Summary Op Stmt (Operators)'!$D$20) | F18: ='Schedule 3 - Other Op Depts'!F13 -> 0 | G18: =IF(OR('Summary Op Stmt (Operators)'!$F$20=0,'Summary Op Stmt (Operators)'!$F$20=""),"",F18/'Summary Op Stmt (Operators)'!$F$20) | H18: ='Schedule 3 - Other Op Depts'!H13 -> 0 | I18: =IF(OR('Summary Op Stmt (Operators)'!$H$20=0,'Summary Op Stmt (Operators)'!$H$20=""),"",H18/'Summary Op Stmt (Operators)'!$H$20) | J18: ='Schedule 3 - Other Op Depts'!J13 -> 0 | K18: =IF(OR('Summary Op Stmt (Operators)'!$J$20=0,'Summary Op Stmt (Operators)'!$J$20=""),"",J18/'Summary Op Stmt (Operators)'!$J$20) | L18: ='Schedule 3 - Other Op Depts'!L13 -> 0 | M18: =IF(OR('Summary Op Stmt (Operators)'!$L$20=0,'Summary Op Stmt (Operators)'!$L$20=""),"",L18/'Summary Op Stmt (Operators)'!$L$20)
A19: Miscellaneous Income | B19: ='Schedule 4 - Misc Income'!B22 -> 0 | C19: =IF(OR('Summary Op Stmt (Operators)'!$B$20=0,'Summary Op Stmt (Operators)'!$B$20=""),"",B19/'Summary Op Stmt (Operators)'!$B$20) | D19: ='Schedule 4 - Misc Income'!D22 -> 0 | E19: =IF(OR('Summary Op Stmt (Operators)'!$D$20=0,'Summary Op Stmt (Operators)'!$D$20=""),"",D19/'Summary Op Stmt (Operators)'!$D$20) | F19: ='Schedule 4 - Misc Income'!F22 -> 0 | G19: =IF(OR('Summary Op Stmt (Operators)'!$F$20=0,'Summary Op Stmt (Operators)'!$F$20=""),"",F19/'Summary Op Stmt (Operators)'!$F$20) | H19: ='Schedule 4 - Misc Income'!H22 -> 0 | I19: =IF(OR('Summary Op Stmt (Operators)'!$H$20=0,'Summary Op Stmt (Operators)'!$H$20=""),"",H19/'Summary Op Stmt (Operators)'!$H$20) | J19: ='Schedule 4 - Misc Income'!J22 -> 0 | K19: =IF(OR('Summary Op Stmt (Operators)'!$J$20=0,'Summary Op Stmt (Operators)'!$J$20=""),"",J19/'Summary Op Stmt (Operators)'!$J$20) | L19: ='Schedule 4 - Misc Income'!L22 -> 0 | M19: =IF(OR('Summary Op Stmt (Operators)'!$L$20=0,'Summary Op Stmt (Operators)'!$L$20=""),"",L19/'Summary Op Stmt (Operators)'!$L$20)
A20: Total Operating Revenue | B20: =B16+B17+B18+B19 -> 0 | C20: =IF(OR('Summary Op Stmt (Operators)'!$B$20=0,'Summary Op Stmt (Operators)'!$B$20=""),"",B20/'Summary Op Stmt (Operators)'!$B$20) | D20: =D16+D17+D18+D19 -> 0 | E20: =IF(OR('Summary Op Stmt (Operators)'!$D$20=0,'Summary Op Stmt (Operators)'!$D$20=""),"",D20/'Summary Op Stmt (Operators)'!$D$20) | F20: =F16+F17+F18+F19 -> 0 | G20: =IF(OR('Summary Op Stmt (Operators)'!$F$20=0,'Summary Op Stmt (Operators)'!$F$20=""),"",F20/'Summary Op Stmt (Operators)'!$F$20) | H20: =H16+H17+H18+H19 -> 0 | I20: =IF(OR('Summary Op Stmt (Operators)'!$H$20=0,'Summary Op Stmt (Operators)'!$H$20=""),"",H20/'Summary Op Stmt (Operators)'!$H$20) | J20: =J16+J17+J18+J19 -> 0 | K20: =IF(OR('Summary Op Stmt (Operators)'!$J$20=0,'Summary Op Stmt (Operators)'!$J$20=""),"",J20/'Summary Op Stmt (Operators)'!$J$20) | L20: =L16+L17+L18+L19 -> 0 | M20: =IF(OR('Summary Op Stmt (Operators)'!$L$20=0,'Summary Op Stmt (Operators)'!$L$20=""),"",L20/'Summary Op Stmt (Operators)'!$L$20)
A21: Departmental Expenses
A22: Rooms | B22: ='Schedule 1 - Rooms'!B81 -> 0 | C22: =IF(OR(B16=0,B16=""),"",B22/B16) | D22: ='Schedule 1 - Rooms'!D81 -> 0 | E22: =IF(OR(D16=0,D16=""),"",D22/D16) | F22: ='Schedule 1 - Rooms'!F81 -> 0 | G22: =IF(OR(F16=0,F16=""),"",F22/F16) | H22: ='Schedule 1 - Rooms'!H81 -> 0 | I22: =IF(OR(H16=0,H16=""),"",H22/H16) | J22: ='Schedule 1 - Rooms'!J81 -> 0 | K22: =IF(OR(J16=0,J16=""),"",J22/J16) | L22: ='Schedule 1 - Rooms'!L81 -> 0 | M22: =IF(OR(L16=0,L16=""),"",L22/L16)
A23: Food and Beverage | B23: ='Schedule 2 - Food & Beverage'!B42+'Schedule 2 - Food & Beverage'!B105 -> 0 | C23: =IF(OR(B17=0,B17=""),"",B23/B17) | D23: ='Schedule 2 - Food & Beverage'!D42+'Schedule 2 - Food & Beverage'!D105 -> 0 | E23: =IF(OR(D17=0,D17=""),"",D23/D17) | F23: ='Schedule 2 - Food & Beverage'!F42+'Schedule 2 - Food & Beverage'!F105 -> 0 | G23: =IF(OR(F17=0,F17=""),"",F23/F17) | H23: ='Schedule 2 - Food & Beverage'!H42+'Schedule 2 - Food & Beverage'!H105 -> 0 | I23: =IF(OR(H17=0,H17=""),"",H23/H17) | J23: ='Schedule 2 - Food & Beverage'!J42+'Schedule 2 - Food & Beverage'!J105 -> 0 | K23: =IF(OR(J17=0,J17=""),"",J23/J17) | L23: ='Schedule 2 - Food & Beverage'!L42+'Schedule 2 - Food & Beverage'!L105 -> 0 | M23: =IF(OR(L17=0,L17=""),"",L23/L17)
A24: Other Operated Departments | B24: ='Schedule 3 - Other Op Depts'!B20 -> 0 | C24: =IF(OR(B18=0,B18=""),"",B24/B18) | D24: ='Schedule 3 - Other Op Depts'!D20 -> 0 | E24: =IF(OR(D18=0,D18=""),"",D24/D18) | F24: ='Schedule 3 - Other Op Depts'!F20 -> 0 | G24: =IF(OR(F18=0,F18=""),"",F24/F18) | H24: ='Schedule 3 - Other Op Depts'!H20 -> 0 | I24: =IF(OR(H18=0,H18=""),"",H24/H18) | J24: ='Schedule 3 - Other Op Depts'!J20 -> 0 | K24: =IF(OR(J18=0,J18=""),"",J24/J18) | L24: ='Schedule 3 - Other Op Depts'!L20 -> 0 | M24: =IF(OR(L18=0,L18=""),"",L24/L18)
A25: Total Departmental Expenses | B25: =B22+B23+B24 -> 0 | C25: =IF(OR('Summary Op Stmt (Operators)'!$B$20=0,'Summary Op Stmt (Operators)'!$B$20=""),"",B25/'Summary Op Stmt (Operators)'!$B$20) | D25: =D22+D23+D24 -> 0 | E25: =IF(OR('Summary Op Stmt (Operators)'!$D$20=0,'Summary Op Stmt (Operators)'!$D$20=""),"",D25/'Summary Op Stmt (Operators)'!$D$20) | F25: =F22+F23+F24 -> 0 | G25: =IF(OR('Summary Op Stmt (Operators)'!$F$20=0,'Summary Op Stmt (Operators)'!$F$20=""),"",F25/'Summary Op Stmt (Operators)'!$F$20) | H25: =H22+H23+H24 -> 0 | I25: =IF(OR('Summary Op Stmt (Operators)'!$H$20=0,'Summary Op Stmt (Operators)'!$H$20=""),"",H25/'Summary Op Stmt (Operators)'!$H$20) | J25: =J22+J23+J24 -> 0 | K25: =IF(OR('Summary Op Stmt (Operators)'!$J$20=0,'Summary Op Stmt (Operators)'!$J$20=""),"",J25/'Summary Op Stmt (Operators)'!$J$20) | L25: =L22+L23+L24 -> 0 | M25: =IF(OR('Summary Op Stmt (Operators)'!$L$20=0,'Summary Op Stmt (Operators)'!$L$20=""),"",L25/'Summary Op Stmt (Operators)'!$L$20)
A26: Total Departmental Profit | B26: =B20-B25 -> 0 | C26: =IF(OR('Summary Op Stmt (Operators)'!$B$20=0,'Summary Op Stmt (Operators)'!$B$20=""),"",B26/'Summary Op Stmt (Operators)'!$B$20) | D26: =D20-D25 -> 0 | E26: =IF(OR('Summary Op Stmt (Operators)'!$D$20=0,'Summary Op Stmt (Operators)'!$D$20=""),"",D26/'Summary Op Stmt (Operators)'!$D$20) | F26: =F20-F25 -> 0 | G26: =IF(OR('Summary Op Stmt (Operators)'!$F$20=0,'Summary Op Stmt (Operators)'!$F$20=""),"",F26/'Summary Op Stmt (Operators)'!$F$20) | H26: =H20-H25 -> 0 | I26: =IF(OR('Summary Op Stmt (Operators)'!$H$20=0,'Summary Op Stmt (Operators)'!$H$20=""),"",H26/'Summary Op Stmt (Operators)'!$H$20) | J26: =J20-J25 -> 0 | K26: =IF(OR('Summary Op Stmt (Operators)'!$J$20=0,'Summary Op Stmt (Operators)'!$J$20=""),"",J26/'Summary Op Stmt (Operators)'!$J$20) | L26: =L20-L25 -> 0 | M26: =IF(OR('Summary Op Stmt (Operators)'!$L$20=0,'Summary Op Stmt (Operators)'!$L$20=""),"",L26/'Summary Op Stmt (Operators)'!$L$20)
A27: Undistributed Operating Expenses
A28: Administrative and General | B28: ='Schedule 5 - Admin & General'!B65 -> 0 | C28: =IF(OR('Summary Op Stmt (Operators)'!$B$20=0,'Summary Op Stmt (Operators)'!$B$20=""),"",B28/'Summary Op Stmt (Operators)'!$B$20) | D28: ='Schedule 5 - Admin & General'!D65 -> 0 | E28: =IF(OR('Summary Op Stmt (Operators)'!$D$20=0,'Summary Op Stmt (Operators)'!$D$20=""),"",D28/'Summary Op Stmt (Operators)'!$D$20) | F28: ='Schedule 5 - Admin & General'!F65 -> 0 | G28: =IF(OR('Summary Op Stmt (Operators)'!$F$20=0,'Summary Op Stmt (Operators)'!$F$20=""),"",F28/'Summary Op Stmt (Operators)'!$F$20) | H28: ='Schedule 5 - Admin & General'!H65 -> 0 | I28: =IF(OR('Summary Op Stmt (Operators)'!$H$20=0,'Summary Op Stmt (Operators)'!$H$20=""),"",H28/'Summary Op Stmt (Operators)'!$H$20) | J28: ='Schedule 5 - Admin & General'!J65 -> 0 | K28: =IF(OR('Summary Op Stmt (Operators)'!$J$20=0,'Summary Op Stmt (Operators)'!$J$20=""),"",J28/'Summary Op Stmt (Operators)'!$J$20) | L28: ='Schedule 5 - Admin & General'!L65 -> 0 | M28: =IF(OR('Summary Op Stmt (Operators)'!$L$20=0,'Summary Op Stmt (Operators)'!$L$20=""),"",L28/'Summary Op Stmt (Operators)'!$L$20)
A29: Information and Telecommunications Systems | B29: ='Schedule 6 - Info & Telecom'!B68 -> 0 | C29: =IF(OR('Summary Op Stmt (Operators)'!$B$20=0,'Summary Op Stmt (Operators)'!$B$20=""),"",B29/'Summary Op Stmt (Operators)'!$B$20) | D29: ='Schedule 6 - Info & Telecom'!D68 -> 0 | E29: =IF(OR('Summary Op Stmt (Operators)'!$D$20=0,'Summary Op Stmt (Operators)'!$D$20=""),"",D29/'Summary Op Stmt (Operators)'!$D$20) | F29: ='Schedule 6 - Info & Telecom'!F68 -> 0 | G29: =IF(OR('Summary Op Stmt (Operators)'!$F$20=0,'Summary Op Stmt (Operators)'!$F$20=""),"",F29/'Summary Op Stmt (Operators)'!$F$20) | H29: ='Schedule 6 - Info & Telecom'!H68 -> 0 | I29: =IF(OR('Summary Op Stmt (Operators)'!$H$20=0,'Summary Op Stmt (Operators)'!$H$20=""),"",H29/'Summary Op Stmt (Operators)'!$H$20) | J29: ='Schedule 6 - Info & Telecom'!J68 -> 0 | K29: =IF(OR('Summary Op Stmt (Operators)'!$J$20=0,'Summary Op Stmt (Operators)'!$J$20=""),"",J29/'Summary Op Stmt (Operators)'!$J$20) | L29: ='Schedule 6 - Info & Telecom'!L68 -> 0 | M29: =IF(OR('Summary Op Stmt (Operators)'!$L$20=0,'Summary Op Stmt (Operators)'!$L$20=""),"",L29/'Summary Op Stmt (Operators)'!$L$20)
A30: Sales and Marketing | B30: ='Schedule 7 - Sales & Marketing'!B57 -> 0 | C30: =IF(OR('Summary Op Stmt (Operators)'!$B$20=0,'Summary Op Stmt (Operators)'!$B$20=""),"",B30/'Summary Op Stmt (Operators)'!$B$20) | D30: ='Schedule 7 - Sales & Marketing'!D57 -> 0 | E30: =IF(OR('Summary Op Stmt (Operators)'!$D$20=0,'Summary Op Stmt (Operators)'!$D$20=""),"",D30/'Summary Op Stmt (Operators)'!$D$20) | F30: ='Schedule 7 - Sales & Marketing'!F57 -> 0 | G30: =IF(OR('Summary Op Stmt (Operators)'!$F$20=0,'Summary Op Stmt (Operators)'!$F$20=""),"",F30/'Summary Op Stmt (Operators)'!$F$20) | H30: ='Schedule 7 - Sales & Marketing'!H57 -> 0 | I30: =IF(OR('Summary Op Stmt (Operators)'!$H$20=0,'Summary Op Stmt (Operators)'!$H$20=""),"",H30/'Summary Op Stmt (Operators)'!$H$20) | J30: ='Schedule 7 - Sales & Marketing'!J57 -> 0 | K30: =IF(OR('Summary Op Stmt (Operators)'!$J$20=0,'Summary Op Stmt (Operators)'!$J$20=""),"",J30/'Summary Op Stmt (Operators)'!$J$20) | L30: ='Schedule 7 - Sales & Marketing'!L57 -> 0 | M30: =IF(OR('Summary Op Stmt (Operators)'!$L$20=0,'Summary Op Stmt (Operators)'!$L$20=""),"",L30/'Summary Op Stmt (Operators)'!$L$20)
A31: Property Operation and Maintenance | B31: ='Schedule 8 - Prop Op & Maint'!B57 -> 0 | C31: =IF(OR('Summary Op Stmt (Operators)'!$B$20=0,'Summary Op Stmt (Operators)'!$B$20=""),"",B31/'Summary Op Stmt (Operators)'!$B$20) | D31: ='Schedule 8 - Prop Op & Maint'!D57 -> 0 | E31: =IF(OR('Summary Op Stmt (Operators)'!$D$20=0,'Summary Op Stmt (Operators)'!$D$20=""),"",D31/'Summary Op Stmt (Operators)'!$D$20) | F31: ='Schedule 8 - Prop Op & Maint'!F57 -> 0 | G31: =IF(OR('Summary Op Stmt (Operators)'!$F$20=0,'Summary Op Stmt (Operators)'!$F$20=""),"",F31/'Summary Op Stmt (Operators)'!$F$20) | H31: ='Schedule 8 - Prop Op & Maint'!H57 -> 0 | I31: =IF(OR('Summary Op Stmt (Operators)'!$H$20=0,'Summary Op Stmt (Operators)'!$H$20=""),"",H31/'Summary Op Stmt (Operators)'!$H$20) | J31: ='Schedule 8 - Prop Op & Maint'!J57 -> 0 | K31: =IF(OR('Summary Op Stmt (Operators)'!$J$20=0,'Summary Op Stmt (Operators)'!$J$20=""),"",J31/'Summary Op Stmt (Operators)'!$J$20) | L31: ='Schedule 8 - Prop Op & Maint'!L57 -> 0 | M31: =IF(OR('Summary Op Stmt (Operators)'!$L$20=0,'Summary Op Stmt (Operators)'!$L$20=""),"",L31/'Summary Op Stmt (Operators)'!$L$20)
A32: Utilities | B32: ='Schedule 9 - Utilities'!B16 -> 0 | C32: =IF(OR('Summary Op Stmt (Operators)'!$B$20=0,'Summary Op Stmt (Operators)'!$B$20=""),"",B32/'Summary Op Stmt (Operators)'!$B$20) | D32: ='Schedule 9 - Utilities'!D16 -> 0 | E32: =IF(OR('Summary Op Stmt (Operators)'!$D$20=0,'Summary Op Stmt (Operators)'!$D$20=""),"",D32/'Summary Op Stmt (Operators)'!$D$20) | F32: ='Schedule 9 - Utilities'!F16 -> 0 | G32: =IF(OR('Summary Op Stmt (Operators)'!$F$20=0,'Summary Op Stmt (Operators)'!$F$20=""),"",F32/'Summary Op Stmt (Operators)'!$F$20) | H32: ='Schedule 9 - Utilities'!H16 -> 0 | I32: =IF(OR('Summary Op Stmt (Operators)'!$H$20=0,'Summary Op Stmt (Operators)'!$H$20=""),"",H32/'Summary Op Stmt (Operators)'!$H$20) | J32: ='Schedule 9 - Utilities'!J16 -> 0 | K32: =IF(OR('Summary Op Stmt (Operators)'!$J$20=0,'Summary Op Stmt (Operators)'!$J$20=""),"",J32/'Summary Op Stmt (Operators)'!$J$20) | L32: ='Schedule 9 - Utilities'!L16 -> 0 | M32: =IF(OR('Summary Op Stmt (Operators)'!$L$20=0,'Summary Op Stmt (Operators)'!$L$20=""),"",L32/'Summary Op Stmt (Operators)'!$L$20)
A33: Total Undistributed Expenses | B33: =B28+B29+B30+B31+B32 -> 0 | C33: =IF(OR('Summary Op Stmt (Operators)'!$B$20=0,'Summary Op Stmt (Operators)'!$B$20=""),"",B33/'Summary Op Stmt (Operators)'!$B$20) | D33: =D28+D29+D30+D31+D32 -> 0 | E33: =IF(OR('Summary Op Stmt (Operators)'!$D$20=0,'Summary Op Stmt (Operators)'!$D$20=""),"",D33/'Summary Op Stmt (Operators)'!$D$20) | F33: =F28+F29+F30+F31+F32 -> 0 | G33: =IF(OR('Summary Op Stmt (Operators)'!$F$20=0,'Summary Op Stmt (Operators)'!$F$20=""),"",F33/'Summary Op Stmt (Operators)'!$F$20) | H33: =H28+H29+H30+H31+H32 -> 0 | I33: =IF(OR('Summary Op Stmt (Operators)'!$H$20=0,'Summary Op Stmt (Operators)'!$H$20=""),"",H33/'Summary Op Stmt (Operators)'!$H$20) | J33: =J28+J29+J30+J31+J32 -> 0 | K33: =IF(OR('Summary Op Stmt (Operators)'!$J$20=0,'Summary Op Stmt (Operators)'!$J$20=""),"",J33/'Summary Op Stmt (Operators)'!$J$20) | L33: =L28+L29+L30+L31+L32 -> 0 | M33: =IF(OR('Summary Op Stmt (Operators)'!$L$20=0,'Summary Op Stmt (Operators)'!$L$20=""),"",L33/'Summary Op Stmt (Operators)'!$L$20)
A34: Gross Operating Profit | B34: =B26-B33 -> 0 | C34: =IF(OR('Summary Op Stmt (Operators)'!$B$20=0,'Summary Op Stmt (Operators)'!$B$20=""),"",B34/'Summary Op Stmt (Operators)'!$B$20) | D34: =D26-D33 -> 0 | E34: =IF(OR('Summary Op Stmt (Operators)'!$D$20=0,'Summary Op Stmt (Operators)'!$D$20=""),"",D34/'Summary Op Stmt (Operators)'!$D$20) | F34: =F26-F33 -> 0 | G34: =IF(OR('Summary Op Stmt (Operators)'!$F$20=0,'Summary Op Stmt (Operators)'!$F$20=""),"",F34/'Summary Op Stmt (Operators)'!$F$20) | H34: =H26-H33 -> 0 | I34: =IF(OR('Summary Op Stmt (Operators)'!$H$20=0,'Summary Op Stmt (Operators)'!$H$20=""),"",H34/'Summary Op Stmt (Operators)'!$H$20) | J34: =J26-J33 -> 0 | K34: =IF(OR('Summary Op Stmt (Operators)'!$J$20=0,'Summary Op Stmt (Operators)'!$J$20=""),"",J34/'Summary Op Stmt (Operators)'!$J$20) | L34: =L26-L33 -> 0 | M34: =IF(OR('Summary Op Stmt (Operators)'!$L$20=0,'Summary Op Stmt (Operators)'!$L$20=""),"",L34/'Summary Op Stmt (Operators)'!$L$20)
A35: Management Fees | B35: ='Schedule 10 - Management Fees'!B10 -> 0 | C35: =IF(OR('Summary Op Stmt (Operators)'!$B$20=0,'Summary Op Stmt (Operators)'!$B$20=""),"",B35/'Summary Op Stmt (Operators)'!$B$20) | D35: ='Schedule 10 - Management Fees'!D10 -> 0 | E35: =IF(OR('Summary Op Stmt (Operators)'!$D$20=0,'Summary Op Stmt (Operators)'!$D$20=""),"",D35/'Summary Op Stmt (Operators)'!$D$20) | F35: ='Schedule 10 - Management Fees'!F10 -> 0 | G35: =IF(OR('Summary Op Stmt (Operators)'!$F$20=0,'Summary Op Stmt (Operators)'!$F$20=""),"",F35/'Summary Op Stmt (Operators)'!$F$20) | H35: ='Schedule 10 - Management Fees'!H10 -> 0 | I35: =IF(OR('Summary Op Stmt (Operators)'!$H$20=0,'Summary Op Stmt (Operators)'!$H$20=""),"",H35/'Summary Op Stmt (Operators)'!$H$20) | J35: ='Schedule 10 - Management Fees'!J10 -> 0 | K35: =IF(OR('Summary Op Stmt (Operators)'!$J$20=0,'Summary Op Stmt (Operators)'!$J$20=""),"",J35/'Summary Op Stmt (Operators)'!$J$20) | L35: ='Schedule 10 - Management Fees'!L10 -> 0 | M35: =IF(OR('Summary Op Stmt (Operators)'!$L$20=0,'Summary Op Stmt (Operators)'!$L$20=""),"",L35/'Summary Op Stmt (Operators)'!$L$20)
A36: Income Before Non-Operating Income and Expenses | B36: =B34-B35 -> 0 | C36: =IF(OR('Summary Op Stmt (Operators)'!$B$20=0,'Summary Op Stmt (Operators)'!$B$20=""),"",B36/'Summary Op Stmt (Operators)'!$B$20) | D36: =D34-D35 -> 0 | E36: =IF(OR('Summary Op Stmt (Operators)'!$D$20=0,'Summary Op Stmt (Operators)'!$D$20=""),"",D36/'Summary Op Stmt (Operators)'!$D$20) | F36: =F34-F35 -> 0 | G36: =IF(OR('Summary Op Stmt (Operators)'!$F$20=0,'Summary Op Stmt (Operators)'!$F$20=""),"",F36/'Summary Op Stmt (Operators)'!$F$20) | H36: =H34-H35 -> 0 | I36: =IF(OR('Summary Op Stmt (Operators)'!$H$20=0,'Summary Op Stmt (Operators)'!$H$20=""),"",H36/'Summary Op Stmt (Operators)'!$H$20) | J36: =J34-J35 -> 0 | K36: =IF(OR('Summary Op Stmt (Operators)'!$J$20=0,'Summary Op Stmt (Operators)'!$J$20=""),"",J36/'Summary Op Stmt (Operators)'!$J$20) | L36: =L34-L35 -> 0 | M36: =IF(OR('Summary Op Stmt (Operators)'!$L$20=0,'Summary Op Stmt (Operators)'!$L$20=""),"",L36/'Summary Op Stmt (Operators)'!$L$20)
A37: Non-Operating Income and Expenses
A38: Income | B38: ='Schedule 11 - Non-Operating'!B11 -> 0 | C38: =IF(OR('Summary Op Stmt (Operators)'!$B$20=0,'Summary Op Stmt (Operators)'!$B$20=""),"",B38/'Summary Op Stmt (Operators)'!$B$20) | D38: ='Schedule 11 - Non-Operating'!D11 -> 0 | E38: =IF(OR('Summary Op Stmt (Operators)'!$D$20=0,'Summary Op Stmt (Operators)'!$D$20=""),"",D38/'Summary Op Stmt (Operators)'!$D$20) | F38: ='Schedule 11 - Non-Operating'!F11 -> 0 | G38: =IF(OR('Summary Op Stmt (Operators)'!$F$20=0,'Summary Op Stmt (Operators)'!$F$20=""),"",F38/'Summary Op Stmt (Operators)'!$F$20) | H38: ='Schedule 11 - Non-Operating'!H11 -> 0 | I38: =IF(OR('Summary Op Stmt (Operators)'!$H$20=0,'Summary Op Stmt (Operators)'!$H$20=""),"",H38/'Summary Op Stmt (Operators)'!$H$20) | J38: ='Schedule 11 - Non-Operating'!J11 -> 0 | K38: =IF(OR('Summary Op Stmt (Operators)'!$J$20=0,'Summary Op Stmt (Operators)'!$J$20=""),"",J38/'Summary Op Stmt (Operators)'!$J$20) | L38: ='Schedule 11 - Non-Operating'!L11 -> 0 | M38: =IF(OR('Summary Op Stmt (Operators)'!$L$20=0,'Summary Op Stmt (Operators)'!$L$20=""),"",L38/'Summary Op Stmt (Operators)'!$L$20)
A39: Rent | B39: ='Schedule 11 - Non-Operating'!B15 -> 0 | C39: =IF(OR('Summary Op Stmt (Operators)'!$B$20=0,'Summary Op Stmt (Operators)'!$B$20=""),"",B39/'Summary Op Stmt (Operators)'!$B$20) | D39: ='Schedule 11 - Non-Operating'!D15 -> 0 | E39: =IF(OR('Summary Op Stmt (Operators)'!$D$20=0,'Summary Op Stmt (Operators)'!$D$20=""),"",D39/'Summary Op Stmt (Operators)'!$D$20) | F39: ='Schedule 11 - Non-Operating'!F15 -> 0 | G39: =IF(OR('Summary Op Stmt (Operators)'!$F$20=0,'Summary Op Stmt (Operators)'!$F$20=""),"",F39/'Summary Op Stmt (Operators)'!$F$20) | H39: ='Schedule 11 - Non-Operating'!H15 -> 0 | I39: =IF(OR('Summary Op Stmt (Operators)'!$H$20=0,'Summary Op Stmt (Operators)'!$H$20=""),"",H39/'Summary Op Stmt (Operators)'!$H$20) | J39: ='Schedule 11 - Non-Operating'!J15 -> 0 | K39: =IF(OR('Summary Op Stmt (Operators)'!$J$20=0,'Summary Op Stmt (Operators)'!$J$20=""),"",J39/'Summary Op Stmt (Operators)'!$J$20) | L39: ='Schedule 11 - Non-Operating'!L15 -> 0 | M39: =IF(OR('Summary Op Stmt (Operators)'!$L$20=0,'Summary Op Stmt (Operators)'!$L$20=""),"",L39/'Summary Op Stmt (Operators)'!$L$20)
A40: Property and Other Taxes | B40: ='Schedule 11 - Non-Operating'!B21 -> 0 | C40: =IF(OR('Summary Op Stmt (Operators)'!$B$20=0,'Summary Op Stmt (Operators)'!$B$20=""),"",B40/'Summary Op Stmt (Operators)'!$B$20) | D40: ='Schedule 11 - Non-Operating'!D21 -> 0 | E40: =IF(OR('Summary Op Stmt (Operators)'!$D$20=0,'Summary Op Stmt (Operators)'!$D$20=""),"",D40/'Summary Op Stmt (Operators)'!$D$20) | F40: ='Schedule 11 - Non-Operating'!F21 -> 0 | G40: =IF(OR('Summary Op Stmt (Operators)'!$F$20=0,'Summary Op Stmt (Operators)'!$F$20=""),"",F40/'Summary Op Stmt (Operators)'!$F$20) | H40: ='Schedule 11 - Non-Operating'!H21 -> 0 | I40: =IF(OR('Summary Op Stmt (Operators)'!$H$20=0,'Summary Op Stmt (Operators)'!$H$20=""),"",H40/'Summary Op Stmt (Operators)'!$H$20) | J40: ='Schedule 11 - Non-Operating'!J21 -> 0 | K40: =IF(OR('Summary Op Stmt (Operators)'!$J$20=0,'Summary Op Stmt (Operators)'!$J$20=""),"",J40/'Summary Op Stmt (Operators)'!$J$20) | L40: ='Schedule 11 - Non-Operating'!L21 -> 0 | M40: =IF(OR('Summary Op Stmt (Operators)'!$L$20=0,'Summary Op Stmt (Operators)'!$L$20=""),"",L40/'Summary Op Stmt (Operators)'!$L$20)
A41: Insurance | B41: ='Schedule 11 - Non-Operating'!B26 -> 0 | C41: =IF(OR('Summary Op Stmt (Operators)'!$B$20=0,'Summary Op Stmt (Operators)'!$B$20=""),"",B41/'Summary Op Stmt (Operators)'!$B$20) | D41: ='Schedule 11 - Non-Operating'!D26 -> 0 | E41: =IF(OR('Summary Op Stmt (Operators)'!$D$20=0,'Summary Op Stmt (Operators)'!$D$20=""),"",D41/'Summary Op Stmt (Operators)'!$D$20) | F41: ='Schedule 11 - Non-Operating'!F26 -> 0 | G41: =IF(OR('Summary Op Stmt (Operators)'!$F$20=0,'Summary Op Stmt (Operators)'!$F$20=""),"",F41/'Summary Op Stmt (Operators)'!$F$20) | H41: ='Schedule 11 - Non-Operating'!H26 -> 0 | I41: =IF(OR('Summary Op Stmt (Operators)'!$H$20=0,'Summary Op Stmt (Operators)'!$H$20=""),"",H41/'Summary Op Stmt (Operators)'!$H$20) | J41: ='Schedule 11 - Non-Operating'!J26 -> 0 | K41: =IF(OR('Summary Op Stmt (Operators)'!$J$20=0,'Summary Op Stmt (Operators)'!$J$20=""),"",J41/'Summary Op Stmt (Operators)'!$J$20) | L41: ='Schedule 11 - Non-Operating'!L26 -> 0 | M41: =IF(OR('Summary Op Stmt (Operators)'!$L$20=0,'Summary Op Stmt (Operators)'!$L$20=""),"",L41/'Summary Op Stmt (Operators)'!$L$20)
A42: Other | B42: ='Schedule 11 - Non-Operating'!B32 -> 0 | C42: =IF(OR('Summary Op Stmt (Operators)'!$B$20=0,'Summary Op Stmt (Operators)'!$B$20=""),"",B42/'Summary Op Stmt (Operators)'!$B$20) | D42: ='Schedule 11 - Non-Operating'!D32 -> 0 | E42: =IF(OR('Summary Op Stmt (Operators)'!$D$20=0,'Summary Op Stmt (Operators)'!$D$20=""),"",D42/'Summary Op Stmt (Operators)'!$D$20) | F42: ='Schedule 11 - Non-Operating'!F32 -> 0 | G42: =IF(OR('Summary Op Stmt (Operators)'!$F$20=0,'Summary Op Stmt (Operators)'!$F$20=""),"",F42/'Summary Op Stmt (Operators)'!$F$20) | H42: ='Schedule 11 - Non-Operating'!H32 -> 0 | I42: =IF(OR('Summary Op Stmt (Operators)'!$H$20=0,'Summary Op Stmt (Operators)'!$H$20=""),"",H42/'Summary Op Stmt (Operators)'!$H$20) | J42: ='Schedule 11 - Non-Operating'!J32 -> 0 | K42: =IF(OR('Summary Op Stmt (Operators)'!$J$20=0,'Summary Op Stmt (Operators)'!$J$20=""),"",J42/'Summary Op Stmt (Operators)'!$J$20) | L42: ='Schedule 11 - Non-Operating'!L32 -> 0 | M42: =IF(OR('Summary Op Stmt (Operators)'!$L$20=0,'Summary Op Stmt (Operators)'!$L$20=""),"",L42/'Summary Op Stmt (Operators)'!$L$20)
A43: Total Non-Operating Income and Expenses | B43: =B39+B40+B41+B42-B38 -> 0 | C43: =IF(OR('Summary Op Stmt (Operators)'!$B$20=0,'Summary Op Stmt (Operators)'!$B$20=""),"",B43/'Summary Op Stmt (Operators)'!$B$20) | D43: =D39+D40+D41+D42-D38 -> 0 | E43: =IF(OR('Summary Op Stmt (Operators)'!$D$20=0,'Summary Op Stmt (Operators)'!$D$20=""),"",D43/'Summary Op Stmt (Operators)'!$D$20) | F43: =F39+F40+F41+F42-F38 -> 0 | G43: =IF(OR('Summary Op Stmt (Operators)'!$F$20=0,'Summary Op Stmt (Operators)'!$F$20=""),"",F43/'Summary Op Stmt (Operators)'!$F$20) | H43: =H39+H40+H41+H42-H38 -> 0 | I43: =IF(OR('Summary Op Stmt (Operators)'!$H$20=0,'Summary Op Stmt (Operators)'!$H$20=""),"",H43/'Summary Op Stmt (Operators)'!$H$20) | J43: =J39+J40+J41+J42-J38 -> 0 | K43: =IF(OR('Summary Op Stmt (Operators)'!$J$20=0,'Summary Op Stmt (Operators)'!$J$20=""),"",J43/'Summary Op Stmt (Operators)'!$J$20) | L43: =L39+L40+L41+L42-L38 -> 0 | M43: =IF(OR('Summary Op Stmt (Operators)'!$L$20=0,'Summary Op Stmt (Operators)'!$L$20=""),"",L43/'Summary Op Stmt (Operators)'!$L$20)
A44: Earnings Before Interest, Taxes, Depreciation, and Amortization | B44: =B36-B43 -> 0 | C44: =IF(OR('Summary Op Stmt (Operators)'!$B$20=0,'Summary Op Stmt (Operators)'!$B$20=""),"",B44/'Summary Op Stmt (Operators)'!$B$20) | D44: =D36-D43 -> 0 | E44: =IF(OR('Summary Op Stmt (Operators)'!$D$20=0,'Summary Op Stmt (Operators)'!$D$20=""),"",D44/'Summary Op Stmt (Operators)'!$D$20) | F44: =F36-F43 -> 0 | G44: =IF(OR('Summary Op Stmt (Operators)'!$F$20=0,'Summary Op Stmt (Operators)'!$F$20=""),"",F44/'Summary Op Stmt (Operators)'!$F$20) | H44: =H36-H43 -> 0 | I44: =IF(OR('Summary Op Stmt (Operators)'!$H$20=0,'Summary Op Stmt (Operators)'!$H$20=""),"",H44/'Summary Op Stmt (Operators)'!$H$20) | J44: =J36-J43 -> 0 | K44: =IF(OR('Summary Op Stmt (Operators)'!$J$20=0,'Summary Op Stmt (Operators)'!$J$20=""),"",J44/'Summary Op Stmt (Operators)'!$J$20) | L44: =L36-L43 -> 0 | M44: =IF(OR('Summary Op Stmt (Operators)'!$L$20=0,'Summary Op Stmt (Operators)'!$L$20=""),"",L44/'Summary Op Stmt (Operators)'!$L$20)
A45: Replacement Reserve | C45: =IF(OR('Summary Op Stmt (Operators)'!$B$20=0,'Summary Op Stmt (Operators)'!$B$20=""),"",B45/'Summary Op Stmt (Operators)'!$B$20) | E45: =IF(OR('Summary Op Stmt (Operators)'!$D$20=0,'Summary Op Stmt (Operators)'!$D$20=""),"",D45/'Summary Op Stmt (Operators)'!$D$20) | G45: =IF(OR('Summary Op Stmt (Operators)'!$F$20=0,'Summary Op Stmt (Operators)'!$F$20=""),"",F45/'Summary Op Stmt (Operators)'!$F$20) | I45: =IF(OR('Summary Op Stmt (Operators)'!$H$20=0,'Summary Op Stmt (Operators)'!$H$20=""),"",H45/'Summary Op Stmt (Operators)'!$H$20) | K45: =IF(OR('Summary Op Stmt (Operators)'!$J$20=0,'Summary Op Stmt (Operators)'!$J$20=""),"",J45/'Summary Op Stmt (Operators)'!$J$20) | M45: =IF(OR('Summary Op Stmt (Operators)'!$L$20=0,'Summary Op Stmt (Operators)'!$L$20=""),"",L45/'Summary Op Stmt (Operators)'!$L$20)
A46: EBITDA Less Replacement Reserve | B46: =B44-B45 -> 0 | C46: =IF(OR('Summary Op Stmt (Operators)'!$B$20=0,'Summary Op Stmt (Operators)'!$B$20=""),"",B46/'Summary Op Stmt (Operators)'!$B$20) | D46: =D44-D45 -> 0 | E46: =IF(OR('Summary Op Stmt (Operators)'!$D$20=0,'Summary Op Stmt (Operators)'!$D$20=""),"",D46/'Summary Op Stmt (Operators)'!$D$20) | F46: =F44-F45 -> 0 | G46: =IF(OR('Summary Op Stmt (Operators)'!$F$20=0,'Summary Op Stmt (Operators)'!$F$20=""),"",F46/'Summary Op Stmt (Operators)'!$F$20) | H46: =H44-H45 -> 0 | I46: =IF(OR('Summary Op Stmt (Operators)'!$H$20=0,'Summary Op Stmt (Operators)'!$H$20=""),"",H46/'Summary Op Stmt (Operators)'!$H$20) | J46: =J44-J45 -> 0 | K46: =IF(OR('Summary Op Stmt (Operators)'!$J$20=0,'Summary Op Stmt (Operators)'!$J$20=""),"",J46/'Summary Op Stmt (Operators)'!$J$20) | L46: =L44-L45 -> 0 | M46: =IF(OR('Summary Op Stmt (Operators)'!$L$20=0,'Summary Op Stmt (Operators)'!$L$20=""),"",L46/'Summary Op Stmt (Operators)'!$L$20)

Sheet Summary Op Stmt (Owners)
A1: SUMMARY OPERATING STATEMENT [For Owners]
A2: Property: | B2: ='Setup & Assumptions'!$B$4 -> Enter property name | H2: Period / Year: | J2: ='Setup & Assumptions'!$B$5 -> e.g. January 2026 / FY2026
A3: Bottom line: Net Income. Revenue/expense % is of Total Operating Revenue; departmental expense % is of departmental revenue.
B4: Current Period | H4: Year-To-Date
B5: Actual | D5: Forecast / Budget | F5: Prior Year | H5: Actual | J5: Forecast / Budget | L5: Prior Year
A6: Line Item | B6: $ | C6: % | D6: $ | E6: % | F6: $ | G6: % | H6: $ | I6: % | J6: $ | K6: % | L6: $ | M6: %
A7: Operating Statistics
A8: Rooms Available
A9: Rooms Sold
A10: Occupancy % | B10: =IF(B8=0,"",B9/B8) | D10: =IF(D8=0,"",D9/D8) | F10: =IF(F8=0,"",F9/F8) | H10: =IF(H8=0,"",H9/H8) | J10: =IF(J8=0,"",J9/J8) | L10: =IF(L8=0,"",L9/L8)
A11: ADR (Average Daily Rate) | B11: =IF(B9=0,"",B16/B9) | D11: =IF(D9=0,"",D16/D9) | F11: =IF(F9=0,"",F16/F9) | H11: =IF(H9=0,"",H16/H9) | J11: =IF(J9=0,"",J16/J9) | L11: =IF(L9=0,"",L16/L9)
A12: Rooms RevPAR | B12: =IF(B8=0,"",B16/B8) | D12: =IF(D8=0,"",D16/D8) | F12: =IF(F8=0,"",F16/F8) | H12: =IF(H8=0,"",H16/H8) | J12: =IF(J8=0,"",J16/J8) | L12: =IF(L8=0,"",L16/L8)
A13: Total RevPAR | B13: =IF(B8=0,"",B20/B8) | D13: =IF(D8=0,"",D20/D8) | F13: =IF(F8=0,"",F20/F8) | H13: =IF(H8=0,"",H20/H8) | J13: =IF(J8=0,"",J20/J8) | L13: =IF(L8=0,"",L20/L8)
A15: Operating Revenue
A16: Rooms | B16: ='Schedule 1 - Rooms'!B25 -> 0 | C16: =IF(OR('Summary Op Stmt (Operators)'!$B$20=0,'Summary Op Stmt (Operators)'!$B$20=""),"",B16/'Summary Op Stmt (Operators)'!$B$20) | D16: ='Schedule 1 - Rooms'!D25 -> 0 | E16: =IF(OR('Summary Op Stmt (Operators)'!$D$20=0,'Summary Op Stmt (Operators)'!$D$20=""),"",D16/'Summary Op Stmt (Operators)'!$D$20) | F16: ='Schedule 1 - Rooms'!F25 -> 0 | G16: =IF(OR('Summary Op Stmt (Operators)'!$F$20=0,'Summary Op Stmt (Operators)'!$F$20=""),"",F16/'Summary Op Stmt (Operators)'!$F$20) | H16: ='Schedule 1 - Rooms'!H25 -> 0 | I16: =IF(OR('Summary Op Stmt (Operators)'!$H$20=0,'Summary Op Stmt (Operators)'!$H$20=""),"",H16/'Summary Op Stmt (Operators)'!$H$20) | J16: ='Schedule 1 - Rooms'!J25 -> 0 | K16: =IF(OR('Summary Op Stmt (Operators)'!$J$20=0,'Summary Op Stmt (Operators)'!$J$20=""),"",J16/'Summary Op Stmt (Operators)'!$J$20) | L16: ='Schedule 1 - Rooms'!L25 -> 0 | M16: =IF(OR('Summary Op Stmt (Operators)'!$L$20=0,'Summary Op Stmt (Operators)'!$L$20=""),"",L16/'Summary Op Stmt (Operators)'!$L$20)
A17: Food and Beverage | B17: ='Schedule 2 - Food & Beverage'!B32 -> 0 | C17: =IF(OR('Summary Op Stmt (Operators)'!$B$20=0,'Summary Op Stmt (Operators)'!$B$20=""),"",B17/'Summary Op Stmt (Operators)'!$B$20) | D17: ='Schedule 2 - Food & Beverage'!D32 -> 0 | E17: =IF(OR('Summary Op Stmt (Operators)'!$D$20=0,'Summary Op Stmt (Operators)'!$D$20=""),"",D17/'Summary Op Stmt (Operators)'!$D$20) | F17: ='Schedule 2 - Food & Beverage'!F32 -> 0 | G17: =IF(OR('Summary Op Stmt (Operators)'!$F$20=0,'Summary Op Stmt (Operators)'!$F$20=""),"",F17/'Summary Op Stmt (Operators)'!$F$20) | H17: ='Schedule 2 - Food & Beverage'!H32 -> 0 | I17: =IF(OR('Summary Op Stmt (Operators)'!$H$20=0,'Summary Op Stmt (Operators)'!$H$20=""),"",H17/'Summary Op Stmt (Operators)'!$H$20) | J17: ='Schedule 2 - Food & Beverage'!J32 -> 0 | K17: =IF(OR('Summary Op Stmt (Operators)'!$J$20=0,'Summary Op Stmt (Operators)'!$J$20=""),"",J17/'Summary Op Stmt (Operators)'!$J$20) | L17: ='Schedule 2 - Food & Beverage'!L32 -> 0 | M17: =IF(OR('Summary Op Stmt (Operators)'!$L$20=0,'Summary Op Stmt (Operators)'!$L$20=""),"",L17/'Summary Op Stmt (Operators)'!$L$20)
A18: Other Operated Departments | B18: ='Schedule 3 - Other Op Depts'!B13 -> 0 | C18: =IF(OR('Summary Op Stmt (Operators)'!$B$20=0,'Summary Op Stmt (Operators)'!$B$20=""),"",B18/'Summary Op Stmt (Operators)'!$B$20) | D18: ='Schedule 3 - Other Op Depts'!D13 -> 0 | E18: =IF(OR('Summary Op Stmt (Operators)'!$D$20=0,'Summary Op Stmt (Operators)'!$D$20=""),"",D18/'Summary Op Stmt (Operators)'!$D$20) | F18: ='Schedule 3 - Other Op Depts'!F13 -> 0 | G18: =IF(OR('Summary Op Stmt (Operators)'!$F$20=0,'Summary Op Stmt (Operators)'!$F$20=""),"",F18/'Summary Op Stmt (Operators)'!$F$20) | H18: ='Schedule 3 - Other Op Depts'!H13 -> 0 | I18: =IF(OR('Summary Op Stmt (Operators)'!$H$20=0,'Summary Op Stmt (Operators)'!$H$20=""),"",H18/'Summary Op Stmt (Operators)'!$H$20) | J18: ='Schedule 3 - Other Op Depts'!J13 -> 0 | K18: =IF(OR('Summary Op Stmt (Operators)'!$J$20=0,'Summary Op Stmt (Operators)'!$J$20=""),"",J18/'Summary Op Stmt (Operators)'!$J$20) | L18: ='Schedule 3 - Other Op Depts'!L13 -> 0 | M18: =IF(OR('Summary Op Stmt (Operators)'!$L$20=0,'Summary Op Stmt (Operators)'!$L$20=""),"",L18/'Summary Op Stmt (Operators)'!$L$20)
A19: Miscellaneous Income | B19: ='Schedule 4 - Misc Income'!B22 -> 0 | C19: =IF(OR('Summary Op Stmt (Operators)'!$B$20=0,'Summary Op Stmt (Operators)'!$B$20=""),"",B19/'Summary Op Stmt (Operators)'!$B$20) | D19: ='Schedule 4 - Misc Income'!D22 -> 0 | E19: =IF(OR('Summary Op Stmt (Operators)'!$D$20=0,'Summary Op Stmt (Operators)'!$D$20=""),"",D19/'Summary Op Stmt (Operators)'!$D$20) | F19: ='Schedule 4 - Misc Income'!F22 -> 0 | G19: =IF(OR('Summary Op Stmt (Operators)'!$F$20=0,'Summary Op Stmt (Operators)'!$F$20=""),"",F19/'Summary Op Stmt (Operators)'!$F$20) | H19: ='Schedule 4 - Misc Income'!H22 -> 0 | I19: =IF(OR('Summary Op Stmt (Operators)'!$H$20=0,'Summary Op Stmt (Operators)'!$H$20=""),"",H19/'Summary Op Stmt (Operators)'!$H$20) | J19: ='Schedule 4 - Misc Income'!J22 -> 0 | K19: =IF(OR('Summary Op Stmt (Operators)'!$J$20=0,'Summary Op Stmt (Operators)'!$J$20=""),"",J19/'Summary Op Stmt (Operators)'!$J$20) | L19: ='Schedule 4 - Misc Income'!L22 -> 0 | M19: =IF(OR('Summary Op Stmt (Operators)'!$L$20=0,'Summary Op Stmt (Operators)'!$L$20=""),"",L19/'Summary Op Stmt (Operators)'!$L$20)
A20: Total Operating Revenue | B20: =B16+B17+B18+B19 -> 0 | C20: =IF(OR('Summary Op Stmt (Operators)'!$B$20=0,'Summary Op Stmt (Operators)'!$B$20=""),"",B20/'Summary Op Stmt (Operators)'!$B$20) | D20: =D16+D17+D18+D19 -> 0 | E20: =IF(OR('Summary Op Stmt (Operators)'!$D$20=0,'Summary Op Stmt (Operators)'!$D$20=""),"",D20/'Summary Op Stmt (Operators)'!$D$20) | F20: =F16+F17+F18+F19 -> 0 | G20: =IF(OR('Summary Op Stmt (Operators)'!$F$20=0,'Summary Op Stmt (Operators)'!$F$20=""),"",F20/'Summary Op Stmt (Operators)'!$F$20) | H20: =H16+H17+H18+H19 -> 0 | I20: =IF(OR('Summary Op Stmt (Operators)'!$H$20=0,'Summary Op Stmt (Operators)'!$H$20=""),"",H20/'Summary Op Stmt (Operators)'!$H$20) | J20: =J16+J17+J18+J19 -> 0 | K20: =IF(OR('Summary Op Stmt (Operators)'!$J$20=0,'Summary Op Stmt (Operators)'!$J$20=""),"",J20/'Summary Op Stmt (Operators)'!$J$20) | L20: =L16+L17+L18+L19 -> 0 | M20: =IF(OR('Summary Op Stmt (Operators)'!$L$20=0,'Summary Op Stmt (Operators)'!$L$20=""),"",L20/'Summary Op Stmt (Operators)'!$L$20)
A21: Departmental Expenses
A22: Rooms | B22: ='Schedule 1 - Rooms'!B81 -> 0 | C22: =IF(OR(B16=0,B16=""),"",B22/B16) | D22: ='Schedule 1 - Rooms'!D81 -> 0 | E22: =IF(OR(D16=0,D16=""),"",D22/D16) | F22: ='Schedule 1 - Rooms'!F81 -> 0 | G22: =IF(OR(F16=0,F16=""),"",F22/F16) | H22: ='Schedule 1 - Rooms'!H81 -> 0 | I22: =IF(OR(H16=0,H16=""),"",H22/H16) | J22: ='Schedule 1 - Rooms'!J81 -> 0 | K22: =IF(OR(J16=0,J16=""),"",J22/J16) | L22: ='Schedule 1 - Rooms'!L81 -> 0 | M22: =IF(OR(L16=0,L16=""),"",L22/L16)
A23: Food and Beverage | B23: ='Schedule 2 - Food & Beverage'!B42+'Schedule 2 - Food & Beverage'!B105 -> 0 | C23: =IF(OR(B17=0,B17=""),"",B23/B17) | D23: ='Schedule 2 - Food & Beverage'!D42+'Schedule 2 - Food & Beverage'!D105 -> 0 | E23: =IF(OR(D17=0,D17=""),"",D23/D17) | F23: ='Schedule 2 - Food & Beverage'!F42+'Schedule 2 - Food & Beverage'!F105 -> 0 | G23: =IF(OR(F17=0,F17=""),"",F23/F17) | H23: ='Schedule 2 - Food & Beverage'!H42+'Schedule 2 - Food & Beverage'!H105 -> 0 | I23: =IF(OR(H17=0,H17=""),"",H23/H17) | J23: ='Schedule 2 - Food & Beverage'!J42+'Schedule 2 - Food & Beverage'!J105 -> 0 | K23: =IF(OR(J17=0,J17=""),"",J23/J17) | L23: ='Schedule 2 - Food & Beverage'!L42+'Schedule 2 - Food & Beverage'!L105 -> 0 | M23: =IF(OR(L17=0,L17=""),"",L23/L17)
A24: Other Operated Departments | B24: ='Schedule 3 - Other Op Depts'!B20 -> 0 | C24: =IF(OR(B18=0,B18=""),"",B24/B18) | D24: ='Schedule 3 - Other Op Depts'!D20 -> 0 | E24: =IF(OR(D18=0,D18=""),"",D24/D18) | F24: ='Schedule 3 - Other Op Depts'!F20 -> 0 | G24: =IF(OR(F18=0,F18=""),"",F24/F18) | H24: ='Schedule 3 - Other Op Depts'!H20 -> 0 | I24: =IF(OR(H18=0,H18=""),"",H24/H18) | J24: ='Schedule 3 - Other Op Depts'!J20 -> 0 | K24: =IF(OR(J18=0,J18=""),"",J24/J18) | L24: ='Schedule 3 - Other Op Depts'!L20 -> 0 | M24: =IF(OR(L18=0,L18=""),"",L24/L18)
A25: Total Departmental Expenses | B25: =B22+B23+B24 -> 0 | C25: =IF(OR('Summary Op Stmt (Operators)'!$B$20=0,'Summary Op Stmt (Operators)'!$B$20=""),"",B25/'Summary Op Stmt (Operators)'!$B$20) | D25: =D22+D23+D24 -> 0 | E25: =IF(OR('Summary Op Stmt (Operators)'!$D$20=0,'Summary Op Stmt (Operators)'!$D$20=""),"",D25/'Summary Op Stmt (Operators)'!$D$20) | F25: =F22+F23+F24 -> 0 | G25: =IF(OR('Summary Op Stmt (Operators)'!$F$20=0,'Summary Op Stmt (Operators)'!$F$20=""),"",F25/'Summary Op Stmt (Operators)'!$F$20) | H25: =H22+H23+H24 -> 0 | I25: =IF(OR('Summary Op Stmt (Operators)'!$H$20=0,'Summary Op Stmt (Operators)'!$H$20=""),"",H25/'Summary Op Stmt (Operators)'!$H$20) | J25: =J22+J23+J24 -> 0 | K25: =IF(OR('Summary Op Stmt (Operators)'!$J$20=0,'Summary Op Stmt (Operators)'!$J$20=""),"",J25/'Summary Op Stmt (Operators)'!$J$20) | L25: =L22+L23+L24 -> 0 | M25: =IF(OR('Summary Op Stmt (Operators)'!$L$20=0,'Summary Op Stmt (Operators)'!$L$20=""),"",L25/'Summary Op Stmt (Operators)'!$L$20)
A26: Total Departmental Profit | B26: =B20-B25 -> 0 | C26: =IF(OR('Summary Op Stmt (Operators)'!$B$20=0,'Summary Op Stmt (Operators)'!$B$20=""),"",B26/'Summary Op Stmt (Operators)'!$B$20) | D26: =D20-D25 -> 0 | E26: =IF(OR('Summary Op Stmt (Operators)'!$D$20=0,'Summary Op Stmt (Operators)'!$D$20=""),"",D26/'Summary Op Stmt (Operators)'!$D$20) | F26: =F20-F25 -> 0 | G26: =IF(OR('Summary Op Stmt (Operators)'!$F$20=0,'Summary Op Stmt (Operators)'!$F$20=""),"",F26/'Summary Op Stmt (Operators)'!$F$20) | H26: =H20-H25 -> 0 | I26: =IF(OR('Summary Op Stmt (Operators)'!$H$20=0,'Summary Op Stmt (Operators)'!$H$20=""),"",H26/'Summary Op Stmt (Operators)'!$H$20) | J26: =J20-J25 -> 0 | K26: =IF(OR('Summary Op Stmt (Operators)'!$J$20=0,'Summary Op Stmt (Operators)'!$J$20=""),"",J26/'Summary Op Stmt (Operators)'!$J$20) | L26: =L20-L25 -> 0 | M26: =IF(OR('Summary Op Stmt (Operators)'!$L$20=0,'Summary Op Stmt (Operators)'!$L$20=""),"",L26/'Summary Op Stmt (Operators)'!$L$20)
A27: Undistributed Operating Expenses
A28: Administrative and General | B28: ='Schedule 5 - Admin & General'!B65 -> 0 | C28: =IF(OR('Summary Op Stmt (Operators)'!$B$20=0,'Summary Op Stmt (Operators)'!$B$20=""),"",B28/'Summary Op Stmt (Operators)'!$B$20) | D28: ='Schedule 5 - Admin & General'!D65 -> 0 | E28: =IF(OR('Summary Op Stmt (Operators)'!$D$20=0,'Summary Op Stmt (Operators)'!$D$20=""),"",D28/'Summary Op Stmt (Operators)'!$D$20) | F28: ='Schedule 5 - Admin & General'!F65 -> 0 | G28: =IF(OR('Summary Op Stmt (Operators)'!$F$20=0,'Summary Op Stmt (Operators)'!$F$20=""),"",F28/'Summary Op Stmt (Operators)'!$F$20) | H28: ='Schedule 5 - Admin & General'!H65 -> 0 | I28: =IF(OR('Summary Op Stmt (Operators)'!$H$20=0,'Summary Op Stmt (Operators)'!$H$20=""),"",H28/'Summary Op Stmt (Operators)'!$H$20) | J28: ='Schedule 5 - Admin & General'!J65 -> 0 | K28: =IF(OR('Summary Op Stmt (Operators)'!$J$20=0,'Summary Op Stmt (Operators)'!$J$20=""),"",J28/'Summary Op Stmt (Operators)'!$J$20) | L28: ='Schedule 5 - Admin & General'!L65 -> 0 | M28: =IF(OR('Summary Op Stmt (Operators)'!$L$20=0,'Summary Op Stmt (Operators)'!$L$20=""),"",L28/'Summary Op Stmt (Operators)'!$L$20)
A29: Information and Telecommunications Systems | B29: ='Schedule 6 - Info & Telecom'!B68 -> 0 | C29: =IF(OR('Summary Op Stmt (Operators)'!$B$20=0,'Summary Op Stmt (Operators)'!$B$20=""),"",B29/'Summary Op Stmt (Operators)'!$B$20) | D29: ='Schedule 6 - Info & Telecom'!D68 -> 0 | E29: =IF(OR('Summary Op Stmt (Operators)'!$D$20=0,'Summary Op Stmt (Operators)'!$D$20=""),"",D29/'Summary Op Stmt (Operators)'!$D$20) | F29: ='Schedule 6 - Info & Telecom'!F68 -> 0 | G29: =IF(OR('Summary Op Stmt (Operators)'!$F$20=0,'Summary Op Stmt (Operators)'!$F$20=""),"",F29/'Summary Op Stmt (Operators)'!$F$20) | H29: ='Schedule 6 - Info & Telecom'!H68 -> 0 | I29: =IF(OR('Summary Op Stmt (Operators)'!$H$20=0,'Summary Op Stmt (Operators)'!$H$20=""),"",H29/'Summary Op Stmt (Operators)'!$H$20) | J29: ='Schedule 6 - Info & Telecom'!J68 -> 0 | K29: =IF(OR('Summary Op Stmt (Operators)'!$J$20=0,'Summary Op Stmt (Operators)'!$J$20=""),"",J29/'Summary Op Stmt (Operators)'!$J$20) | L29: ='Schedule 6 - Info & Telecom'!L68 -> 0 | M29: =IF(OR('Summary Op Stmt (Operators)'!$L$20=0,'Summary Op Stmt (Operators)'!$L$20=""),"",L29/'Summary Op Stmt (Operators)'!$L$20)
A30: Sales and Marketing | B30: ='Schedule 7 - Sales & Marketing'!B57 -> 0 | C30: =IF(OR('Summary Op Stmt (Operators)'!$B$20=0,'Summary Op Stmt (Operators)'!$B$20=""),"",B30/'Summary Op Stmt (Operators)'!$B$20) | D30: ='Schedule 7 - Sales & Marketing'!D57 -> 0 | E30: =IF(OR('Summary Op Stmt (Operators)'!$D$20=0,'Summary Op Stmt (Operators)'!$D$20=""),"",D30/'Summary Op Stmt (Operators)'!$D$20) | F30: ='Schedule 7 - Sales & Marketing'!F57 -> 0 | G30: =IF(OR('Summary Op Stmt (Operators)'!$F$20=0,'Summary Op Stmt (Operators)'!$F$20=""),"",F30/'Summary Op Stmt (Operators)'!$F$20) | H30: ='Schedule 7 - Sales & Marketing'!H57 -> 0 | I30: =IF(OR('Summary Op Stmt (Operators)'!$H$20=0,'Summary Op Stmt (Operators)'!$H$20=""),"",H30/'Summary Op Stmt (Operators)'!$H$20) | J30: ='Schedule 7 - Sales & Marketing'!J57 -> 0 | K30: =IF(OR('Summary Op Stmt (Operators)'!$J$20=0,'Summary Op Stmt (Operators)'!$J$20=""),"",J30/'Summary Op Stmt (Operators)'!$J$20) | L30: ='Schedule 7 - Sales & Marketing'!L57 -> 0 | M30: =IF(OR('Summary Op Stmt (Operators)'!$L$20=0,'Summary Op Stmt (Operators)'!$L$20=""),"",L30/'Summary Op Stmt (Operators)'!$L$20)
A31: Property Operation and Maintenance | B31: ='Schedule 8 - Prop Op & Maint'!B57 -> 0 | C31: =IF(OR('Summary Op Stmt (Operators)'!$B$20=0,'Summary Op Stmt (Operators)'!$B$20=""),"",B31/'Summary Op Stmt (Operators)'!$B$20) | D31: ='Schedule 8 - Prop Op & Maint'!D57 -> 0 | E31: =IF(OR('Summary Op Stmt (Operators)'!$D$20=0,'Summary Op Stmt (Operators)'!$D$20=""),"",D31/'Summary Op Stmt (Operators)'!$D$20) | F31: ='Schedule 8 - Prop Op & Maint'!F57 -> 0 | G31: =IF(OR('Summary Op Stmt (Operators)'!$F$20=0,'Summary Op Stmt (Operators)'!$F$20=""),"",F31/'Summary Op Stmt (Operators)'!$F$20) | H31: ='Schedule 8 - Prop Op & Maint'!H57 -> 0 | I31: =IF(OR('Summary Op Stmt (Operators)'!$H$20=0,'Summary Op Stmt (Operators)'!$H$20=""),"",H31/'Summary Op Stmt (Operators)'!$H$20) | J31: ='Schedule 8 - Prop Op & Maint'!J57 -> 0 | K31: =IF(OR('Summary Op Stmt (Operators)'!$J$20=0,'Summary Op Stmt (Operators)'!$J$20=""),"",J31/'Summary Op Stmt (Operators)'!$J$20) | L31: ='Schedule 8 - Prop Op & Maint'!L57 -> 0 | M31: =IF(OR('Summary Op Stmt (Operators)'!$L$20=0,'Summary Op Stmt (Operators)'!$L$20=""),"",L31/'Summary Op Stmt (Operators)'!$L$20)
A32: Utilities | B32: ='Schedule 9 - Utilities'!B16 -> 0 | C32: =IF(OR('Summary Op Stmt (Operators)'!$B$20=0,'Summary Op Stmt (Operators)'!$B$20=""),"",B32/'Summary Op Stmt (Operators)'!$B$20) | D32: ='Schedule 9 - Utilities'!D16 -> 0 | E32: =IF(OR('Summary Op Stmt (Operators)'!$D$20=0,'Summary Op Stmt (Operators)'!$D$20=""),"",D32/'Summary Op Stmt (Operators)'!$D$20) | F32: ='Schedule 9 - Utilities'!F16 -> 0 | G32: =IF(OR('Summary Op Stmt (Operators)'!$F$20=0,'Summary Op Stmt (Operators)'!$F$20=""),"",F32/'Summary Op Stmt (Operators)'!$F$20) | H32: ='Schedule 9 - Utilities'!H16 -> 0 | I32: =IF(OR('Summary Op Stmt (Operators)'!$H$20=0,'Summary Op Stmt (Operators)'!$H$20=""),"",H32/'Summary Op Stmt (Operators)'!$H$20) | J32: ='Schedule 9 - Utilities'!J16 -> 0 | K32: =IF(OR('Summary Op Stmt (Operators)'!$J$20=0,'Summary Op Stmt (Operators)'!$J$20=""),"",J32/'Summary Op Stmt (Operators)'!$J$20) | L32: ='Schedule 9 - Utilities'!L16 -> 0 | M32: =IF(OR('Summary Op Stmt (Operators)'!$L$20=0,'Summary Op Stmt (Operators)'!$L$20=""),"",L32/'Summary Op Stmt (Operators)'!$L$20)
A33: Total Undistributed Expenses | B33: =B28+B29+B30+B31+B32 -> 0 | C33: =IF(OR('Summary Op Stmt (Operators)'!$B$20=0,'Summary Op Stmt (Operators)'!$B$20=""),"",B33/'Summary Op Stmt (Operators)'!$B$20) | D33: =D28+D29+D30+D31+D32 -> 0 | E33: =IF(OR('Summary Op Stmt (Operators)'!$D$20=0,'Summary Op Stmt (Operators)'!$D$20=""),"",D33/'Summary Op Stmt (Operators)'!$D$20) | F33: =F28+F29+F30+F31+F32 -> 0 | G33: =IF(OR('Summary Op Stmt (Operators)'!$F$20=0,'Summary Op Stmt (Operators)'!$F$20=""),"",F33/'Summary Op Stmt (Operators)'!$F$20) | H33: =H28+H29+H30+H31+H32 -> 0 | I33: =IF(OR('Summary Op Stmt (Operators)'!$H$20=0,'Summary Op Stmt (Operators)'!$H$20=""),"",H33/'Summary Op Stmt (Operators)'!$H$20) | J33: =J28+J29+J30+J31+J32 -> 0 | K33: =IF(OR('Summary Op Stmt (Operators)'!$J$20=0,'Summary Op Stmt (Operators)'!$J$20=""),"",J33/'Summary Op Stmt (Operators)'!$J$20) | L33: =L28+L29+L30+L31+L32 -> 0 | M33: =IF(OR('Summary Op Stmt (Operators)'!$L$20=0,'Summary Op Stmt (Operators)'!$L$20=""),"",L33/'Summary Op Stmt (Operators)'!$L$20)
A34: Gross Operating Profit | B34: =B26-B33 -> 0 | C34: =IF(OR('Summary Op Stmt (Operators)'!$B$20=0,'Summary Op Stmt (Operators)'!$B$20=""),"",B34/'Summary Op Stmt (Operators)'!$B$20) | D34: =D26-D33 -> 0 | E34: =IF(OR('Summary Op Stmt (Operators)'!$D$20=0,'Summary Op Stmt (Operators)'!$D$20=""),"",D34/'Summary Op Stmt (Operators)'!$D$20) | F34: =F26-F33 -> 0 | G34: =IF(OR('Summary Op Stmt (Operators)'!$F$20=0,'Summary Op Stmt (Operators)'!$F$20=""),"",F34/'Summary Op Stmt (Operators)'!$F$20) | H34: =H26-H33 -> 0 | I34: =IF(OR('Summary Op Stmt (Operators)'!$H$20=0,'Summary Op Stmt (Operators)'!$H$20=""),"",H34/'Summary Op Stmt (Operators)'!$H$20) | J34: =J26-J33 -> 0 | K34: =IF(OR('Summary Op Stmt (Operators)'!$J$20=0,'Summary Op Stmt (Operators)'!$J$20=""),"",J34/'Summary Op Stmt (Operators)'!$J$20) | L34: =L26-L33 -> 0 | M34: =IF(OR('Summary Op Stmt (Operators)'!$L$20=0,'Summary Op Stmt (Operators)'!$L$20=""),"",L34/'Summary Op Stmt (Operators)'!$L$20)
A35: Management Fees | B35: ='Schedule 10 - Management Fees'!B10 -> 0 | C35: =IF(OR('Summary Op Stmt (Operators)'!$B$20=0,'Summary Op Stmt (Operators)'!$B$20=""),"",B35/'Summary Op Stmt (Operators)'!$B$20) | D35: ='Schedule 10 - Management Fees'!D10 -> 0 | E35: =IF(OR('Summary Op Stmt (Operators)'!$D$20=0,'Summary Op Stmt (Operators)'!$D$20=""),"",D35/'Summary Op Stmt (Operators)'!$D$20) | F35: ='Schedule 10 - Management Fees'!F10 -> 0 | G35: =IF(OR('Summary Op Stmt (Operators)'!$F$20=0,'Summary Op Stmt (Operators)'!$F$20=""),"",F35/'Summary Op Stmt (Operators)'!$F$20) | H35: ='Schedule 10 - Management Fees'!H10 -> 0 | I35: =IF(OR('Summary Op Stmt (Operators)'!$H$20=0,'Summary Op Stmt (Operators)'!$H$20=""),"",H35/'Summary Op Stmt (Operators)'!$H$20) | J35: ='Schedule 10 - Management Fees'!J10 -> 0 | K35: =IF(OR('Summary Op Stmt (Operators)'!$J$20=0,'Summary Op Stmt (Operators)'!$J$20=""),"",J35/'Summary Op Stmt (Operators)'!$J$20) | L35: ='Schedule 10 - Management Fees'!L10 -> 0 | M35: =IF(OR('Summary Op Stmt (Operators)'!$L$20=0,'Summary Op Stmt (Operators)'!$L$20=""),"",L35/'Summary Op Stmt (Operators)'!$L$20)
A36: Income Before Non-Operating Income and Expenses | B36: =B34-B35 -> 0 | C36: =IF(OR('Summary Op Stmt (Operators)'!$B$20=0,'Summary Op Stmt (Operators)'!$B$20=""),"",B36/'Summary Op Stmt (Operators)'!$B$20) | D36: =D34-D35 -> 0 | E36: =IF(OR('Summary Op Stmt (Operators)'!$D$20=0,'Summary Op Stmt (Operators)'!$D$20=""),"",D36/'Summary Op Stmt (Operators)'!$D$20) | F36: =F34-F35 -> 0 | G36: =IF(OR('Summary Op Stmt (Operators)'!$F$20=0,'Summary Op Stmt (Operators)'!$F$20=""),"",F36/'Summary Op Stmt (Operators)'!$F$20) | H36: =H34-H35 -> 0 | I36: =IF(OR('Summary Op Stmt (Operators)'!$H$20=0,'Summary Op Stmt (Operators)'!$H$20=""),"",H36/'Summary Op Stmt (Operators)'!$H$20) | J36: =J34-J35 -> 0 | K36: =IF(OR('Summary Op Stmt (Operators)'!$J$20=0,'Summary Op Stmt (Operators)'!$J$20=""),"",J36/'Summary Op Stmt (Operators)'!$J$20) | L36: =L34-L35 -> 0 | M36: =IF(OR('Summary Op Stmt (Operators)'!$L$20=0,'Summary Op Stmt (Operators)'!$L$20=""),"",L36/'Summary Op Stmt (Operators)'!$L$20)
A37: Non-Operating Income and Expenses
A38: Income | B38: ='Schedule 11 - Non-Operating'!B11 -> 0 | C38: =IF(OR('Summary Op Stmt (Operators)'!$B$20=0,'Summary Op Stmt (Operators)'!$B$20=""),"",B38/'Summary Op Stmt (Operators)'!$B$20) | D38: ='Schedule 11 - Non-Operating'!D11 -> 0 | E38: =IF(OR('Summary Op Stmt (Operators)'!$D$20=0,'Summary Op Stmt (Operators)'!$D$20=""),"",D38/'Summary Op Stmt (Operators)'!$D$20) | F38: ='Schedule 11 - Non-Operating'!F11 -> 0 | G38: =IF(OR('Summary Op Stmt (Operators)'!$F$20=0,'Summary Op Stmt (Operators)'!$F$20=""),"",F38/'Summary Op Stmt (Operators)'!$F$20) | H38: ='Schedule 11 - Non-Operating'!H11 -> 0 | I38: =IF(OR('Summary Op Stmt (Operators)'!$H$20=0,'Summary Op Stmt (Operators)'!$H$20=""),"",H38/'Summary Op Stmt (Operators)'!$H$20) | J38: ='Schedule 11 - Non-Operating'!J11 -> 0 | K38: =IF(OR('Summary Op Stmt (Operators)'!$J$20=0,'Summary Op Stmt (Operators)'!$J$20=""),"",J38/'Summary Op Stmt (Operators)'!$J$20) | L38: ='Schedule 11 - Non-Operating'!L11 -> 0 | M38: =IF(OR('Summary Op Stmt (Operators)'!$L$20=0,'Summary Op Stmt (Operators)'!$L$20=""),"",L38/'Summary Op Stmt (Operators)'!$L$20)
A39: Rent | B39: ='Schedule 11 - Non-Operating'!B15 -> 0 | C39: =IF(OR('Summary Op Stmt (Operators)'!$B$20=0,'Summary Op Stmt (Operators)'!$B$20=""),"",B39/'Summary Op Stmt (Operators)'!$B$20) | D39: ='Schedule 11 - Non-Operating'!D15 -> 0 | E39: =IF(OR('Summary Op Stmt (Operators)'!$D$20=0,'Summary Op Stmt (Operators)'!$D$20=""),"",D39/'Summary Op Stmt (Operators)'!$D$20) | F39: ='Schedule 11 - Non-Operating'!F15 -> 0 | G39: =IF(OR('Summary Op Stmt (Operators)'!$F$20=0,'Summary Op Stmt (Operators)'!$F$20=""),"",F39/'Summary Op Stmt (Operators)'!$F$20) | H39: ='Schedule 11 - Non-Operating'!H15 -> 0 | I39: =IF(OR('Summary Op Stmt (Operators)'!$H$20=0,'Summary Op Stmt (Operators)'!$H$20=""),"",H39/'Summary Op Stmt (Operators)'!$H$20) | J39: ='Schedule 11 - Non-Operating'!J15 -> 0 | K39: =IF(OR('Summary Op Stmt (Operators)'!$J$20=0,'Summary Op Stmt (Operators)'!$J$20=""),"",J39/'Summary Op Stmt (Operators)'!$J$20) | L39: ='Schedule 11 - Non-Operating'!L15 -> 0 | M39: =IF(OR('Summary Op Stmt (Operators)'!$L$20=0,'Summary Op Stmt (Operators)'!$L$20=""),"",L39/'Summary Op Stmt (Operators)'!$L$20)
A40: Property and Other Taxes | B40: ='Schedule 11 - Non-Operating'!B21 -> 0 | C40: =IF(OR('Summary Op Stmt (Operators)'!$B$20=0,'Summary Op Stmt (Operators)'!$B$20=""),"",B40/'Summary Op Stmt (Operators)'!$B$20) | D40: ='Schedule 11 - Non-Operating'!D21 -> 0 | E40: =IF(OR('Summary Op Stmt (Operators)'!$D$20=0,'Summary Op Stmt (Operators)'!$D$20=""),"",D40/'Summary Op Stmt (Operators)'!$D$20) | F40: ='Schedule 11 - Non-Operating'!F21 -> 0 | G40: =IF(OR('Summary Op Stmt (Operators)'!$F$20=0,'Summary Op Stmt (Operators)'!$F$20=""),"",F40/'Summary Op Stmt (Operators)'!$F$20) | H40: ='Schedule 11 - Non-Operating'!H21 -> 0 | I40: =IF(OR('Summary Op Stmt (Operators)'!$H$20=0,'Summary Op Stmt (Operators)'!$H$20=""),"",H40/'Summary Op Stmt (Operators)'!$H$20) | J40: ='Schedule 11 - Non-Operating'!J21 -> 0 | K40: =IF(OR('Summary Op Stmt (Operators)'!$J$20=0,'Summary Op Stmt (Operators)'!$J$20=""),"",J40/'Summary Op Stmt (Operators)'!$J$20) | L40: ='Schedule 11 - Non-Operating'!L21 -> 0 | M40: =IF(OR('Summary Op Stmt (Operators)'!$L$20=0,'Summary Op Stmt (Operators)'!$L$20=""),"",L40/'Summary Op Stmt (Operators)'!$L$20)
A41: Insurance | B41: ='Schedule 11 - Non-Operating'!B26 -> 0 | C41: =IF(OR('Summary Op Stmt (Operators)'!$B$20=0,'Summary Op Stmt (Operators)'!$B$20=""),"",B41/'Summary Op Stmt (Operators)'!$B$20) | D41: ='Schedule 11 - Non-Operating'!D26 -> 0 | E41: =IF(OR('Summary Op Stmt (Operators)'!$D$20=0,'Summary Op Stmt (Operators)'!$D$20=""),"",D41/'Summary Op Stmt (Operators)'!$D$20) | F41: ='Schedule 11 - Non-Operating'!F26 -> 0 | G41: =IF(OR('Summary Op Stmt (Operators)'!$F$20=0,'Summary Op Stmt (Operators)'!$F$20=""),"",F41/'Summary Op Stmt (Operators)'!$F$20) | H41: ='Schedule 11 - Non-Operating'!H26 -> 0 | I41: =IF(OR('Summary Op Stmt (Operators)'!$H$20=0,'Summary Op Stmt (Operators)'!$H$20=""),"",H41/'Summary Op Stmt (Operators)'!$H$20) | J41: ='Schedule 11 - Non-Operating'!J26 -> 0 | K41: =IF(OR('Summary Op Stmt (Operators)'!$J$20=0,'Summary Op Stmt (Operators)'!$J$20=""),"",J41/'Summary Op Stmt (Operators)'!$J$20) | L41: ='Schedule 11 - Non-Operating'!L26 -> 0 | M41: =IF(OR('Summary Op Stmt (Operators)'!$L$20=0,'Summary Op Stmt (Operators)'!$L$20=""),"",L41/'Summary Op Stmt (Operators)'!$L$20)
A42: Other | B42: ='Schedule 11 - Non-Operating'!B32 -> 0 | C42: =IF(OR('Summary Op Stmt (Operators)'!$B$20=0,'Summary Op Stmt (Operators)'!$B$20=""),"",B42/'Summary Op Stmt (Operators)'!$B$20) | D42: ='Schedule 11 - Non-Operating'!D32 -> 0 | E42: =IF(OR('Summary Op Stmt (Operators)'!$D$20=0,'Summary Op Stmt (Operators)'!$D$20=""),"",D42/'Summary Op Stmt (Operators)'!$D$20) | F42: ='Schedule 11 - Non-Operating'!F32 -> 0 | G42: =IF(OR('Summary Op Stmt (Operators)'!$F$20=0,'Summary Op Stmt (Operators)'!$F$20=""),"",F42/'Summary Op Stmt (Operators)'!$F$20) | H42: ='Schedule 11 - Non-Operating'!H32 -> 0 | I42: =IF(OR('Summary Op Stmt (Operators)'!$H$20=0,'Summary Op Stmt (Operators)'!$H$20=""),"",H42/'Summary Op Stmt (Operators)'!$H$20) | J42: ='Schedule 11 - Non-Operating'!J32 -> 0 | K42: =IF(OR('Summary Op Stmt (Operators)'!$J$20=0,'Summary Op Stmt (Operators)'!$J$20=""),"",J42/'Summary Op Stmt (Operators)'!$J$20) | L42: ='Schedule 11 - Non-Operating'!L32 -> 0 | M42: =IF(OR('Summary Op Stmt (Operators)'!$L$20=0,'Summary Op Stmt (Operators)'!$L$20=""),"",L42/'Summary Op Stmt (Operators)'!$L$20)
A43: Total Non-Operating Income and Expenses | B43: =B39+B40+B41+B42-B38 -> 0 | C43: =IF(OR('Summary Op Stmt (Operators)'!$B$20=0,'Summary Op Stmt (Operators)'!$B$20=""),"",B43/'Summary Op Stmt (Operators)'!$B$20) | D43: =D39+D40+D41+D42-D38 -> 0 | E43: =IF(OR('Summary Op Stmt (Operators)'!$D$20=0,'Summary Op Stmt (Operators)'!$D$20=""),"",D43/'Summary Op Stmt (Operators)'!$D$20) | F43: =F39+F40+F41+F42-F38 -> 0 | G43: =IF(OR('Summary Op Stmt (Operators)'!$F$20=0,'Summary Op Stmt (Operators)'!$F$20=""),"",F43/'Summary Op Stmt (Operators)'!$F$20) | H43: =H39+H40+H41+H42-H38 -> 0 | I43: =IF(OR('Summary Op Stmt (Operators)'!$H$20=0,'Summary Op Stmt (Operators)'!$H$20=""),"",H43/'Summary Op Stmt (Operators)'!$H$20) | J43: =J39+J40+J41+J42-J38 -> 0 | K43: =IF(OR('Summary Op Stmt (Operators)'!$J$20=0,'Summary Op Stmt (Operators)'!$J$20=""),"",J43/'Summary Op Stmt (Operators)'!$J$20) | L43: =L39+L40+L41+L42-L38 -> 0 | M43: =IF(OR('Summary Op Stmt (Operators)'!$L$20=0,'Summary Op Stmt (Operators)'!$L$20=""),"",L43/'Summary Op Stmt (Operators)'!$L$20)
A44: Earnings Before Interest, Taxes, Depreciation, and Amortization | B44: =B36-B43 -> 0 | C44: =IF(OR('Summary Op Stmt (Operators)'!$B$20=0,'Summary Op Stmt (Operators)'!$B$20=""),"",B44/'Summary Op Stmt (Operators)'!$B$20) | D44: =D36-D43 -> 0 | E44: =IF(OR('Summary Op Stmt (Operators)'!$D$20=0,'Summary Op Stmt (Operators)'!$D$20=""),"",D44/'Summary Op Stmt (Operators)'!$D$20) | F44: =F36-F43 -> 0 | G44: =IF(OR('Summary Op Stmt (Operators)'!$F$20=0,'Summary Op Stmt (Operators)'!$F$20=""),"",F44/'Summary Op Stmt (Operators)'!$F$20) | H44: =H36-H43 -> 0 | I44: =IF(OR('Summary Op Stmt (Operators)'!$H$20=0,'Summary Op Stmt (Operators)'!$H$20=""),"",H44/'Summary Op Stmt (Operators)'!$H$20) | J44: =J36-J43 -> 0 | K44: =IF(OR('Summary Op Stmt (Operators)'!$J$20=0,'Summary Op Stmt (Operators)'!$J$20=""),"",J44/'Summary Op Stmt (Operators)'!$J$20) | L44: =L36-L43 -> 0 | M44: =IF(OR('Summary Op Stmt (Operators)'!$L$20=0,'Summary Op Stmt (Operators)'!$L$20=""),"",L44/'Summary Op Stmt (Operators)'!$L$20)
A45: Interest, Depreciation, and Amortization
A46: Interest | C46: =IF(OR('Summary Op Stmt (Operators)'!$B$20=0,'Summary Op Stmt (Operators)'!$B$20=""),"",B46/'Summary Op Stmt (Operators)'!$B$20) | E46: =IF(OR('Summary Op Stmt (Operators)'!$D$20=0,'Summary Op Stmt (Operators)'!$D$20=""),"",D46/'Summary Op Stmt (Operators)'!$D$20) | G46: =IF(OR('Summary Op Stmt (Operators)'!$F$20=0,'Summary Op Stmt (Operators)'!$F$20=""),"",F46/'Summary Op Stmt (Operators)'!$F$20) | I46: =IF(OR('Summary Op Stmt (Operators)'!$H$20=0,'Summary Op Stmt (Operators)'!$H$20=""),"",H46/'Summary Op Stmt (Operators)'!$H$20) | K46: =IF(OR('Summary Op Stmt (Operators)'!$J$20=0,'Summary Op Stmt (Operators)'!$J$20=""),"",J46/'Summary Op Stmt (Operators)'!$J$20) | M46: =IF(OR('Summary Op Stmt (Operators)'!$L$20=0,'Summary Op Stmt (Operators)'!$L$20=""),"",L46/'Summary Op Stmt (Operators)'!$L$20)
A47: Depreciation | C47: =IF(OR('Summary Op Stmt (Operators)'!$B$20=0,'Summary Op Stmt (Operators)'!$B$20=""),"",B47/'Summary Op Stmt (Operators)'!$B$20) | E47: =IF(OR('Summary Op Stmt (Operators)'!$D$20=0,'Summary Op Stmt (Operators)'!$D$20=""),"",D47/'Summary Op Stmt (Operators)'!$D$20) | G47: =IF(OR('Summary Op Stmt (Operators)'!$F$20=0,'Summary Op Stmt (Operators)'!$F$20=""),"",F47/'Summary Op Stmt (Operators)'!$F$20) | I47: =IF(OR('Summary Op Stmt (Operators)'!$H$20=0,'Summary Op Stmt (Operators)'!$H$20=""),"",H47/'Summary Op Stmt (Operators)'!$H$20) | K47: =IF(OR('Summary Op Stmt (Operators)'!$J$20=0,'Summary Op Stmt (Operators)'!$J$20=""),"",J47/'Summary Op Stmt (Operators)'!$J$20) | M47: =IF(OR('Summary Op Stmt (Operators)'!$L$20=0,'Summary Op Stmt (Operators)'!$L$20=""),"",L47/'Summary Op Stmt (Operators)'!$L$20)
A48: Amortization | C48: =IF(OR('Summary Op Stmt (Operators)'!$B$20=0,'Summary Op Stmt (Operators)'!$B$20=""),"",B48/'Summary Op Stmt (Operators)'!$B$20) | E48: =IF(OR('Summary Op Stmt (Operators)'!$D$20=0,'Summary Op Stmt (Operators)'!$D$20=""),"",D48/'Summary Op Stmt (Operators)'!$D$20) | G48: =IF(OR('Summary Op Stmt (Operators)'!$F$20=0,'Summary Op Stmt (Operators)'!$F$20=""),"",F48/'Summary Op Stmt (Operators)'!$F$20) | I48: =IF(OR('Summary Op Stmt (Operators)'!$H$20=0,'Summary Op Stmt (Operators)'!$H$20=""),"",H48/'Summary Op Stmt (Operators)'!$H$20) | K48: =IF(OR('Summary Op Stmt (Operators)'!$J$20=0,'Summary Op Stmt (Operators)'!$J$20=""),"",J48/'Summary Op Stmt (Operators)'!$J$20) | M48: =IF(OR('Summary Op Stmt (Operators)'!$L$20=0,'Summary Op Stmt (Operators)'!$L$20=""),"",L48/'Summary Op Stmt (Operators)'!$L$20)
A49: Total Interest, Depreciation, and Amortization | B49: =B46+B47+B48 -> 0 | C49: =IF(OR('Summary Op Stmt (Operators)'!$B$20=0,'Summary Op Stmt (Operators)'!$B$20=""),"",B49/'Summary Op Stmt (Operators)'!$B$20) | D49: =D46+D47+D48 -> 0 | E49: =IF(OR('Summary Op Stmt (Operators)'!$D$20=0,'Summary Op Stmt (Operators)'!$D$20=""),"",D49/'Summary Op Stmt (Operators)'!$D$20) | F49: =F46+F47+F48 -> 0 | G49: =IF(OR('Summary Op Stmt (Operators)'!$F$20=0,'Summary Op Stmt (Operators)'!$F$20=""),"",F49/'Summary Op Stmt (Operators)'!$F$20) | H49: =H46+H47+H48 -> 0 | I49: =IF(OR('Summary Op Stmt (Operators)'!$H$20=0,'Summary Op Stmt (Operators)'!$H$20=""),"",H49/'Summary Op Stmt (Operators)'!$H$20) | J49: =J46+J47+J48 -> 0 | K49: =IF(OR('Summary Op Stmt (Operators)'!$J$20=0,'Summary Op Stmt (Operators)'!$J$20=""),"",J49/'Summary Op Stmt (Operators)'!$J$20) | L49: =L46+L47+L48 -> 0 | M49: =IF(OR('Summary Op Stmt (Operators)'!$L$20=0,'Summary Op Stmt (Operators)'!$L$20=""),"",L49/'Summary Op Stmt (Operators)'!$L$20)
A50: Income Before Income Taxes | B50: =B44-B49 -> 0 | C50: =IF(OR('Summary Op Stmt (Operators)'!$B$20=0,'Summary Op Stmt (Operators)'!$B$20=""),"",B50/'Summary Op Stmt (Operators)'!$B$20) | D50: =D44-D49 -> 0 | E50: =IF(OR('Summary Op Stmt (Operators)'!$D$20=0,'Summary Op Stmt (Operators)'!$D$20=""),"",D50/'Summary Op Stmt (Operators)'!$D$20) | F50: =F44-F49 -> 0 | G50: =IF(OR('Summary Op Stmt (Operators)'!$F$20=0,'Summary Op Stmt (Operators)'!$F$20=""),"",F50/'Summary Op Stmt (Operators)'!$F$20) | H50: =H44-H49 -> 0 | I50: =IF(OR('Summary Op Stmt (Operators)'!$H$20=0,'Summary Op Stmt (Operators)'!$H$20=""),"",H50/'Summary Op Stmt (Operators)'!$H$20) | J50: =J44-J49 -> 0 | K50: =IF(OR('Summary Op Stmt (Operators)'!$J$20=0,'Summary Op Stmt (Operators)'!$J$20=""),"",J50/'Summary Op Stmt (Operators)'!$J$20) | L50: =L44-L49 -> 0 | M50: =IF(OR('Summary Op Stmt (Operators)'!$L$20=0,'Summary Op Stmt (Operators)'!$L$20=""),"",L50/'Summary Op Stmt (Operators)'!$L$20)
A51: Income Taxes | C51: =IF(OR('Summary Op Stmt (Operators)'!$B$20=0,'Summary Op Stmt (Operators)'!$B$20=""),"",B51/'Summary Op Stmt (Operators)'!$B$20) | E51: =IF(OR('Summary Op Stmt (Operators)'!$D$20=0,'Summary Op Stmt (Operators)'!$D$20=""),"",D51/'Summary Op Stmt (Operators)'!$D$20) | G51: =IF(OR('Summary Op Stmt (Operators)'!$F$20=0,'Summary Op Stmt (Operators)'!$F$20=""),"",F51/'Summary Op Stmt (Operators)'!$F$20) | I51: =IF(OR('Summary Op Stmt (Operators)'!$H$20=0,'Summary Op Stmt (Operators)'!$H$20=""),"",H51/'Summary Op Stmt (Operators)'!$H$20) | K51: =IF(OR('Summary Op Stmt (Operators)'!$J$20=0,'Summary Op Stmt (Operators)'!$J$20=""),"",J51/'Summary Op Stmt (Operators)'!$J$20) | M51: =IF(OR('Summary Op Stmt (Operators)'!$L$20=0,'Summary Op Stmt (Operators)'!$L$20=""),"",L51/'Summary Op Stmt (Operators)'!$L$20)
A52: Net Income | B52: =B50-B51 -> 0 | C52: =IF(OR('Summary Op Stmt (Operators)'!$B$20=0,'Summary Op Stmt (Operators)'!$B$20=""),"",B52/'Summary Op Stmt (Operators)'!$B$20) | D52: =D50-D51 -> 0 | E52: =IF(OR('Summary Op Stmt (Operators)'!$D$20=0,'Summary Op Stmt (Operators)'!$D$20=""),"",D52/'Summary Op Stmt (Operators)'!$D$20) | F52: =F50-F51 -> 0 | G52: =IF(OR('Summary Op Stmt (Operators)'!$F$20=0,'Summary Op Stmt (Operators)'!$F$20=""),"",F52/'Summary Op Stmt (Operators)'!$F$20) | H52: =H50-H51 -> 0 | I52: =IF(OR('Summary Op Stmt (Operators)'!$H$20=0,'Summary Op Stmt (Operators)'!$H$20=""),"",H52/'Summary Op Stmt (Operators)'!$H$20) | J52: =J50-J51 -> 0 | K52: =IF(OR('Summary Op Stmt (Operators)'!$J$20=0,'Summary Op Stmt (Operators)'!$J$20=""),"",J52/'Summary Op Stmt (Operators)'!$J$20) | L52: =L50-L51 -> 0 | M52: =IF(OR('Summary Op Stmt (Operators)'!$L$20=0,'Summary Op Stmt (Operators)'!$L$20=""),"",L52/'Summary Op Stmt (Operators)'!$L$20)

Sheet Schedule 1 - Rooms
A1: ROOMS — SCHEDULE 1
A2: Property: | B2: ='Setup & Assumptions'!$B$4 -> Enter property name | H2: Period / Year: | J2: ='Setup & Assumptions'!$B$5 -> e.g. January 2026 / FY2026
A3: Departmental percentages are calculated on Total Rooms Revenue.
B4: Current Period | H4: Year-To-Date
B5: Actual | D5: Forecast / Budget | F5: Prior Year | H5: Actual | J5: Forecast / Budget | L5: Prior Year
A6: Line Item | B6: $ | C6: % | D6: $ | E6: % | F6: $ | G6: % | H6: $ | I6: % | J6: $ | K6: % | L6: $ | M6: %
A7: Revenue
A8: Transient Rooms Revenue
A9: Retail | C9: =IF(OR(B25=0,B25=""),"",B9/B25) | E9: =IF(OR(D25=0,D25=""),"",D9/D25) | G9: =IF(OR(F25=0,F25=""),"",F9/F25) | I9: =IF(OR(H25=0,H25=""),"",H9/H25) | K9: =IF(OR(J25=0,J25=""),"",J9/J25) | M9: =IF(OR(L25=0,L25=""),"",L9/L25)
A10: Discount | C10: =IF(OR(B25=0,B25=""),"",B10/B25) | E10: =IF(OR(D25=0,D25=""),"",D10/D25) | G10: =IF(OR(F25=0,F25=""),"",F10/F25) | I10: =IF(OR(H25=0,H25=""),"",H10/H25) | K10: =IF(OR(J25=0,J25=""),"",J10/J25) | M10: =IF(OR(L25=0,L25=""),"",L10/L25)
A11: Negotiated | C11: =IF(OR(B25=0,B25=""),"",B11/B25) | E11: =IF(OR(D25=0,D25=""),"",D11/D25) | G11: =IF(OR(F25=0,F25=""),"",F11/F25) | I11: =IF(OR(H25=0,H25=""),"",H11/H25) | K11: =IF(OR(J25=0,J25=""),"",J11/J25) | M11: =IF(OR(L25=0,L25=""),"",L11/L25)
A12: Qualified | C12: =IF(OR(B25=0,B25=""),"",B12/B25) | E12: =IF(OR(D25=0,D25=""),"",D12/D25) | G12: =IF(OR(F25=0,F25=""),"",F12/F25) | I12: =IF(OR(H25=0,H25=""),"",H12/H25) | K12: =IF(OR(J25=0,J25=""),"",J12/J25) | M12: =IF(OR(L25=0,L25=""),"",L12/L25)
A13: Wholesale | C13: =IF(OR(B25=0,B25=""),"",B13/B25) | E13: =IF(OR(D25=0,D25=""),"",D13/D25) | G13: =IF(OR(F25=0,F25=""),"",F13/F25) | I13: =IF(OR(H25=0,H25=""),"",H13/H25) | K13: =IF(OR(J25=0,J25=""),"",J13/J25) | M13: =IF(OR(L25=0,L25=""),"",L13/L25)
A14: Total Transient Rooms Revenue | B14: =B9+B10+B11+B12+B13 -> 0 | C14: =IF(OR(B25=0,B25=""),"",B14/B25) | D14: =D9+D10+D11+D12+D13 -> 0 | E14: =IF(OR(D25=0,D25=""),"",D14/D25) | F14: =F9+F10+F11+F12+F13 -> 0 | G14: =IF(OR(F25=0,F25=""),"",F14/F25) | H14: =H9+H10+H11+H12+H13 -> 0 | I14: =IF(OR(H25=0,H25=""),"",H14/H25) | J14: =J9+J10+J11+J12+J13 -> 0 | K14: =IF(OR(J25=0,J25=""),"",J14/J25) | L14: =L9+L10+L11+L12+L13 -> 0 | M14: =IF(OR(L25=0,L25=""),"",L14/L25)
A15: Group Rooms Revenue
A16: Corporate | C16: =IF(OR(B25=0,B25=""),"",B16/B25) | E16: =IF(OR(D25=0,D25=""),"",D16/D25) | G16: =IF(OR(F25=0,F25=""),"",F16/F25) | I16: =IF(OR(H25=0,H25=""),"",H16/H25) | K16: =IF(OR(J25=0,J25=""),"",J16/J25) | M16: =IF(OR(L25=0,L25=""),"",L16/L25)
A17: Association/Convention | C17: =IF(OR(B25=0,B25=""),"",B17/B25) | E17: =IF(OR(D25=0,D25=""),"",D17/D25) | G17: =IF(OR(F25=0,F25=""),"",F17/F25) | I17: =IF(OR(H25=0,H25=""),"",H17/H25) | K17: =IF(OR(J25=0,J25=""),"",J17/J25) | M17: =IF(OR(L25=0,L25=""),"",L17/L25)
A18: Government | C18: =IF(OR(B25=0,B25=""),"",B18/B25) | E18: =IF(OR(D25=0,D25=""),"",D18/D25) | G18: =IF(OR(F25=0,F25=""),"",F18/F25) | I18: =IF(OR(H25=0,H25=""),"",H18/H25) | K18: =IF(OR(J25=0,J25=""),"",J18/J25) | M18: =IF(OR(L25=0,L25=""),"",L18/L25)
A19: Tour/Wholesalers | C19: =IF(OR(B25=0,B25=""),"",B19/B25) | E19: =IF(OR(D25=0,D25=""),"",D19/D25) | G19: =IF(OR(F25=0,F25=""),"",F19/F25) | I19: =IF(OR(H25=0,H25=""),"",H19/H25) | K19: =IF(OR(J25=0,J25=""),"",J19/J25) | M19: =IF(OR(L25=0,L25=""),"",L19/L25)
A20: SMERF | C20: =IF(OR(B25=0,B25=""),"",B20/B25) | E20: =IF(OR(D25=0,D25=""),"",D20/D25) | G20: =IF(OR(F25=0,F25=""),"",F20/F25) | I20: =IF(OR(H25=0,H25=""),"",H20/H25) | K20: =IF(OR(J25=0,J25=""),"",J20/J25) | M20: =IF(OR(L25=0,L25=""),"",L20/L25)
A21: Total Group Rooms Revenue | B21: =B16+B17+B18+B19+B20 -> 0 | C21: =IF(OR(B25=0,B25=""),"",B21/B25) | D21: =D16+D17+D18+D19+D20 -> 0 | E21: =IF(OR(D25=0,D25=""),"",D21/D25) | F21: =F16+F17+F18+F19+F20 -> 0 | G21: =IF(OR(F25=0,F25=""),"",F21/F25) | H21: =H16+H17+H18+H19+H20 -> 0 | I21: =IF(OR(H25=0,H25=""),"",H21/H25) | J21: =J16+J17+J18+J19+J20 -> 0 | K21: =IF(OR(J25=0,J25=""),"",J21/J25) | L21: =L16+L17+L18+L19+L20 -> 0 | M21: =IF(OR(L25=0,L25=""),"",L21/L25)
A22: Contract Rooms Revenue | C22: =IF(OR(B25=0,B25=""),"",B22/B25) | E22: =IF(OR(D25=0,D25=""),"",D22/D25) | G22: =IF(OR(F25=0,F25=""),"",F22/F25) | I22: =IF(OR(H25=0,H25=""),"",H22/H25) | K22: =IF(OR(J25=0,J25=""),"",J22/J25) | M22: =IF(OR(L25=0,L25=""),"",L22/L25)
A23: Other Rooms Revenue | C23: =IF(OR(B25=0,B25=""),"",B23/B25) | E23: =IF(OR(D25=0,D25=""),"",D23/D25) | G23: =IF(OR(F25=0,F25=""),"",F23/F25) | I23: =IF(OR(H25=0,H25=""),"",H23/H25) | K23: =IF(OR(J25=0,J25=""),"",J23/J25) | M23: =IF(OR(L25=0,L25=""),"",L23/L25)
A24: Less: Allowances | C24: =IF(OR(B25=0,B25=""),"",B24/B25) | E24: =IF(OR(D25=0,D25=""),"",D24/D25) | G24: =IF(OR(F25=0,F25=""),"",F24/F25) | I24: =IF(OR(H25=0,H25=""),"",H24/H25) | K24: =IF(OR(J25=0,J25=""),"",J24/J25) | M24: =IF(OR(L25=0,L25=""),"",L24/L25)
A25: Total Rooms Revenue | B25: =B14+B21+B22+B23-B24 -> 0 | C25: =IF(OR(B25=0,B25=""),"",B25/B25) | D25: =D14+D21+D22+D23-D24 -> 0 | E25: =IF(OR(D25=0,D25=""),"",D25/D25) | F25: =F14+F21+F22+F23-F24 -> 0 | G25: =IF(OR(F25=0,F25=""),"",F25/F25) | H25: =H14+H21+H22+H23-H24 -> 0 | I25: =IF(OR(H25=0,H25=""),"",H25/H25) | J25: =J14+J21+J22+J23-J24 -> 0 | K25: =IF(OR(J25=0,J25=""),"",J25/J25) | L25: =L14+L21+L22+L23-L24 -> 0 | M25: =IF(OR(L25=0,L25=""),"",L25/L25)
A26: Expenses
A27: Labor Costs and Related Expenses
A28: Salaries, Wages, Service Charges, Contracted Labor and Bonuses
A29: Salaries and Wages
A30: Management
A31: Non-Management
A32: Front Office
A33: Guest Services
A34: Housekeeping
A35: Laundry
A36: Reservations
A37: Transportation
A38: Sub-Total: Salaries and Wages | B38: =B30+B32+B33+B34+B35+B36+B37 -> 0 | D38: =D30+D32+D33+D34+D35+D36+D37 -> 0 | F38: =F30+F32+F33+F34+F35+F36+F37 -> 0 | H38: =H30+H32+H33+H34+H35+H36+H37 -> 0 | J38: =J30+J32+J33+J34+J35+J36+J37 -> 0 | L38: =L30+L32+L33+L34+L35+L36+L37 -> 0
A39: Service Charge Distribution
A40: Contracted, Leased and Outsourced Labor
A41: Bonuses and Incentives
A42: Total Salaries, Wages, Service Charges, Contracted Labor and Bonuses | B42: =B38+B39+B40+B41 -> 0 | C42: =IF(OR(B25=0,B25=""),"",B42/B25) | D42: =D38+D39+D40+D41 -> 0 | E42: =IF(OR(D25=0,D25=""),"",D42/D25) | F42: =F38+F39+F40+F41 -> 0 | G42: =IF(OR(F25=0,F25=""),"",F42/F25) | H42: =H38+H39+H40+H41 -> 0 | I42: =IF(OR(H25=0,H25=""),"",H42/H25) | J42: =J38+J39+J40+J41 -> 0 | K42: =IF(OR(J25=0,J25=""),"",J42/J25) | L42: =L38+L39+L40+L41 -> 0 | M42: =IF(OR(L25=0,L25=""),"",L42/L25)
A43: Payroll-Related Expenses
A44: Payroll Taxes | C44: =IF(OR(B25=0,B25=""),"",B44/B25) | E44: =IF(OR(D25=0,D25=""),"",D44/D25) | G44: =IF(OR(F25=0,F25=""),"",F44/F25) | I44: =IF(OR(H25=0,H25=""),"",H44/H25) | K44: =IF(OR(J25=0,J25=""),"",J44/J25) | M44: =IF(OR(L25=0,L25=""),"",L44/L25)
A45: Supplemental Pay | C45: =IF(OR(B25=0,B25=""),"",B45/B25) | E45: =IF(OR(D25=0,D25=""),"",D45/D25) | G45: =IF(OR(F25=0,F25=""),"",F45/F25) | I45: =IF(OR(H25=0,H25=""),"",H45/H25) | K45: =IF(OR(J25=0,J25=""),"",J45/J25) | M45: =IF(OR(L25=0,L25=""),"",L45/L25)
A46: Employee Benefits | C46: =IF(OR(B25=0,B25=""),"",B46/B25) | E46: =IF(OR(D25=0,D25=""),"",D46/D25) | G46: =IF(OR(F25=0,F25=""),"",F46/F25) | I46: =IF(OR(H25=0,H25=""),"",H46/H25) | K46: =IF(OR(J25=0,J25=""),"",J46/J25) | M46: =IF(OR(L25=0,L25=""),"",L46/L25)
A47: Total Payroll-Related Expenses | B47: =B44+B45+B46 -> 0 | C47: =IF(OR(B25=0,B25=""),"",B47/B25) | D47: =D44+D45+D46 -> 0 | E47: =IF(OR(D25=0,D25=""),"",D47/D25) | F47: =F44+F45+F46 -> 0 | G47: =IF(OR(F25=0,F25=""),"",F47/F25) | H47: =H44+H45+H46 -> 0 | I47: =IF(OR(H25=0,H25=""),"",H47/H25) | J47: =J44+J45+J46 -> 0 | K47: =IF(OR(J25=0,J25=""),"",J47/J25) | L47: =L44+L45+L46 -> 0 | M47: =IF(OR(L25=0,L25=""),"",L47/L25)
A48: Total Labor Costs and Related Expenses | B48: =B42+B47 -> 0 | C48: =IF(OR(B25=0,B25=""),"",B48/B25) | D48: =D42+D47 -> 0 | E48: =IF(OR(D25=0,D25=""),"",D48/D25) | F48: =F42+F47 -> 0 | G48: =IF(OR(F25=0,F25=""),"",F48/F25) | H48: =H42+H47 -> 0 | I48: =IF(OR(H25=0,H25=""),"",H48/H25) | J48: =J42+J47 -> 0 | K48: =IF(OR(J25=0,J25=""),"",J48/J25) | L48: =L42+L47 -> 0 | M48: =IF(OR(L25=0,L25=""),"",L48/L25)
A49: Other Expenses
A50: Cleaning Supplies | C50: =IF(OR(B25=0,B25=""),"",B50/B25) | E50: =IF(OR(D25=0,D25=""),"",D50/D25) | G50: =IF(OR(F25=0,F25=""),"",F50/F25) | I50: =IF(OR(H25=0,H25=""),"",H50/H25) | K50: =IF(OR(J25=0,J25=""),"",J50/J25) | M50: =IF(OR(L25=0,L25=""),"",L50/L25)
A51: Cluster Services | C51: =IF(OR(B25=0,B25=""),"",B51/B25) | E51: =IF(OR(D25=0,D25=""),"",D51/D25) | G51: =IF(OR(F25=0,F25=""),"",F51/F25) | I51: =IF(OR(H25=0,H25=""),"",H51/H25) | K51: =IF(OR(J25=0,J25=""),"",J51/J25) | M51: =IF(OR(L25=0,L25=""),"",L51/L25)
A52: Commissions | C52: =IF(OR(B25=0,B25=""),"",B52/B25) | E52: =IF(OR(D25=0,D25=""),"",D52/D25) | G52: =IF(OR(F25=0,F25=""),"",F52/F25) | I52: =IF(OR(H25=0,H25=""),"",H52/H25) | K52: =IF(OR(J25=0,J25=""),"",J52/J25) | M52: =IF(OR(L25=0,L25=""),"",L52/L25)
A53: Commissions and Fees - Group | C53: =IF(OR(B25=0,B25=""),"",B53/B25) | E53: =IF(OR(D25=0,D25=""),"",D53/D25) | G53: =IF(OR(F25=0,F25=""),"",F53/F25) | I53: =IF(OR(H25=0,H25=""),"",H53/H25) | K53: =IF(OR(J25=0,J25=""),"",J53/J25) | M53: =IF(OR(L25=0,L25=""),"",L53/L25)
A54: Complimentary Food and Beverage | C54: =IF(OR(B25=0,B25=""),"",B54/B25) | E54: =IF(OR(D25=0,D25=""),"",D54/D25) | G54: =IF(OR(F25=0,F25=""),"",F54/F25) | I54: =IF(OR(H25=0,H25=""),"",H54/H25) | K54: =IF(OR(J25=0,J25=""),"",J54/J25) | M54: =IF(OR(L25=0,L25=""),"",L54/L25)
A55: Complimentary In-Room/Media Entertainment | C55: =IF(OR(B25=0,B25=""),"",B55/B25) | E55: =IF(OR(D25=0,D25=""),"",D55/D25) | G55: =IF(OR(F25=0,F25=""),"",F55/F25) | I55: =IF(OR(H25=0,H25=""),"",H55/H25) | K55: =IF(OR(J25=0,J25=""),"",J55/J25) | M55: =IF(OR(L25=0,L25=""),"",L55/L25)
A56: Complimentary Services and Gifts | C56: =IF(OR(B25=0,B25=""),"",B56/B25) | E56: =IF(OR(D25=0,D25=""),"",D56/D25) | G56: =IF(OR(F25=0,F25=""),"",F56/F25) | I56: =IF(OR(H25=0,H25=""),"",H56/H25) | K56: =IF(OR(J25=0,J25=""),"",J56/J25) | M56: =IF(OR(L25=0,L25=""),"",L56/L25)
A57: Contract Services | C57: =IF(OR(B25=0,B25=""),"",B57/B25) | E57: =IF(OR(D25=0,D25=""),"",D57/D25) | G57: =IF(OR(F25=0,F25=""),"",F57/F25) | I57: =IF(OR(H25=0,H25=""),"",H57/H25) | K57: =IF(OR(J25=0,J25=""),"",J57/J25) | M57: =IF(OR(L25=0,L25=""),"",L57/L25)
A58: Corporate Office Reimbursables | C58: =IF(OR(B25=0,B25=""),"",B58/B25) | E58: =IF(OR(D25=0,D25=""),"",D58/D25) | G58: =IF(OR(F25=0,F25=""),"",F58/F25) | I58: =IF(OR(H25=0,H25=""),"",H58/H25) | K58: =IF(OR(J25=0,J25=""),"",J58/J25) | M58: =IF(OR(L25=0,L25=""),"",L58/L25)
A59: Decorations | C59: =IF(OR(B25=0,B25=""),"",B59/B25) | E59: =IF(OR(D25=0,D25=""),"",D59/D25) | G59: =IF(OR(F25=0,F25=""),"",F59/F25) | I59: =IF(OR(H25=0,H25=""),"",H59/H25) | K59: =IF(OR(J25=0,J25=""),"",J59/J25) | M59: =IF(OR(L25=0,L25=""),"",L59/L25)
A60: Dues and Subscriptions | C60: =IF(OR(B25=0,B25=""),"",B60/B25) | E60: =IF(OR(D25=0,D25=""),"",D60/D25) | G60: =IF(OR(F25=0,F25=""),"",F60/F25) | I60: =IF(OR(H25=0,H25=""),"",H60/H25) | K60: =IF(OR(J25=0,J25=""),"",J60/J25) | M60: =IF(OR(L25=0,L25=""),"",L60/L25)
A61: Entertainment - In-House | C61: =IF(OR(B25=0,B25=""),"",B61/B25) | E61: =IF(OR(D25=0,D25=""),"",D61/D25) | G61: =IF(OR(F25=0,F25=""),"",F61/F25) | I61: =IF(OR(H25=0,H25=""),"",H61/H25) | K61: =IF(OR(J25=0,J25=""),"",J61/J25) | M61: =IF(OR(L25=0,L25=""),"",L61/L25)
A62: Equipment Rental | C62: =IF(OR(B25=0,B25=""),"",B62/B25) | E62: =IF(OR(D25=0,D25=""),"",D62/D25) | G62: =IF(OR(F25=0,F25=""),"",F62/F25) | I62: =IF(OR(H25=0,H25=""),"",H62/H25) | K62: =IF(OR(J25=0,J25=""),"",J62/J25) | M62: =IF(OR(L25=0,L25=""),"",L62/L25)
A63: Guest Relocation | C63: =IF(OR(B25=0,B25=""),"",B63/B25) | E63: =IF(OR(D25=0,D25=""),"",D63/D25) | G63: =IF(OR(F25=0,F25=""),"",F63/F25) | I63: =IF(OR(H25=0,H25=""),"",H63/H25) | K63: =IF(OR(J25=0,J25=""),"",J63/J25) | M63: =IF(OR(L25=0,L25=""),"",L63/L25)
A64: Guest Supplies | C64: =IF(OR(B25=0,B25=""),"",B64/B25) | E64: =IF(OR(D25=0,D25=""),"",D64/D25) | G64: =IF(OR(F25=0,F25=""),"",F64/F25) | I64: =IF(OR(H25=0,H25=""),"",H64/H25) | K64: =IF(OR(J25=0,J25=""),"",J64/J25) | M64: =IF(OR(L25=0,L25=""),"",L64/L25)
A65: Guest Transportation | C65: =IF(OR(B25=0,B25=""),"",B65/B25) | E65: =IF(OR(D25=0,D25=""),"",D65/D25) | G65: =IF(OR(F25=0,F25=""),"",F65/F25) | I65: =IF(OR(H25=0,H25=""),"",H65/H25) | K65: =IF(OR(J25=0,J25=""),"",J65/J25) | M65: =IF(OR(L25=0,L25=""),"",L65/L25)
A66: Laundry and Dry Cleaning | C66: =IF(OR(B25=0,B25=""),"",B66/B25) | E66: =IF(OR(D25=0,D25=""),"",D66/D25) | G66: =IF(OR(F25=0,F25=""),"",F66/F25) | I66: =IF(OR(H25=0,H25=""),"",H66/H25) | K66: =IF(OR(J25=0,J25=""),"",J66/J25) | M66: =IF(OR(L25=0,L25=""),"",L66/L25)
A67: Licenses and Permits | C67: =IF(OR(B25=0,B25=""),"",B67/B25) | E67: =IF(OR(D25=0,D25=""),"",D67/D25) | G67: =IF(OR(F25=0,F25=""),"",F67/F25) | I67: =IF(OR(H25=0,H25=""),"",H67/H25) | K67: =IF(OR(J25=0,J25=""),"",J67/J25) | M67: =IF(OR(L25=0,L25=""),"",L67/L25)
A68: Linen | C68: =IF(OR(B25=0,B25=""),"",B68/B25) | E68: =IF(OR(D25=0,D25=""),"",D68/D25) | G68: =IF(OR(F25=0,F25=""),"",F68/F25) | I68: =IF(OR(H25=0,H25=""),"",H68/H25) | K68: =IF(OR(J25=0,J25=""),"",J68/J25) | M68: =IF(OR(L25=0,L25=""),"",L68/L25)
A69: Miscellaneous | C69: =IF(OR(B25=0,B25=""),"",B69/B25) | E69: =IF(OR(D25=0,D25=""),"",D69/D25) | G69: =IF(OR(F25=0,F25=""),"",F69/F25) | I69: =IF(OR(H25=0,H25=""),"",H69/H25) | K69: =IF(OR(J25=0,J25=""),"",J69/J25) | M69: =IF(OR(L25=0,L25=""),"",L69/L25)
A70: Operating Supplies | C70: =IF(OR(B25=0,B25=""),"",B70/B25) | E70: =IF(OR(D25=0,D25=""),"",D70/D25) | G70: =IF(OR(F25=0,F25=""),"",F70/F25) | I70: =IF(OR(H25=0,H25=""),"",H70/H25) | K70: =IF(OR(J25=0,J25=""),"",J70/J25) | M70: =IF(OR(L25=0,L25=""),"",L70/L25)
A71: Postage and Overnight Delivery Charges | C71: =IF(OR(B25=0,B25=""),"",B71/B25) | E71: =IF(OR(D25=0,D25=""),"",D71/D25) | G71: =IF(OR(F25=0,F25=""),"",F71/F25) | I71: =IF(OR(H25=0,H25=""),"",H71/H25) | K71: =IF(OR(J25=0,J25=""),"",J71/J25) | M71: =IF(OR(L25=0,L25=""),"",L71/L25)
A72: Printing and Stationery | C72: =IF(OR(B25=0,B25=""),"",B72/B25) | E72: =IF(OR(D25=0,D25=""),"",D72/D25) | G72: =IF(OR(F25=0,F25=""),"",F72/F25) | I72: =IF(OR(H25=0,H25=""),"",H72/H25) | K72: =IF(OR(J25=0,J25=""),"",J72/J25) | M72: =IF(OR(L25=0,L25=""),"",L72/L25)
A73: Reservations | C73: =IF(OR(B25=0,B25=""),"",B73/B25) | E73: =IF(OR(D25=0,D25=""),"",D73/D25) | G73: =IF(OR(F25=0,F25=""),"",F73/F25) | I73: =IF(OR(H25=0,H25=""),"",H73/H25) | K73: =IF(OR(J25=0,J25=""),"",J73/J25) | M73: =IF(OR(L25=0,L25=""),"",L73/L25)
A74: Royalty Fees | C74: =IF(OR(B25=0,B25=""),"",B74/B25) | E74: =IF(OR(D25=0,D25=""),"",D74/D25) | G74: =IF(OR(F25=0,F25=""),"",F74/F25) | I74: =IF(OR(H25=0,H25=""),"",H74/H25) | K74: =IF(OR(J25=0,J25=""),"",J74/J25) | M74: =IF(OR(L25=0,L25=""),"",L74/L25)
A75: Training | C75: =IF(OR(B25=0,B25=""),"",B75/B25) | E75: =IF(OR(D25=0,D25=""),"",D75/D25) | G75: =IF(OR(F25=0,F25=""),"",F75/F25) | I75: =IF(OR(H25=0,H25=""),"",H75/H25) | K75: =IF(OR(J25=0,J25=""),"",J75/J25) | M75: =IF(OR(L25=0,L25=""),"",L75/L25)
A76: Travel - Meals and Entertainment | C76: =IF(OR(B25=0,B25=""),"",B76/B25) | E76: =IF(OR(D25=0,D25=""),"",D76/D25) | G76: =IF(OR(F25=0,F25=""),"",F76/F25) | I76: =IF(OR(H25=0,H25=""),"",H76/H25) | K76: =IF(OR(J25=0,J25=""),"",J76/J25) | M76: =IF(OR(L25=0,L25=""),"",L76/L25)
A77: Travel - Other | C77: =IF(OR(B25=0,B25=""),"",B77/B25) | E77: =IF(OR(D25=0,D25=""),"",D77/D25) | G77: =IF(OR(F25=0,F25=""),"",F77/F25) | I77: =IF(OR(H25=0,H25=""),"",H77/H25) | K77: =IF(OR(J25=0,J25=""),"",J77/J25) | M77: =IF(OR(L25=0,L25=""),"",L77/L25)
A78: Uniform Costs | C78: =IF(OR(B25=0,B25=""),"",B78/B25) | E78: =IF(OR(D25=0,D25=""),"",D78/D25) | G78: =IF(OR(F25=0,F25=""),"",F78/F25) | I78: =IF(OR(H25=0,H25=""),"",H78/H25) | K78: =IF(OR(J25=0,J25=""),"",J78/J25) | M78: =IF(OR(L25=0,L25=""),"",L78/L25)
A79: Uniform Laundry | C79: =IF(OR(B25=0,B25=""),"",B79/B25) | E79: =IF(OR(D25=0,D25=""),"",D79/D25) | G79: =IF(OR(F25=0,F25=""),"",F79/F25) | I79: =IF(OR(H25=0,H25=""),"",H79/H25) | K79: =IF(OR(J25=0,J25=""),"",J79/J25) | M79: =IF(OR(L25=0,L25=""),"",L79/L25)
A80: Total Other Expenses | B80: =B50+B51+B52+B53+B54+B55+B56+B57+B58+B59+B60+B61+B62+B63+B64+B65+B66+B67+B68+B69+B70+B71+B72+B73+B74+B75+B76+B77+B78+B79 -> 0 | C80: =IF(OR(B25=0,B25=""),"",B80/B25) | D80: =D50+D51+D52+D53+D54+D55+D56+D57+D58+D59+D60+D61+D62+D63+D64+D65+D66+D67+D68+D69+D70+D71+D72+D73+D74+D75+D76+D77+D78+D79 -> 0 | E80: =IF(OR(D25=0,D25=""),"",D80/D25) | F80: =F50+F51+F52+F53+F54+F55+F56+F57+F58+F59+F60+F61+F62+F63+F64+F65+F66+F67+F68+F69+F70+F71+F72+F73+F74+F75+F76+F77+F78+F79 -> 0 | G80: =IF(OR(F25=0,F25=""),"",F80/F25) | H80: =H50+H51+H52+H53+H54+H55+H56+H57+H58+H59+H60+H61+H62+H63+H64+H65+H66+H67+H68+H69+H70+H71+H72+H73+H74+H75+H76+H77+H78+H79 -> 0 | I80: =IF(OR(H25=0,H25=""),"",H80/H25) | J80: =J50+J51+J52+J53+J54+J55+J56+J57+J58+J59+J60+J61+J62+J63+J64+J65+J66+J67+J68+J69+J70+J71+J72+J73+J74+J75+J76+J77+J78+J79 -> 0 | K80: =IF(OR(J25=0,J25=""),"",J80/J25) | L80: =L50+L51+L52+L53+L54+L55+L56+L57+L58+L59+L60+L61+L62+L63+L64+L65+L66+L67+L68+L69+L70+L71+L72+L73+L74+L75+L76+L77+L78+L79 -> 0 | M80: =IF(OR(L25=0,L25=""),"",L80/L25)
A81: Total Expenses | B81: =B48+B80 -> 0 | C81: =IF(OR(B25=0,B25=""),"",B81/B25) | D81: =D48+D80 -> 0 | E81: =IF(OR(D25=0,D25=""),"",D81/D25) | F81: =F48+F80 -> 0 | G81: =IF(OR(F25=0,F25=""),"",F81/F25) | H81: =H48+H80 -> 0 | I81: =IF(OR(H25=0,H25=""),"",H81/H25) | J81: =J48+J80 -> 0 | K81: =IF(OR(J25=0,J25=""),"",J81/J25) | L81: =L48+L80 -> 0 | M81: =IF(OR(L25=0,L25=""),"",L81/L25)
A82: Departmental Profit | B82: =B25-B81 -> 0 | C82: =IF(OR(B25=0,B25=""),"",B82/B25) | D82: =D25-D81 -> 0 | E82: =IF(OR(D25=0,D25=""),"",D82/D25) | F82: =F25-F81 -> 0 | G82: =IF(OR(F25=0,F25=""),"",F82/F25) | H82: =H25-H81 -> 0 | I82: =IF(OR(H25=0,H25=""),"",H82/H25) | J82: =J25-J81 -> 0 | K82: =IF(OR(J25=0,J25=""),"",J82/J25) | L82: =L25-L81 -> 0 | M82: =IF(OR(L25=0,L25=""),"",L82/L25)

Sheet Schedule 2 - Food & Beverage
A1: FOOD AND BEVERAGE — SCHEDULE 2
A2: Property: | B2: ='Setup & Assumptions'!$B$4 -> Enter property name | H2: Period / Year: | J2: ='Setup & Assumptions'!$B$5 -> e.g. January 2026 / FY2026
A3: Departmental percentages are calculated on Total Revenue. Departmental Expense (for the Summary) = Cost of Sales + Total Expenses.
B4: Current Period | H4: Year-To-Date
B5: Actual | D5: Forecast / Budget | F5: Prior Year | H5: Actual | J5: Forecast / Budget | L5: Prior Year
A6: Line Item | B6: $ | C6: % | D6: $ | E6: % | F6: $ | G6: % | H6: $ | I6: % | J6: $ | K6: % | L6: $ | M6: %
A7: Revenue
A8: Food Revenue
A9: Venue Food Revenue | C9: =IF(OR(B32=0,B32=""),"",B9/B32) | E9: =IF(OR(D32=0,D32=""),"",D9/D32) | G9: =IF(OR(F32=0,F32=""),"",F9/F32) | I9: =IF(OR(H32=0,H32=""),"",H9/H32) | K9: =IF(OR(J32=0,J32=""),"",J9/J32) | M9: =IF(OR(L32=0,L32=""),"",L9/L32)
A10: In-Room Dining Food Revenue | C10: =IF(OR(B32=0,B32=""),"",B10/B32) | E10: =IF(OR(D32=0,D32=""),"",D10/D32) | G10: =IF(OR(F32=0,F32=""),"",F10/F32) | I10: =IF(OR(H32=0,H32=""),"",H10/H32) | K10: =IF(OR(J32=0,J32=""),"",J10/J32) | M10: =IF(OR(L32=0,L32=""),"",L10/L32)
A11: Banquet/Conference/Catering Food Revenue | C11: =IF(OR(B32=0,B32=""),"",B11/B32) | E11: =IF(OR(D32=0,D32=""),"",D11/D32) | G11: =IF(OR(F32=0,F32=""),"",F11/F32) | I11: =IF(OR(H32=0,H32=""),"",H11/H32) | K11: =IF(OR(J32=0,J32=""),"",J11/J32) | M11: =IF(OR(L32=0,L32=""),"",L11/L32)
A12: Mini Bar Food Revenue | C12: =IF(OR(B32=0,B32=""),"",B12/B32) | E12: =IF(OR(D32=0,D32=""),"",D12/D32) | G12: =IF(OR(F32=0,F32=""),"",F12/F32) | I12: =IF(OR(H32=0,H32=""),"",H12/H32) | K12: =IF(OR(J32=0,J32=""),"",J12/J32) | M12: =IF(OR(L32=0,L32=""),"",L12/L32)
A13: Other Food Revenue | C13: =IF(OR(B32=0,B32=""),"",B13/B32) | E13: =IF(OR(D32=0,D32=""),"",D13/D32) | G13: =IF(OR(F32=0,F32=""),"",F13/F32) | I13: =IF(OR(H32=0,H32=""),"",H13/H32) | K13: =IF(OR(J32=0,J32=""),"",J13/J32) | M13: =IF(OR(L32=0,L32=""),"",L13/L32)
A14: Total Food Revenue | B14: =B9+B10+B11+B12+B13 -> 0 | C14: =IF(OR(B32=0,B32=""),"",B14/B32) | D14: =D9+D10+D11+D12+D13 -> 0 | E14: =IF(OR(D32=0,D32=""),"",D14/D32) | F14: =F9+F10+F11+F12+F13 -> 0 | G14: =IF(OR(F32=0,F32=""),"",F14/F32) | H14: =H9+H10+H11+H12+H13 -> 0 | I14: =IF(OR(H32=0,H32=""),"",H14/H32) | J14: =J9+J10+J11+J12+J13 -> 0 | K14: =IF(OR(J32=0,J32=""),"",J14/J32) | L14: =L9+L10+L11+L12+L13 -> 0 | M14: =IF(OR(L32=0,L32=""),"",L14/L32)
A15: Beverage Revenue
A16: Venue Beverage Revenue | C16: =IF(OR(B32=0,B32=""),"",B16/B32) | E16: =IF(OR(D32=0,D32=""),"",D16/D32) | G16: =IF(OR(F32=0,F32=""),"",F16/F32) | I16: =IF(OR(H32=0,H32=""),"",H16/H32) | K16: =IF(OR(J32=0,J32=""),"",J16/J32) | M16: =IF(OR(L32=0,L32=""),"",L16/L32)
A17: In-Room Dining Beverage Revenue | C17: =IF(OR(B32=0,B32=""),"",B17/B32) | E17: =IF(OR(D32=0,D32=""),"",D17/D32) | G17: =IF(OR(F32=0,F32=""),"",F17/F32) | I17: =IF(OR(H32=0,H32=""),"",H17/H32) | K17: =IF(OR(J32=0,J32=""),"",J17/J32) | M17: =IF(OR(L32=0,L32=""),"",L17/L32)
A18: Banquet/Conference/Catering Beverage Revenue | C18: =IF(OR(B32=0,B32=""),"",B18/B32) | E18: =IF(OR(D32=0,D32=""),"",D18/D32) | G18: =IF(OR(F32=0,F32=""),"",F18/F32) | I18: =IF(OR(H32=0,H32=""),"",H18/H32) | K18: =IF(OR(J32=0,J32=""),"",J18/J32) | M18: =IF(OR(L32=0,L32=""),"",L18/L32)
A19: Mini Bar Beverage Revenue | C19: =IF(OR(B32=0,B32=""),"",B19/B32) | E19: =IF(OR(D32=0,D32=""),"",D19/D32) | G19: =IF(OR(F32=0,F32=""),"",F19/F32) | I19: =IF(OR(H32=0,H32=""),"",H19/H32) | K19: =IF(OR(J32=0,J32=""),"",J19/J32) | M19: =IF(OR(L32=0,L32=""),"",L19/L32)
A20: Other Beverage Revenue | C20: =IF(OR(B32=0,B32=""),"",B20/B32) | E20: =IF(OR(D32=0,D32=""),"",D20/D32) | G20: =IF(OR(F32=0,F32=""),"",F20/F32) | I20: =IF(OR(H32=0,H32=""),"",H20/H32) | K20: =IF(OR(J32=0,J32=""),"",J20/J32) | M20: =IF(OR(L32=0,L32=""),"",L20/L32)
A21: Total Beverage Revenue | B21: =B16+B17+B18+B19+B20 -> 0 | C21: =IF(OR(B32=0,B32=""),"",B21/B32) | D21: =D16+D17+D18+D19+D20 -> 0 | E21: =IF(OR(D32=0,D32=""),"",D21/D32) | F21: =F16+F17+F18+F19+F20 -> 0 | G21: =IF(OR(F32=0,F32=""),"",F21/F32) | H21: =H16+H17+H18+H19+H20 -> 0 | I21: =IF(OR(H32=0,H32=""),"",H21/H32) | J21: =J16+J17+J18+J19+J20 -> 0 | K21: =IF(OR(J32=0,J32=""),"",J21/J32) | L21: =L16+L17+L18+L19+L20 -> 0 | M21: =IF(OR(L32=0,L32=""),"",L21/L32)
A22: Less: Allowances | C22: =IF(OR(B32=0,B32=""),"",B22/B32) | E22: =IF(OR(D32=0,D32=""),"",D22/D32) | G22: =IF(OR(F32=0,F32=""),"",F22/F32) | I22: =IF(OR(H32=0,H32=""),"",H22/H32) | K22: =IF(OR(J32=0,J32=""),"",J22/J32) | M22: =IF(OR(L32=0,L32=""),"",L22/L32)
A23: Total Food and Beverage Revenue | B23: =B14+B21-B22 -> 0 | C23: =IF(OR(B32=0,B32=""),"",B23/B32) | D23: =D14+D21-D22 -> 0 | E23: =IF(OR(D32=0,D32=""),"",D23/D32) | F23: =F14+F21-F22 -> 0 | G23: =IF(OR(F32=0,F32=""),"",F23/F32) | H23: =H14+H21-H22 -> 0 | I23: =IF(OR(H32=0,H32=""),"",H23/H32) | J23: =J14+J21-J22 -> 0 | K23: =IF(OR(J32=0,J32=""),"",J23/J32) | L23: =L14+L21-L22 -> 0 | M23: =IF(OR(L32=0,L32=""),"",L23/L32)
A24: Other Revenue
A25: Audiovisual | C25: =IF(OR(B32=0,B32=""),"",B25/B32) | E25: =IF(OR(D32=0,D32=""),"",D25/D32) | G25: =IF(OR(F32=0,F32=""),"",F25/F32) | I25: =IF(OR(H32=0,H32=""),"",H25/H32) | K25: =IF(OR(J32=0,J32=""),"",J25/J32) | M25: =IF(OR(L32=0,L32=""),"",L25/L32)
A26: Function Room Rental and Setup Charges | C26: =IF(OR(B32=0,B32=""),"",B26/B32) | E26: =IF(OR(D32=0,D32=""),"",D26/D32) | G26: =IF(OR(F32=0,F32=""),"",F26/F32) | I26: =IF(OR(H32=0,H32=""),"",H26/H32) | K26: =IF(OR(J32=0,J32=""),"",J26/J32) | M26: =IF(OR(L32=0,L32=""),"",L26/L32)
A27: Cover Charges | C27: =IF(OR(B32=0,B32=""),"",B27/B32) | E27: =IF(OR(D32=0,D32=""),"",D27/D32) | G27: =IF(OR(F32=0,F32=""),"",F27/F32) | I27: =IF(OR(H32=0,H32=""),"",H27/H32) | K27: =IF(OR(J32=0,J32=""),"",J27/J32) | M27: =IF(OR(L32=0,L32=""),"",L27/L32)
A28: Surcharges and Service Charges | C28: =IF(OR(B32=0,B32=""),"",B28/B32) | E28: =IF(OR(D32=0,D32=""),"",D28/D32) | G28: =IF(OR(F32=0,F32=""),"",F28/F32) | I28: =IF(OR(H32=0,H32=""),"",H28/H32) | K28: =IF(OR(J32=0,J32=""),"",J28/J32) | M28: =IF(OR(L32=0,L32=""),"",L28/L32)
A29: Miscellaneous Other Revenue | C29: =IF(OR(B32=0,B32=""),"",B29/B32) | E29: =IF(OR(D32=0,D32=""),"",D29/D32) | G29: =IF(OR(F32=0,F32=""),"",F29/F32) | I29: =IF(OR(H32=0,H32=""),"",H29/H32) | K29: =IF(OR(J32=0,J32=""),"",J29/J32) | M29: =IF(OR(L32=0,L32=""),"",L29/L32)
A30: Less: Allowances | C30: =IF(OR(B32=0,B32=""),"",B30/B32) | E30: =IF(OR(D32=0,D32=""),"",D30/D32) | G30: =IF(OR(F32=0,F32=""),"",F30/F32) | I30: =IF(OR(H32=0,H32=""),"",H30/H32) | K30: =IF(OR(J32=0,J32=""),"",J30/J32) | M30: =IF(OR(L32=0,L32=""),"",L30/L32)
A31: Total Other Revenue | B31: =B25+B26+B27+B28+B29-B30 -> 0 | C31: =IF(OR(B32=0,B32=""),"",B31/B32) | D31: =D25+D26+D27+D28+D29-D30 -> 0 | E31: =IF(OR(D32=0,D32=""),"",D31/D32) | F31: =F25+F26+F27+F28+F29-F30 -> 0 | G31: =IF(OR(F32=0,F32=""),"",F31/F32) | H31: =H25+H26+H27+H28+H29-H30 -> 0 | I31: =IF(OR(H32=0,H32=""),"",H31/H32) | J31: =J25+J26+J27+J28+J29-J30 -> 0 | K31: =IF(OR(J32=0,J32=""),"",J31/J32) | L31: =L25+L26+L27+L28+L29-L30 -> 0 | M31: =IF(OR(L32=0,L32=""),"",L31/L32)
A32: Total Revenue | B32: =B23+B31 -> 0 | C32: =IF(OR(B32=0,B32=""),"",B32/B32) | D32: =D23+D31 -> 0 | E32: =IF(OR(D32=0,D32=""),"",D32/D32) | F32: =F23+F31 -> 0 | G32: =IF(OR(F32=0,F32=""),"",F32/F32) | H32: =H23+H31 -> 0 | I32: =IF(OR(H32=0,H32=""),"",H32/H32) | J32: =J23+J31 -> 0 | K32: =IF(OR(J32=0,J32=""),"",J32/J32) | L32: =L23+L31 -> 0 | M32: =IF(OR(L32=0,L32=""),"",L32/L32)
A33: Cost of Sales and Other Revenue
A34: Cost of Food and Beverage Sales
A35: Cost of Food Sales | C35: =IF(OR(B32=0,B32=""),"",B35/B32) | E35: =IF(OR(D32=0,D32=""),"",D35/D32) | G35: =IF(OR(F32=0,F32=""),"",F35/F32) | I35: =IF(OR(H32=0,H32=""),"",H35/H32) | K35: =IF(OR(J32=0,J32=""),"",J35/J32) | M35: =IF(OR(L32=0,L32=""),"",L35/L32)
A36: Cost of Beverage Sales | C36: =IF(OR(B32=0,B32=""),"",B36/B32) | E36: =IF(OR(D32=0,D32=""),"",D36/D32) | G36: =IF(OR(F32=0,F32=""),"",F36/F32) | I36: =IF(OR(H32=0,H32=""),"",H36/H32) | K36: =IF(OR(J32=0,J32=""),"",J36/J32) | M36: =IF(OR(L32=0,L32=""),"",L36/L32)
A37: Total Cost of Food and Beverage Sales | B37: =B35+B36 -> 0 | C37: =IF(OR(B32=0,B32=""),"",B37/B32) | D37: =D35+D36 -> 0 | E37: =IF(OR(D32=0,D32=""),"",D37/D32) | F37: =F35+F36 -> 0 | G37: =IF(OR(F32=0,F32=""),"",F37/F32) | H37: =H35+H36 -> 0 | I37: =IF(OR(H32=0,H32=""),"",H37/H32) | J37: =J35+J36 -> 0 | K37: =IF(OR(J32=0,J32=""),"",J37/J32) | L37: =L35+L36 -> 0 | M37: =IF(OR(L32=0,L32=""),"",L37/L32)
A38: Cost of Other Revenue
A39: Audiovisual Cost | C39: =IF(OR(B32=0,B32=""),"",B39/B32) | E39: =IF(OR(D32=0,D32=""),"",D39/D32) | G39: =IF(OR(F32=0,F32=""),"",F39/F32) | I39: =IF(OR(H32=0,H32=""),"",H39/H32) | K39: =IF(OR(J32=0,J32=""),"",J39/J32) | M39: =IF(OR(L32=0,L32=""),"",L39/L32)
A40: Miscellaneous Cost | C40: =IF(OR(B32=0,B32=""),"",B40/B32) | E40: =IF(OR(D32=0,D32=""),"",D40/D32) | G40: =IF(OR(F32=0,F32=""),"",F40/F32) | I40: =IF(OR(H32=0,H32=""),"",H40/H32) | K40: =IF(OR(J32=0,J32=""),"",J40/J32) | M40: =IF(OR(L32=0,L32=""),"",L40/L32)
A41: Total Cost of Other Revenue | B41: =B39+B40 -> 0 | C41: =IF(OR(B32=0,B32=""),"",B41/B32) | D41: =D39+D40 -> 0 | E41: =IF(OR(D32=0,D32=""),"",D41/D32) | F41: =F39+F40 -> 0 | G41: =IF(OR(F32=0,F32=""),"",F41/F32) | H41: =H39+H40 -> 0 | I41: =IF(OR(H32=0,H32=""),"",H41/H32) | J41: =J39+J40 -> 0 | K41: =IF(OR(J32=0,J32=""),"",J41/J32) | L41: =L39+L40 -> 0 | M41: =IF(OR(L32=0,L32=""),"",L41/L32)
A42: Total Cost of Sales and Other Revenue | B42: =B37+B41 -> 0 | C42: =IF(OR(B32=0,B32=""),"",B42/B32) | D42: =D37+D41 -> 0 | E42: =IF(OR(D32=0,D32=""),"",D42/D32) | F42: =F37+F41 -> 0 | G42: =IF(OR(F32=0,F32=""),"",F42/F32) | H42: =H37+H41 -> 0 | I42: =IF(OR(H32=0,H32=""),"",H42/H32) | J42: =J37+J41 -> 0 | K42: =IF(OR(J32=0,J32=""),"",J42/J32) | L42: =L37+L41 -> 0 | M42: =IF(OR(L32=0,L32=""),"",L42/L32)
A43: Gross Profit | B43: =B32-B42 -> 0 | C43: =IF(OR(B32=0,B32=""),"",B43/B32) | D43: =D32-D42 -> 0 | E43: =IF(OR(D32=0,D32=""),"",D43/D32) | F43: =F32-F42 -> 0 | G43: =IF(OR(F32=0,F32=""),"",F43/F32) | H43: =H32-H42 -> 0 | I43: =IF(OR(H32=0,H32=""),"",H43/H32) | J43: =J32-J42 -> 0 | K43: =IF(OR(J32=0,J32=""),"",J43/J32) | L43: =L32-L42 -> 0 | M43: =IF(OR(L32=0,L32=""),"",L43/L32)
A44: Expenses
A45: Labor Costs and Related Expenses
A46: Salaries, Wages, Service Charges, Contracted Labor and Bonuses
A47: Salaries and Wages
A48: Management
A49: Service
A50: Kitchen
A51: Non-Management
A52: Banquet/Conference/Catering Service
A53: Kitchen
A54: Venues
A55: Sub-Total: Salaries and Wages | B55: =B49+B50+B52+B53+B54 -> 0 | D55: =D49+D50+D52+D53+D54 -> 0 | F55: =F49+F50+F52+F53+F54 -> 0 | H55: =H49+H50+H52+H53+H54 -> 0 | J55: =J49+J50+J52+J53+J54 -> 0 | L55: =L49+L50+L52+L53+L54 -> 0
A56: Service Charge Distribution
A57: Contracted, Leased and Outsourced Labor
A58: Bonuses and Incentives
A59: Total Salaries, Wages, Service Charges, Contracted Labor and Bonuses | B59: =B55+B56+B57+B58 -> 0 | C59: =IF(OR(B32=0,B32=""),"",B59/B32) | D59: =D55+D56+D57+D58 -> 0 | E59: =IF(OR(D32=0,D32=""),"",D59/D32) | F59: =F55+F56+F57+F58 -> 0 | G59: =IF(OR(F32=0,F32=""),"",F59/F32) | H59: =H55+H56+H57+H58 -> 0 | I59: =IF(OR(H32=0,H32=""),"",H59/H32) | J59: =J55+J56+J57+J58 -> 0 | K59: =IF(OR(J32=0,J32=""),"",J59/J32) | L59: =L55+L56+L57+L58 -> 0 | M59: =IF(OR(L32=0,L32=""),"",L59/L32)
A60: Payroll-Related Expenses
A61: Payroll Taxes | C61: =IF(OR(B32=0,B32=""),"",B61/B32) | E61: =IF(OR(D32=0,D32=""),"",D61/D32) | G61: =IF(OR(F32=0,F32=""),"",F61/F32) | I61: =IF(OR(H32=0,H32=""),"",H61/H32) | K61: =IF(OR(J32=0,J32=""),"",J61/J32) | M61: =IF(OR(L32=0,L32=""),"",L61/L32)
A62: Supplemental Pay | C62: =IF(OR(B32=0,B32=""),"",B62/B32) | E62: =IF(OR(D32=0,D32=""),"",D62/D32) | G62: =IF(OR(F32=0,F32=""),"",F62/F32) | I62: =IF(OR(H32=0,H32=""),"",H62/H32) | K62: =IF(OR(J32=0,J32=""),"",J62/J32) | M62: =IF(OR(L32=0,L32=""),"",L62/L32)
A63: Employee Benefits | C63: =IF(OR(B32=0,B32=""),"",B63/B32) | E63: =IF(OR(D32=0,D32=""),"",D63/D32) | G63: =IF(OR(F32=0,F32=""),"",F63/F32) | I63: =IF(OR(H32=0,H32=""),"",H63/H32) | K63: =IF(OR(J32=0,J32=""),"",J63/J32) | M63: =IF(OR(L32=0,L32=""),"",L63/L32)
A64: Total Payroll-Related Expenses | B64: =B61+B62+B63 -> 0 | C64: =IF(OR(B32=0,B32=""),"",B64/B32) | D64: =D61+D62+D63 -> 0 | E64: =IF(OR(D32=0,D32=""),"",D64/D32) | F64: =F61+F62+F63 -> 0 | G64: =IF(OR(F32=0,F32=""),"",F64/F32) | H64: =H61+H62+H63 -> 0 | I64: =IF(OR(H32=0,H32=""),"",H64/H32) | J64: =J61+J62+J63 -> 0 | K64: =IF(OR(J32=0,J32=""),"",J64/J32) | L64: =L61+L62+L63 -> 0 | M64: =IF(OR(L32=0,L32=""),"",L64/L32)
A65: Total Labor Costs and Related Expenses | B65: =B59+B64 -> 0 | C65: =IF(OR(B32=0,B32=""),"",B65/B32) | D65: =D59+D64 -> 0 | E65: =IF(OR(D32=0,D32=""),"",D65/D32) | F65: =F59+F64 -> 0 | G65: =IF(OR(F32=0,F32=""),"",F65/F32) | H65: =H59+H64 -> 0 | I65: =IF(OR(H32=0,H32=""),"",H65/H32) | J65: =J59+J64 -> 0 | K65: =IF(OR(J32=0,J32=""),"",J65/J32) | L65: =L59+L64 -> 0 | M65: =IF(OR(L32=0,L32=""),"",L65/L32)
A66: Other Expenses
A67: Banquet Expenses | C67: =IF(OR(B32=0,B32=""),"",B67/B32) | E67: =IF(OR(D32=0,D32=""),"",D67/D32) | G67: =IF(OR(F32=0,F32=""),"",F67/F32) | I67: =IF(OR(H32=0,H32=""),"",H67/H32) | K67: =IF(OR(J32=0,J32=""),"",J67/J32) | M67: =IF(OR(L32=0,L32=""),"",L67/L32)
A68: China | C68: =IF(OR(B32=0,B32=""),"",B68/B32) | E68: =IF(OR(D32=0,D32=""),"",D68/D32) | G68: =IF(OR(F32=0,F32=""),"",F68/F32) | I68: =IF(OR(H32=0,H32=""),"",H68/H32) | K68: =IF(OR(J32=0,J32=""),"",J68/J32) | M68: =IF(OR(L32=0,L32=""),"",L68/L32)
A69: Cleaning Supplies | C69: =IF(OR(B32=0,B32=""),"",B69/B32) | E69: =IF(OR(D32=0,D32=""),"",D69/D32) | G69: =IF(OR(F32=0,F32=""),"",F69/F32) | I69: =IF(OR(H32=0,H32=""),"",H69/H32) | K69: =IF(OR(J32=0,J32=""),"",J69/J32) | M69: =IF(OR(L32=0,L32=""),"",L69/L32)
A70: Cluster Services | C70: =IF(OR(B32=0,B32=""),"",B70/B32) | E70: =IF(OR(D32=0,D32=""),"",D70/D32) | G70: =IF(OR(F32=0,F32=""),"",F70/F32) | I70: =IF(OR(H32=0,H32=""),"",H70/H32) | K70: =IF(OR(J32=0,J32=""),"",J70/J32) | M70: =IF(OR(L32=0,L32=""),"",L70/L32)
A71: Commissions | C71: =IF(OR(B32=0,B32=""),"",B71/B32) | E71: =IF(OR(D32=0,D32=""),"",D71/D32) | G71: =IF(OR(F32=0,F32=""),"",F71/F32) | I71: =IF(OR(H32=0,H32=""),"",H71/H32) | K71: =IF(OR(J32=0,J32=""),"",J71/J32) | M71: =IF(OR(L32=0,L32=""),"",L71/L32)
A72: Complimentary Services and Gifts | C72: =IF(OR(B32=0,B32=""),"",B72/B32) | E72: =IF(OR(D32=0,D32=""),"",D72/D32) | G72: =IF(OR(F32=0,F32=""),"",F72/F32) | I72: =IF(OR(H32=0,H32=""),"",H72/H32) | K72: =IF(OR(J32=0,J32=""),"",J72/J32) | M72: =IF(OR(L32=0,L32=""),"",L72/L32)
A73: Contract Services | C73: =IF(OR(B32=0,B32=""),"",B73/B32) | E73: =IF(OR(D32=0,D32=""),"",D73/D32) | G73: =IF(OR(F32=0,F32=""),"",F73/F32) | I73: =IF(OR(H32=0,H32=""),"",H73/H32) | K73: =IF(OR(J32=0,J32=""),"",J73/J32) | M73: =IF(OR(L32=0,L32=""),"",L73/L32)
A74: Corporate Office Reimbursables | C74: =IF(OR(B32=0,B32=""),"",B74/B32) | E74: =IF(OR(D32=0,D32=""),"",D74/D32) | G74: =IF(OR(F32=0,F32=""),"",F74/F32) | I74: =IF(OR(H32=0,H32=""),"",H74/H32) | K74: =IF(OR(J32=0,J32=""),"",J74/J32) | M74: =IF(OR(L32=0,L32=""),"",L74/L32)
A75: Decorations | C75: =IF(OR(B32=0,B32=""),"",B75/B32) | E75: =IF(OR(D32=0,D32=""),"",D75/D32) | G75: =IF(OR(F32=0,F32=""),"",F75/F32) | I75: =IF(OR(H32=0,H32=""),"",H75/H32) | K75: =IF(OR(J32=0,J32=""),"",J75/J32) | M75: =IF(OR(L32=0,L32=""),"",L75/L32)
A76: Dishwashing Supplies | C76: =IF(OR(B32=0,B32=""),"",B76/B32) | E76: =IF(OR(D32=0,D32=""),"",D76/D32) | G76: =IF(OR(F32=0,F32=""),"",F76/F32) | I76: =IF(OR(H32=0,H32=""),"",H76/H32) | K76: =IF(OR(J32=0,J32=""),"",J76/J32) | M76: =IF(OR(L32=0,L32=""),"",L76/L32)
A77: Dues and Subscriptions | C77: =IF(OR(B32=0,B32=""),"",B77/B32) | E77: =IF(OR(D32=0,D32=""),"",D77/D32) | G77: =IF(OR(F32=0,F32=""),"",F77/F32) | I77: =IF(OR(H32=0,H32=""),"",H77/H32) | K77: =IF(OR(J32=0,J32=""),"",J77/J32) | M77: =IF(OR(L32=0,L32=""),"",L77/L32)
A78: Entertainment - In-House | C78: =IF(OR(B32=0,B32=""),"",B78/B32) | E78: =IF(OR(D32=0,D32=""),"",D78/D32) | G78: =IF(OR(F32=0,F32=""),"",F78/F32) | I78: =IF(OR(H32=0,H32=""),"",H78/H32) | K78: =IF(OR(J32=0,J32=""),"",J78/J32) | M78: =IF(OR(L32=0,L32=""),"",L78/L32)
A79: Equipment Rental | C79: =IF(OR(B32=0,B32=""),"",B79/B32) | E79: =IF(OR(D32=0,D32=""),"",D79/D32) | G79: =IF(OR(F32=0,F32=""),"",F79/F32) | I79: =IF(OR(H32=0,H32=""),"",H79/H32) | K79: =IF(OR(J32=0,J32=""),"",J79/J32) | M79: =IF(OR(L32=0,L32=""),"",L79/L32)
A80: Flatware | C80: =IF(OR(B32=0,B32=""),"",B80/B32) | E80: =IF(OR(D32=0,D32=""),"",D80/D32) | G80: =IF(OR(F32=0,F32=""),"",F80/F32) | I80: =IF(OR(H32=0,H32=""),"",H80/H32) | K80: =IF(OR(J32=0,J32=""),"",J80/J32) | M80: =IF(OR(L32=0,L32=""),"",L80/L32)
A81: Glassware | C81: =IF(OR(B32=0,B32=""),"",B81/B32) | E81: =IF(OR(D32=0,D32=""),"",D81/D32) | G81: =IF(OR(F32=0,F32=""),"",F81/F32) | I81: =IF(OR(H32=0,H32=""),"",H81/H32) | K81: =IF(OR(J32=0,J32=""),"",J81/J32) | M81: =IF(OR(L32=0,L32=""),"",L81/L32)
A82: Ice | C82: =IF(OR(B32=0,B32=""),"",B82/B32) | E82: =IF(OR(D32=0,D32=""),"",D82/D32) | G82: =IF(OR(F32=0,F32=""),"",F82/F32) | I82: =IF(OR(H32=0,H32=""),"",H82/H32) | K82: =IF(OR(J32=0,J32=""),"",J82/J32) | M82: =IF(OR(L32=0,L32=""),"",L82/L32)
A83: Kitchen Fuel | C83: =IF(OR(B32=0,B32=""),"",B83/B32) | E83: =IF(OR(D32=0,D32=""),"",D83/D32) | G83: =IF(OR(F32=0,F32=""),"",F83/F32) | I83: =IF(OR(H32=0,H32=""),"",H83/H32) | K83: =IF(OR(J32=0,J32=""),"",J83/J32) | M83: =IF(OR(L32=0,L32=""),"",L83/L32)
A84: Kitchen Smallwares | C84: =IF(OR(B32=0,B32=""),"",B84/B32) | E84: =IF(OR(D32=0,D32=""),"",D84/D32) | G84: =IF(OR(F32=0,F32=""),"",F84/F32) | I84: =IF(OR(H32=0,H32=""),"",H84/H32) | K84: =IF(OR(J32=0,J32=""),"",J84/J32) | M84: =IF(OR(L32=0,L32=""),"",L84/L32)
A85: Laundry and Dry Cleaning | C85: =IF(OR(B32=0,B32=""),"",B85/B32) | E85: =IF(OR(D32=0,D32=""),"",D85/D32) | G85: =IF(OR(F32=0,F32=""),"",F85/F32) | I85: =IF(OR(H32=0,H32=""),"",H85/H32) | K85: =IF(OR(J32=0,J32=""),"",J85/J32) | M85: =IF(OR(L32=0,L32=""),"",L85/L32)
A86: Licenses and Permits | C86: =IF(OR(B32=0,B32=""),"",B86/B32) | E86: =IF(OR(D32=0,D32=""),"",D86/D32) | G86: =IF(OR(F32=0,F32=""),"",F86/F32) | I86: =IF(OR(H32=0,H32=""),"",H86/H32) | K86: =IF(OR(J32=0,J32=""),"",J86/J32) | M86: =IF(OR(L32=0,L32=""),"",L86/L32)
A87: Linen | C87: =IF(OR(B32=0,B32=""),"",B87/B32) | E87: =IF(OR(D32=0,D32=""),"",D87/D32) | G87: =IF(OR(F32=0,F32=""),"",F87/F32) | I87: =IF(OR(H32=0,H32=""),"",H87/H32) | K87: =IF(OR(J32=0,J32=""),"",J87/J32) | M87: =IF(OR(L32=0,L32=""),"",L87/L32)
A88: Management Fees | C88: =IF(OR(B32=0,B32=""),"",B88/B32) | E88: =IF(OR(D32=0,D32=""),"",D88/D32) | G88: =IF(OR(F32=0,F32=""),"",F88/F32) | I88: =IF(OR(H32=0,H32=""),"",H88/H32) | K88: =IF(OR(J32=0,J32=""),"",J88/J32) | M88: =IF(OR(L32=0,L32=""),"",L88/L32)
A89: Menus and Beverage Lists | C89: =IF(OR(B32=0,B32=""),"",B89/B32) | E89: =IF(OR(D32=0,D32=""),"",D89/D32) | G89: =IF(OR(F32=0,F32=""),"",F89/F32) | I89: =IF(OR(H32=0,H32=""),"",H89/H32) | K89: =IF(OR(J32=0,J32=""),"",J89/J32) | M89: =IF(OR(L32=0,L32=""),"",L89/L32)
A90: Miscellaneous | C90: =IF(OR(B32=0,B32=""),"",B90/B32) | E90: =IF(OR(D32=0,D32=""),"",D90/D32) | G90: =IF(OR(F32=0,F32=""),"",F90/F32) | I90: =IF(OR(H32=0,H32=""),"",H90/H32) | K90: =IF(OR(J32=0,J32=""),"",J90/J32) | M90: =IF(OR(L32=0,L32=""),"",L90/L32)
A91: Music and Entertainment | C91: =IF(OR(B32=0,B32=""),"",B91/B32) | E91: =IF(OR(D32=0,D32=""),"",D91/D32) | G91: =IF(OR(F32=0,F32=""),"",F91/F32) | I91: =IF(OR(H32=0,H32=""),"",H91/H32) | K91: =IF(OR(J32=0,J32=""),"",J91/J32) | M91: =IF(OR(L32=0,L32=""),"",L91/L32)
A92: Operating Supplies | C92: =IF(OR(B32=0,B32=""),"",B92/B32) | E92: =IF(OR(D32=0,D32=""),"",D92/D32) | G92: =IF(OR(F32=0,F32=""),"",F92/F32) | I92: =IF(OR(H32=0,H32=""),"",H92/H32) | K92: =IF(OR(J32=0,J32=""),"",J92/J32) | M92: =IF(OR(L32=0,L32=""),"",L92/L32)
A93: Paper and Plastics | C93: =IF(OR(B32=0,B32=""),"",B93/B32) | E93: =IF(OR(D32=0,D32=""),"",D93/D32) | G93: =IF(OR(F32=0,F32=""),"",F93/F32) | I93: =IF(OR(H32=0,H32=""),"",H93/H32) | K93: =IF(OR(J32=0,J32=""),"",J93/J32) | M93: =IF(OR(L32=0,L32=""),"",L93/L32)
A94: Postage and Overnight Delivery Charges | C94: =IF(OR(B32=0,B32=""),"",B94/B32) | E94: =IF(OR(D32=0,D32=""),"",D94/D32) | G94: =IF(OR(F32=0,F32=""),"",F94/F32) | I94: =IF(OR(H32=0,H32=""),"",H94/H32) | K94: =IF(OR(J32=0,J32=""),"",J94/J32) | M94: =IF(OR(L32=0,L32=""),"",L94/L32)
A95: Printing and Stationery | C95: =IF(OR(B32=0,B32=""),"",B95/B32) | E95: =IF(OR(D32=0,D32=""),"",D95/D32) | G95: =IF(OR(F32=0,F32=""),"",F95/F32) | I95: =IF(OR(H32=0,H32=""),"",H95/H32) | K95: =IF(OR(J32=0,J32=""),"",J95/J32) | M95: =IF(OR(L32=0,L32=""),"",L95/L32)
A96: Reservations | C96: =IF(OR(B32=0,B32=""),"",B96/B32) | E96: =IF(OR(D32=0,D32=""),"",D96/D32) | G96: =IF(OR(F32=0,F32=""),"",F96/F32) | I96: =IF(OR(H32=0,H32=""),"",H96/H32) | K96: =IF(OR(J32=0,J32=""),"",J96/J32) | M96: =IF(OR(L32=0,L32=""),"",L96/L32)
A97: Royalty Fees | C97: =IF(OR(B32=0,B32=""),"",B97/B32) | E97: =IF(OR(D32=0,D32=""),"",D97/D32) | G97: =IF(OR(F32=0,F32=""),"",F97/F32) | I97: =IF(OR(H32=0,H32=""),"",H97/H32) | K97: =IF(OR(J32=0,J32=""),"",J97/J32) | M97: =IF(OR(L32=0,L32=""),"",L97/L32)
A98: Training | C98: =IF(OR(B32=0,B32=""),"",B98/B32) | E98: =IF(OR(D32=0,D32=""),"",D98/D32) | G98: =IF(OR(F32=0,F32=""),"",F98/F32) | I98: =IF(OR(H32=0,H32=""),"",H98/H32) | K98: =IF(OR(J32=0,J32=""),"",J98/J32) | M98: =IF(OR(L32=0,L32=""),"",L98/L32)
A99: Travel - Meals and Entertainment | C99: =IF(OR(B32=0,B32=""),"",B99/B32) | E99: =IF(OR(D32=0,D32=""),"",D99/D32) | G99: =IF(OR(F32=0,F32=""),"",F99/F32) | I99: =IF(OR(H32=0,H32=""),"",H99/H32) | K99: =IF(OR(J32=0,J32=""),"",J99/J32) | M99: =IF(OR(L32=0,L32=""),"",L99/L32)
A100: Travel - Other | C100: =IF(OR(B32=0,B32=""),"",B100/B32) | E100: =IF(OR(D32=0,D32=""),"",D100/D32) | G100: =IF(OR(F32=0,F32=""),"",F100/F32) | I100: =IF(OR(H32=0,H32=""),"",H100/H32) | K100: =IF(OR(J32=0,J32=""),"",J100/J32) | M100: =IF(OR(L32=0,L32=""),"",L100/L32)
...

Sheet Schedule 3 - Other Op Depts
A1: OTHER OPERATED DEPARTMENTS — SCHEDULE 3
A2: Property: | B2: ='Setup & Assumptions'!$B$4 -> Enter property name | H2: Period / Year: | J2: ='Setup & Assumptions'!$B$5 -> e.g. January 2026 / FY2026
A3: Roll-up of all Other Operated Departments and the consolidated Minor Operated Departments. Use the sub-schedules to build each department, then enter the totals here.
B4: Current Period | H4: Year-To-Date
B5: Actual | D5: Forecast / Budget | F5: Prior Year | H5: Actual | J5: Forecast / Budget | L5: Prior Year
A6: Line Item | B6: $ | C6: % | D6: $ | E6: % | F6: $ | G6: % | H6: $ | I6: % | J6: $ | K6: % | L6: $ | M6: %
A7: Departmental Revenue
A8: Other Operated Department 1 | C8: =IF(OR(B13=0,B13=""),"",B8/B13) | E8: =IF(OR(D13=0,D13=""),"",D8/D13) | G8: =IF(OR(F13=0,F13=""),"",F8/F13) | I8: =IF(OR(H13=0,H13=""),"",H8/H13) | K8: =IF(OR(J13=0,J13=""),"",J8/J13) | M8: =IF(OR(L13=0,L13=""),"",L8/L13)
A9: Other Operated Department 2 | C9: =IF(OR(B13=0,B13=""),"",B9/B13) | E9: =IF(OR(D13=0,D13=""),"",D9/D13) | G9: =IF(OR(F13=0,F13=""),"",F9/F13) | I9: =IF(OR(H13=0,H13=""),"",H9/H13) | K9: =IF(OR(J13=0,J13=""),"",J9/J13) | M9: =IF(OR(L13=0,L13=""),"",L9/L13)
A10: Other Operated Department 3 | C10: =IF(OR(B13=0,B13=""),"",B10/B13) | E10: =IF(OR(D13=0,D13=""),"",D10/D13) | G10: =IF(OR(F13=0,F13=""),"",F10/F13) | I10: =IF(OR(H13=0,H13=""),"",H10/H13) | K10: =IF(OR(J13=0,J13=""),"",J10/J13) | M10: =IF(OR(L13=0,L13=""),"",L10/L13)
A11: Other Operated Department 4 | C11: =IF(OR(B13=0,B13=""),"",B11/B13) | E11: =IF(OR(D13=0,D13=""),"",D11/D13) | G11: =IF(OR(F13=0,F13=""),"",F11/F13) | I11: =IF(OR(H13=0,H13=""),"",H11/H13) | K11: =IF(OR(J13=0,J13=""),"",J11/J13) | M11: =IF(OR(L13=0,L13=""),"",L11/L13)
A12: Minor Operated Departments | C12: =IF(OR(B13=0,B13=""),"",B12/B13) | E12: =IF(OR(D13=0,D13=""),"",D12/D13) | G12: =IF(OR(F13=0,F13=""),"",F12/F13) | I12: =IF(OR(H13=0,H13=""),"",H12/H13) | K12: =IF(OR(J13=0,J13=""),"",J12/J13) | M12: =IF(OR(L13=0,L13=""),"",L12/L13)
A13: Total Departmental Revenue | B13: =B8+B9+B10+B11+B12 -> 0 | C13: =IF(OR(B13=0,B13=""),"",B13/B13) | D13: =D8+D9+D10+D11+D12 -> 0 | E13: =IF(OR(D13=0,D13=""),"",D13/D13) | F13: =F8+F9+F10+F11+F12 -> 0 | G13: =IF(OR(F13=0,F13=""),"",F13/F13) | H13: =H8+H9+H10+H11+H12 -> 0 | I13: =IF(OR(H13=0,H13=""),"",H13/H13) | J13: =J8+J9+J10+J11+J12 -> 0 | K13: =IF(OR(J13=0,J13=""),"",J13/J13) | L13: =L8+L9+L10+L11+L12 -> 0 | M13: =IF(OR(L13=0,L13=""),"",L13/L13)
A14: Departmental Expenses (Cost of Sales + Total Expenses)
A15: Other Operated Department 1 | C15: =IF(OR(B13=0,B13=""),"",B15/B13) | E15: =IF(OR(D13=0,D13=""),"",D15/D13) | G15: =IF(OR(F13=0,F13=""),"",F15/F13) | I15: =IF(OR(H13=0,H13=""),"",H15/H13) | K15: =IF(OR(J13=0,J13=""),"",J15/J13) | M15: =IF(OR(L13=0,L13=""),"",L15/L13)
A16: Other Operated Department 2 | C16: =IF(OR(B13=0,B13=""),"",B16/B13) | E16: =IF(OR(D13=0,D13=""),"",D16/D13) | G16: =IF(OR(F13=0,F13=""),"",F16/F13) | I16: =IF(OR(H13=0,H13=""),"",H16/H13) | K16: =IF(OR(J13=0,J13=""),"",J16/J13) | M16: =IF(OR(L13=0,L13=""),"",L16/L13)
A17: Other Operated Department 3 | C17: =IF(OR(B13=0,B13=""),"",B17/B13) | E17: =IF(OR(D13=0,D13=""),"",D17/D13) | G17: =IF(OR(F13=0,F13=""),"",F17/F13) | I17: =IF(OR(H13=0,H13=""),"",H17/H13) | K17: =IF(OR(J13=0,J13=""),"",J17/J13) | M17: =IF(OR(L13=0,L13=""),"",L17/L13)
A18: Other Operated Department 4 | C18: =IF(OR(B13=0,B13=""),"",B18/B13) | E18: =IF(OR(D13=0,D13=""),"",D18/D13) | G18: =IF(OR(F13=0,F13=""),"",F18/F13) | I18: =IF(OR(H13=0,H13=""),"",H18/H13) | K18: =IF(OR(J13=0,J13=""),"",J18/J13) | M18: =IF(OR(L13=0,L13=""),"",L18/L13)
A19: Minor Operated Departments | C19: =IF(OR(B13=0,B13=""),"",B19/B13) | E19: =IF(OR(D13=0,D13=""),"",D19/D13) | G19: =IF(OR(F13=0,F13=""),"",F19/F13) | I19: =IF(OR(H13=0,H13=""),"",H19/H13) | K19: =IF(OR(J13=0,J13=""),"",J19/J13) | M19: =IF(OR(L13=0,L13=""),"",L19/L13)
A20: Total Departmental Expenses | B20: =B15+B16+B17+B18+B19 -> 0 | C20: =IF(OR(B13=0,B13=""),"",B20/B13) | D20: =D15+D16+D17+D18+D19 -> 0 | E20: =IF(OR(D13=0,D13=""),"",D20/D13) | F20: =F15+F16+F17+F18+F19 -> 0 | G20: =IF(OR(F13=0,F13=""),"",F20/F13) | H20: =H15+H16+H17+H18+H19 -> 0 | I20: =IF(OR(H13=0,H13=""),"",H20/H13) | J20: =J15+J16+J17+J18+J19 -> 0 | K20: =IF(OR(J13=0,J13=""),"",J20/J13) | L20: =L15+L16+L17+L18+L19 -> 0 | M20: =IF(OR(L13=0,L13=""),"",L20/L13)
A21: Departmental Profit
A22: Other Operated Department 1 | B22: =B8-B15 -> 0 | C22: =IF(OR(B13=0,B13=""),"",B22/B13) | D22: =D8-D15 -> 0 | E22: =IF(OR(D13=0,D13=""),"",D22/D13) | F22: =F8-F15 -> 0 | G22: =IF(OR(F13=0,F13=""),"",F22/F13) | H22: =H8-H15 -> 0 | I22: =IF(OR(H13=0,H13=""),"",H22/H13) | J22: =J8-J15 -> 0 | K22: =IF(OR(J13=0,J13=""),"",J22/J13) | L22: =L8-L15 -> 0 | M22: =IF(OR(L13=0,L13=""),"",L22/L13)
A23: Other Operated Department 2 | B23: =B9-B16 -> 0 | C23: =IF(OR(B13=0,B13=""),"",B23/B13) | D23: =D9-D16 -> 0 | E23: =IF(OR(D13=0,D13=""),"",D23/D13) | F23: =F9-F16 -> 0 | G23: =IF(OR(F13=0,F13=""),"",F23/F13) | H23: =H9-H16 -> 0 | I23: =IF(OR(H13=0,H13=""),"",H23/H13) | J23: =J9-J16 -> 0 | K23: =IF(OR(J13=0,J13=""),"",J23/J13) | L23: =L9-L16 -> 0 | M23: =IF(OR(L13=0,L13=""),"",L23/L13)
A24: Other Operated Department 3 | B24: =B10-B17 -> 0 | C24: =IF(OR(B13=0,B13=""),"",B24/B13) | D24: =D10-D17 -> 0 | E24: =IF(OR(D13=0,D13=""),"",D24/D13) | F24: =F10-F17 -> 0 | G24: =IF(OR(F13=0,F13=""),"",F24/F13) | H24: =H10-H17 -> 0 | I24: =IF(OR(H13=0,H13=""),"",H24/H13) | J24: =J10-J17 -> 0 | K24: =IF(OR(J13=0,J13=""),"",J24/J13) | L24: =L10-L17 -> 0 | M24: =IF(OR(L13=0,L13=""),"",L24/L13)
A25: Other Operated Department 4 | B25: =B11-B18 -> 0 | C25: =IF(OR(B13=0,B13=""),"",B25/B13) | D25: =D11-D18 -> 0 | E25: =IF(OR(D13=0,D13=""),"",D25/D13) | F25: =F11-F18 -> 0 | G25: =IF(OR(F13=0,F13=""),"",F25/F13) | H25: =H11-H18 -> 0 | I25: =IF(OR(H13=0,H13=""),"",H25/H13) | J25: =J11-J18 -> 0 | K25: =IF(OR(J13=0,J13=""),"",J25/J13) | L25: =L11-L18 -> 0 | M25: =IF(OR(L13=0,L13=""),"",L25/L13)
A26: Minor Operated Departments | B26: =B12-B19 -> 0 | C26: =IF(OR(B13=0,B13=""),"",B26/B13) | D26: =D12-D19 -> 0 | E26: =IF(OR(D13=0,D13=""),"",D26/D13) | F26: =F12-F19 -> 0 | G26: =IF(OR(F13=0,F13=""),"",F26/F13) | H26: =H12-H19 -> 0 | I26: =IF(OR(H13=0,H13=""),"",H26/H13) | J26: =J12-J19 -> 0 | K26: =IF(OR(J13=0,J13=""),"",J26/J13) | L26: =L12-L19 -> 0 | M26: =IF(OR(L13=0,L13=""),"",L26/L13)
A27: Total Other Operated Department Profit | B27: =B13-B20 -> 0 | C27: =IF(OR(B13=0,B13=""),"",B27/B13) | D27: =D13-D20 -> 0 | E27: =IF(OR(D13=0,D13=""),"",D27/D13) | F27: =F13-F20 -> 0 | G27: =IF(OR(F13=0,F13=""),"",F27/F13) | H27: =H13-H20 -> 0 | I27: =IF(OR(H13=0,H13=""),"",H27/H13) | J27: =J13-J20 -> 0 | K27: =IF(OR(J13=0,J13=""),"",J27/J13) | L27: =L13-L20 -> 0 | M27: =IF(OR(L13=0,L13=""),"",L27/L13)

Sheet Sub-Sch 3-1 - Golf
A1: GOLF COURSE AND PRO SHOP — SUB-SCHEDULE 3-1
A2: Property: | B2: ='Setup & Assumptions'!$B$4 -> Enter property name | H2: Period / Year: | J2: ='Setup & Assumptions'!$B$5 -> e.g. January 2026 / FY2026
B4: Current Period | H4: Year-To-Date
B5: Actual | D5: Forecast / Budget | F5: Prior Year | H5: Actual | J5: Forecast / Budget | L5: Prior Year
A6: Line Item | B6: $ | C6: % | D6: $ | E6: % | F6: $ | G6: % | H6: $ | I6: % | J6: $ | K6: % | L6: $ | M6: %
A7: Revenue
A8: Greens Fee Revenue | C8: =IF(OR(B21=0,B21=""),"",B8/B21) | E8: =IF(OR(D21=0,D21=""),"",D8/D21) | G8: =IF(OR(F21=0,F21=""),"",F8/F21) | I8: =IF(OR(H21=0,H21=""),"",H8/H21) | K8: =IF(OR(J21=0,J21=""),"",J8/J21) | M8: =IF(OR(L21=0,L21=""),"",L8/L21)
A9: Tournament Fee Revenue | C9: =IF(OR(B21=0,B21=""),"",B9/B21) | E9: =IF(OR(D21=0,D21=""),"",D9/D21) | G9: =IF(OR(F21=0,F21=""),"",F9/F21) | I9: =IF(OR(H21=0,H21=""),"",H9/H21) | K9: =IF(OR(J21=0,J21=""),"",J9/J21) | M9: =IF(OR(L21=0,L21=""),"",L9/L21)
A10: Golf Cart Rental Revenue | C10: =IF(OR(B21=0,B21=""),"",B10/B21) | E10: =IF(OR(D21=0,D21=""),"",D10/D21) | G10: =IF(OR(F21=0,F21=""),"",F10/F21) | I10: =IF(OR(H21=0,H21=""),"",H10/H21) | K10: =IF(OR(J21=0,J21=""),"",J10/J21) | M10: =IF(OR(L21=0,L21=""),"",L10/L21)
A11: Golf Equipment Rental Revenue | C11: =IF(OR(B21=0,B21=""),"",B11/B21) | E11: =IF(OR(D21=0,D21=""),"",D11/D21) | G11: =IF(OR(F21=0,F21=""),"",F11/F21) | I11: =IF(OR(H21=0,H21=""),"",H11/H21) | K11: =IF(OR(J21=0,J21=""),"",J11/J21) | M11: =IF(OR(L21=0,L21=""),"",L11/L21)
A12: Practice Range Fee Revenue | C12: =IF(OR(B21=0,B21=""),"",B12/B21) | E12: =IF(OR(D21=0,D21=""),"",D12/D21) | G12: =IF(OR(F21=0,F21=""),"",F12/F21) | I12: =IF(OR(H21=0,H21=""),"",H12/H21) | K12: =IF(OR(J21=0,J21=""),"",J12/J21) | M12: =IF(OR(L21=0,L21=""),"",L12/L21)
A13: Lesson Fee Revenue | C13: =IF(OR(B21=0,B21=""),"",B13/B21) | E13: =IF(OR(D21=0,D21=""),"",D13/D21) | G13: =IF(OR(F21=0,F21=""),"",F13/F21) | I13: =IF(OR(H21=0,H21=""),"",H13/H21) | K13: =IF(OR(J21=0,J21=""),"",J13/J21) | M13: =IF(OR(L21=0,L21=""),"",L13/L21)
A14: Golf Club Maintenance Revenue | C14: =IF(OR(B21=0,B21=""),"",B14/B21) | E14: =IF(OR(D21=0,D21=""),"",D14/D21) | G14: =IF(OR(F21=0,F21=""),"",F14/F21) | I14: =IF(OR(H21=0,H21=""),"",H14/H21) | K14: =IF(OR(J21=0,J21=""),"",J14/J21) | M14: =IF(OR(L21=0,L21=""),"",L14/L21)
A15: Storage Fee Revenue | C15: =IF(OR(B21=0,B21=""),"",B15/B21) | E15: =IF(OR(D21=0,D21=""),"",D15/D21) | G15: =IF(OR(F21=0,F21=""),"",F15/F21) | I15: =IF(OR(H21=0,H21=""),"",H15/H21) | K15: =IF(OR(J21=0,J21=""),"",J15/J21) | M15: =IF(OR(L21=0,L21=""),"",L15/L21)
A16: Membership Fee Revenue | C16: =IF(OR(B21=0,B21=""),"",B16/B21) | E16: =IF(OR(D21=0,D21=""),"",D16/D21) | G16: =IF(OR(F21=0,F21=""),"",F16/F21) | I16: =IF(OR(H21=0,H21=""),"",H16/H21) | K16: =IF(OR(J21=0,J21=""),"",J16/J21) | M16: =IF(OR(L21=0,L21=""),"",L16/L21)
A17: Merchandise Revenue | C17: =IF(OR(B21=0,B21=""),"",B17/B21) | E17: =IF(OR(D21=0,D21=""),"",D17/D21) | G17: =IF(OR(F21=0,F21=""),"",F17/F21) | I17: =IF(OR(H21=0,H21=""),"",H17/H21) | K17: =IF(OR(J21=0,J21=""),"",J17/J21) | M17: =IF(OR(L21=0,L21=""),"",L17/L21)
A18: Clothing Revenue | C18: =IF(OR(B21=0,B21=""),"",B18/B21) | E18: =IF(OR(D21=0,D21=""),"",D18/D21) | G18: =IF(OR(F21=0,F21=""),"",F18/F21) | I18: =IF(OR(H21=0,H21=""),"",H18/H21) | K18: =IF(OR(J21=0,J21=""),"",J18/J21) | M18: =IF(OR(L21=0,L21=""),"",L18/L21)
A19: Other Revenue | C19: =IF(OR(B21=0,B21=""),"",B19/B21) | E19: =IF(OR(D21=0,D21=""),"",D19/D21) | G19: =IF(OR(F21=0,F21=""),"",F19/F21) | I19: =IF(OR(H21=0,H21=""),"",H19/H21) | K19: =IF(OR(J21=0,J21=""),"",J19/J21) | M19: =IF(OR(L21=0,L21=""),"",L19/L21)
A20: Less: Allowances | C20: =IF(OR(B21=0,B21=""),"",B20/B21) | E20: =IF(OR(D21=0,D21=""),"",D20/D21) | G20: =IF(OR(F21=0,F21=""),"",F20/F21) | I20: =IF(OR(H21=0,H21=""),"",H20/H21) | K20: =IF(OR(J21=0,J21=""),"",J20/J21) | M20: =IF(OR(L21=0,L21=""),"",L20/L21)
A21: Total Golf Revenue | B21: =B8+B9+B10+B11+B12+B13+B14+B15+B16+B17+B18+B19-B20 -> 0 | C21: =IF(OR(B21=0,B21=""),"",B21/B21) | D21: =D8+D9+D10+D11+D12+D13+D14+D15+D16+D17+D18+D19-D20 -> 0 | E21: =IF(OR(D21=0,D21=""),"",D21/D21) | F21: =F8+F9+F10+F11+F12+F13+F14+F15+F16+F17+F18+F19-F20 -> 0 | G21: =IF(OR(F21=0,F21=""),"",F21/F21) | H21: =H8+H9+H10+H11+H12+H13+H14+H15+H16+H17+H18+H19-H20 -> 0 | I21: =IF(OR(H21=0,H21=""),"",H21/H21) | J21: =J8+J9+J10+J11+J12+J13+J14+J15+J16+J17+J18+J19-J20 -> 0 | K21: =IF(OR(J21=0,J21=""),"",J21/J21) | L21: =L8+L9+L10+L11+L12+L13+L14+L15+L16+L17+L18+L19-L20 -> 0 | M21: =IF(OR(L21=0,L21=""),"",L21/L21)
A22: Cost of Sales
A23: Cost of Merchandise Sales | C23: =IF(OR(B21=0,B21=""),"",B23/B21) | E23: =IF(OR(D21=0,D21=""),"",D23/D21) | G23: =IF(OR(F21=0,F21=""),"",F23/F21) | I23: =IF(OR(H21=0,H21=""),"",H23/H21) | K23: =IF(OR(J21=0,J21=""),"",J23/J21) | M23: =IF(OR(L21=0,L21=""),"",L23/L21)
A24: Cost of Clothing Sales | C24: =IF(OR(B21=0,B21=""),"",B24/B21) | E24: =IF(OR(D21=0,D21=""),"",D24/D21) | G24: =IF(OR(F21=0,F21=""),"",F24/F21) | I24: =IF(OR(H21=0,H21=""),"",H24/H21) | K24: =IF(OR(J21=0,J21=""),"",J24/J21) | M24: =IF(OR(L21=0,L21=""),"",L24/L21)
A25: Total Cost of Sales | B25: =B23+B24 -> 0 | C25: =IF(OR(B21=0,B21=""),"",B25/B21) | D25: =D23+D24 -> 0 | E25: =IF(OR(D21=0,D21=""),"",D25/D21) | F25: =F23+F24 -> 0 | G25: =IF(OR(F21=0,F21=""),"",F25/F21) | H25: =H23+H24 -> 0 | I25: =IF(OR(H21=0,H21=""),"",H25/H21) | J25: =J23+J24 -> 0 | K25: =IF(OR(J21=0,J21=""),"",J25/J21) | L25: =L23+L24 -> 0 | M25: =IF(OR(L21=0,L21=""),"",L25/L21)
A26: Gross Profit | B26: =B21-B25 -> 0 | C26: =IF(OR(B21=0,B21=""),"",B26/B21) | D26: =D21-D25 -> 0 | E26: =IF(OR(D21=0,D21=""),"",D26/D21) | F26: =F21-F25 -> 0 | G26: =IF(OR(F21=0,F21=""),"",F26/F21) | H26: =H21-H25 -> 0 | I26: =IF(OR(H21=0,H21=""),"",H26/H21) | J26: =J21-J25 -> 0 | K26: =IF(OR(J21=0,J21=""),"",J26/J21) | L26: =L21-L25 -> 0 | M26: =IF(OR(L21=0,L21=""),"",L26/L21)
A27: Expenses
A28: Labor Costs and Related Expenses
A29: Salaries, Wages, Service Charges, Contracted Labor and Bonuses
A30: Salaries and Wages
A31: Management
A32: Non-Management
A33: Golf Pros/Operations
A34: Greens/Maintenance
A35: Pro Shop
A36: Sub-Total: Salaries and Wages | B36: =B31+B33+B34+B35 -> 0 | D36: =D31+D33+D34+D35 -> 0 | F36: =F31+F33+F34+F35 -> 0 | H36: =H31+H33+H34+H35 -> 0 | J36: =J31+J33+J34+J35 -> 0 | L36: =L31+L33+L34+L35 -> 0
A37: Service Charge Distribution
A38: Contracted, Leased and Outsourced Labor
A39: Bonuses and Incentives
A40: Total Salaries, Wages, Service Charges, Contracted Labor and Bonuses | B40: =B36+B37+B38+B39 -> 0 | C40: =IF(OR(B21=0,B21=""),"",B40/B21) | D40: =D36+D37+D38+D39 -> 0 | E40: =IF(OR(D21=0,D21=""),"",D40/D21) | F40: =F36+F37+F38+F39 -> 0 | G40: =IF(OR(F21=0,F21=""),"",F40/F21) | H40: =H36+H37+H38+H39 -> 0 | I40: =IF(OR(H21=0,H21=""),"",H40/H21) | J40: =J36+J37+J38+J39 -> 0 | K40: =IF(OR(J21=0,J21=""),"",J40/J21) | L40: =L36+L37+L38+L39 -> 0 | M40: =IF(OR(L21=0,L21=""),"",L40/L21)
A41: Payroll-Related Expenses
A42: Payroll Taxes | C42: =IF(OR(B21=0,B21=""),"",B42/B21) | E42: =IF(OR(D21=0,D21=""),"",D42/D21) | G42: =IF(OR(F21=0,F21=""),"",F42/F21) | I42: =IF(OR(H21=0,H21=""),"",H42/H21) | K42: =IF(OR(J21=0,J21=""),"",J42/J21) | M42: =IF(OR(L21=0,L21=""),"",L42/L21)
A43: Supplemental Pay | C43: =IF(OR(B21=0,B21=""),"",B43/B21) | E43: =IF(OR(D21=0,D21=""),"",D43/D21) | G43: =IF(OR(F21=0,F21=""),"",F43/F21) | I43: =IF(OR(H21=0,H21=""),"",H43/H21) | K43: =IF(OR(J21=0,J21=""),"",J43/J21) | M43: =IF(OR(L21=0,L21=""),"",L43/L21)
A44: Employee Benefits | C44: =IF(OR(B21=0,B21=""),"",B44/B21) | E44: =IF(OR(D21=0,D21=""),"",D44/D21) | G44: =IF(OR(F21=0,F21=""),"",F44/F21) | I44: =IF(OR(H21=0,H21=""),"",H44/H21) | K44: =IF(OR(J21=0,J21=""),"",J44/J21) | M44: =IF(OR(L21=0,L21=""),"",L44/L21)
A45: Total Payroll-Related Expenses | B45: =B42+B43+B44 -> 0 | C45: =IF(OR(B21=0,B21=""),"",B45/B21) | D45: =D42+D43+D44 -> 0 | E45: =IF(OR(D21=0,D21=""),"",D45/D21) | F45: =F42+F43+F44 -> 0 | G45: =IF(OR(F21=0,F21=""),"",F45/F21) | H45: =H42+H43+H44 -> 0 | I45: =IF(OR(H21=0,H21=""),"",H45/H21) | J45: =J42+J43+J44 -> 0 | K45: =IF(OR(J21=0,J21=""),"",J45/J21) | L45: =L42+L43+L44 -> 0 | M45: =IF(OR(L21=0,L21=""),"",L45/L21)
A46: Total Labor Costs and Related Expenses | B46: =B40+B45 -> 0 | C46: =IF(OR(B21=0,B21=""),"",B46/B21) | D46: =D40+D45 -> 0 | E46: =IF(OR(D21=0,D21=""),"",D46/D21) | F46: =F40+F45 -> 0 | G46: =IF(OR(F21=0,F21=""),"",F46/F21) | H46: =H40+H45 -> 0 | I46: =IF(OR(H21=0,H21=""),"",H46/H21) | J46: =J40+J45 -> 0 | K46: =IF(OR(J21=0,J21=""),"",J46/J21) | L46: =L40+L45 -> 0 | M46: =IF(OR(L21=0,L21=""),"",L46/L21)
A47: Other Expenses
A48: Cleaning Supplies | C48: =IF(OR(B21=0,B21=""),"",B48/B21) | E48: =IF(OR(D21=0,D21=""),"",D48/D21) | G48: =IF(OR(F21=0,F21=""),"",F48/F21) | I48: =IF(OR(H21=0,H21=""),"",H48/H21) | K48: =IF(OR(J21=0,J21=""),"",J48/J21) | M48: =IF(OR(L21=0,L21=""),"",L48/L21)
A49: Cluster Services | C49: =IF(OR(B21=0,B21=""),"",B49/B21) | E49: =IF(OR(D21=0,D21=""),"",D49/D21) | G49: =IF(OR(F21=0,F21=""),"",F49/F21) | I49: =IF(OR(H21=0,H21=""),"",H49/H21) | K49: =IF(OR(J21=0,J21=""),"",J49/J21) | M49: =IF(OR(L21=0,L21=""),"",L49/L21)
A50: Complimentary Services and Gifts | C50: =IF(OR(B21=0,B21=""),"",B50/B21) | E50: =IF(OR(D21=0,D21=""),"",D50/D21) | G50: =IF(OR(F21=0,F21=""),"",F50/F21) | I50: =IF(OR(H21=0,H21=""),"",H50/H21) | K50: =IF(OR(J21=0,J21=""),"",J50/J21) | M50: =IF(OR(L21=0,L21=""),"",L50/L21)
A51: Contract Services | C51: =IF(OR(B21=0,B21=""),"",B51/B21) | E51: =IF(OR(D21=0,D21=""),"",D51/D21) | G51: =IF(OR(F21=0,F21=""),"",F51/F21) | I51: =IF(OR(H21=0,H21=""),"",H51/H21) | K51: =IF(OR(J21=0,J21=""),"",J51/J21) | M51: =IF(OR(L21=0,L21=""),"",L51/L21)
A52: Corporate Office Reimbursables | C52: =IF(OR(B21=0,B21=""),"",B52/B21) | E52: =IF(OR(D21=0,D21=""),"",D52/D21) | G52: =IF(OR(F21=0,F21=""),"",F52/F21) | I52: =IF(OR(H21=0,H21=""),"",H52/H21) | K52: =IF(OR(J21=0,J21=""),"",J52/J21) | M52: =IF(OR(L21=0,L21=""),"",L52/L21)
A53: Decorations | C53: =IF(OR(B21=0,B21=""),"",B53/B21) | E53: =IF(OR(D21=0,D21=""),"",D53/D21) | G53: =IF(OR(F21=0,F21=""),"",F53/F21) | I53: =IF(OR(H21=0,H21=""),"",H53/H21) | K53: =IF(OR(J21=0,J21=""),"",J53/J21) | M53: =IF(OR(L21=0,L21=""),"",L53/L21)
A54: Dues and Subscriptions | C54: =IF(OR(B21=0,B21=""),"",B54/B21) | E54: =IF(OR(D21=0,D21=""),"",D54/D21) | G54: =IF(OR(F21=0,F21=""),"",F54/F21) | I54: =IF(OR(H21=0,H21=""),"",H54/H21) | K54: =IF(OR(J21=0,J21=""),"",J54/J21) | M54: =IF(OR(L21=0,L21=""),"",L54/L21)
A55: Entertainment - In-House | C55: =IF(OR(B21=0,B21=""),"",B55/B21) | E55: =IF(OR(D21=0,D21=""),"",D55/D21) | G55: =IF(OR(F21=0,F21=""),"",F55/F21) | I55: =IF(OR(H21=0,H21=""),"",H55/H21) | K55: =IF(OR(J21=0,J21=""),"",J55/J21) | M55: =IF(OR(L21=0,L21=""),"",L55/L21)
A56: Equipment Rental | C56: =IF(OR(B21=0,B21=""),"",B56/B21) | E56: =IF(OR(D21=0,D21=""),"",D56/D21) | G56: =IF(OR(F21=0,F21=""),"",F56/F21) | I56: =IF(OR(H21=0,H21=""),"",H56/H21) | K56: =IF(OR(J21=0,J21=""),"",J56/J21) | M56: =IF(OR(L21=0,L21=""),"",L56/L21)
A57: Gasoline and Lubricants | C57: =IF(OR(B21=0,B21=""),"",B57/B21) | E57: =IF(OR(D21=0,D21=""),"",D57/D21) | G57: =IF(OR(F21=0,F21=""),"",F57/F21) | I57: =IF(OR(H21=0,H21=""),"",H57/H21) | K57: =IF(OR(J21=0,J21=""),"",J57/J21) | M57: =IF(OR(L21=0,L21=""),"",L57/L21)
A58: Grounds Maintenance and Landscaping | C58: =IF(OR(B21=0,B21=""),"",B58/B21) | E58: =IF(OR(D21=0,D21=""),"",D58/D21) | G58: =IF(OR(F21=0,F21=""),"",F58/F21) | I58: =IF(OR(H21=0,H21=""),"",H58/H21) | K58: =IF(OR(J21=0,J21=""),"",J58/J21) | M58: =IF(OR(L21=0,L21=""),"",L58/L21)
A59: Irrigation | C59: =IF(OR(B21=0,B21=""),"",B59/B21) | E59: =IF(OR(D21=0,D21=""),"",D59/D21) | G59: =IF(OR(F21=0,F21=""),"",F59/F21) | I59: =IF(OR(H21=0,H21=""),"",H59/H21) | K59: =IF(OR(J21=0,J21=""),"",J59/J21) | M59: =IF(OR(L21=0,L21=""),"",L59/L21)
A60: Laundry and Dry Cleaning | C60: =IF(OR(B21=0,B21=""),"",B60/B21) | E60: =IF(OR(D21=0,D21=""),"",D60/D21) | G60: =IF(OR(F21=0,F21=""),"",F60/F21) | I60: =IF(OR(H21=0,H21=""),"",H60/H21) | K60: =IF(OR(J21=0,J21=""),"",J60/J21) | M60: =IF(OR(L21=0,L21=""),"",L60/L21)
A61: Licenses and Permits | C61: =IF(OR(B21=0,B21=""),"",B61/B21) | E61: =IF(OR(D21=0,D21=""),"",D61/D21) | G61: =IF(OR(F21=0,F21=""),"",F61/F21) | I61: =IF(OR(H21=0,H21=""),"",H61/H21) | K61: =IF(OR(J21=0,J21=""),"",J61/J21) | M61: =IF(OR(L21=0,L21=""),"",L61/L21)
A62: Linen | C62: =IF(OR(B21=0,B21=""),"",B62/B21) | E62: =IF(OR(D21=0,D21=""),"",D62/D21) | G62: =IF(OR(F21=0,F21=""),"",F62/F21) | I62: =IF(OR(H21=0,H21=""),"",H62/H21) | K62: =IF(OR(J21=0,J21=""),"",J62/J21) | M62: =IF(OR(L21=0,L21=""),"",L62/L21)
A63: Management Fees | C63: =IF(OR(B21=0,B21=""),"",B63/B21) | E63: =IF(OR(D21=0,D21=""),"",D63/D21) | G63: =IF(OR(F21=0,F21=""),"",F63/F21) | I63: =IF(OR(H21=0,H21=""),"",H63/H21) | K63: =IF(OR(J21=0,J21=""),"",J63/J21) | M63: =IF(OR(L21=0,L21=""),"",L63/L21)
A64: Miscellaneous | C64: =IF(OR(B21=0,B21=""),"",B64/B21) | E64: =IF(OR(D21=0,D21=""),"",D64/D21) | G64: =IF(OR(F21=0,F21=""),"",F64/F21) | I64: =IF(OR(H21=0,H21=""),"",H64/H21) | K64: =IF(OR(J21=0,J21=""),"",J64/J21) | M64: =IF(OR(L21=0,L21=""),"",L64/L21)
A65: Operating Supplies | C65: =IF(OR(B21=0,B21=""),"",B65/B21) | E65: =IF(OR(D21=0,D21=""),"",D65/D21) | G65: =IF(OR(F21=0,F21=""),"",F65/F21) | I65: =IF(OR(H21=0,H21=""),"",H65/H21) | K65: =IF(OR(J21=0,J21=""),"",J65/J21) | M65: =IF(OR(L21=0,L21=""),"",L65/L21)
A66: Printing and Stationery | C66: =IF(OR(B21=0,B21=""),"",B66/B21) | E66: =IF(OR(D21=0,D21=""),"",D66/D21) | G66: =IF(OR(F21=0,F21=""),"",F66/F21) | I66: =IF(OR(H21=0,H21=""),"",H66/H21) | K66: =IF(OR(J21=0,J21=""),"",J66/J21) | M66: =IF(OR(L21=0,L21=""),"",L66/L21)
A67: Reservations | C67: =IF(OR(B21=0,B21=""),"",B67/B21) | E67: =IF(OR(D21=0,D21=""),"",D67/D21) | G67: =IF(OR(F21=0,F21=""),"",F67/F21) | I67: =IF(OR(H21=0,H21=""),"",H67/H21) | K67: =IF(OR(J21=0,J21=""),"",J67/J21) | M67: =IF(OR(L21=0,L21=""),"",L67/L21)
A68: Royalty Fees | C68: =IF(OR(B21=0,B21=""),"",B68/B21) | E68: =IF(OR(D21=0,D21=""),"",D68/D21) | G68: =IF(OR(F21=0,F21=""),"",F68/F21) | I68: =IF(OR(H21=0,H21=""),"",H68/H21) | K68: =IF(OR(J21=0,J21=""),"",J68/J21) | M68: =IF(OR(L21=0,L21=""),"",L68/L21)
A69: Tournament Expenses | C69: =IF(OR(B21=0,B21=""),"",B69/B21) | E69: =IF(OR(D21=0,D21=""),"",D69/D21) | G69: =IF(OR(F21=0,F21=""),"",F69/F21) | I69: =IF(OR(H21=0,H21=""),"",H69/H21) | K69: =IF(OR(J21=0,J21=""),"",J69/J21) | M69: =IF(OR(L21=0,L21=""),"",L69/L21)
A70: Training | C70: =IF(OR(B21=0,B21=""),"",B70/B21) | E70: =IF(OR(D21=0,D21=""),"",D70/D21) | G70: =IF(OR(F21=0,F21=""),"",F70/F21) | I70: =IF(OR(H21=0,H21=""),"",H70/H21) | K70: =IF(OR(J21=0,J21=""),"",J70/J21) | M70: =IF(OR(L21=0,L21=""),"",L70/L21)
A71: Transportation | C71: =IF(OR(B21=0,B21=""),"",B71/B21) | E71: =IF(OR(D21=0,D21=""),"",D71/D21) | G71: =IF(OR(F21=0,F21=""),"",F71/F21) | I71: =IF(OR(H21=0,H21=""),"",H71/H21) | K71: =IF(OR(J21=0,J21=""),"",J71/J21) | M71: =IF(OR(L21=0,L21=""),"",L71/L21)
A72: Travel - Meals and Entertainment | C72: =IF(OR(B21=0,B21=""),"",B72/B21) | E72: =IF(OR(D21=0,D21=""),"",D72/D21) | G72: =IF(OR(F21=0,F21=""),"",F72/F21) | I72: =IF(OR(H21=0,H21=""),"",H72/H21) | K72: =IF(OR(J21=0,J21=""),"",J72/J21) | M72: =IF(OR(L21=0,L21=""),"",L72/L21)
A73: Travel - Other | C73: =IF(OR(B21=0,B21=""),"",B73/B21) | E73: =IF(OR(D21=0,D21=""),"",D73/D21) | G73: =IF(OR(F21=0,F21=""),"",F73/F21) | I73: =IF(OR(H21=0,H21=""),"",H73/H21) | K73: =IF(OR(J21=0,J21=""),"",J73/J21) | M73: =IF(OR(L21=0,L21=""),"",L73/L21)
A74: Uniform Costs | C74: =IF(OR(B21=0,B21=""),"",B74/B21) | E74: =IF(OR(D21=0,D21=""),"",D74/D21) | G74: =IF(OR(F21=0,F21=""),"",F74/F21) | I74: =IF(OR(H21=0,H21=""),"",H74/H21) | K74: =IF(OR(J21=0,J21=""),"",J74/J21) | M74: =IF(OR(L21=0,L21=""),"",L74/L21)
A75: Uniform Laundry | C75: =IF(OR(B21=0,B21=""),"",B75/B21) | E75: =IF(OR(D21=0,D21=""),"",D75/D21) | G75: =IF(OR(F21=0,F21=""),"",F75/F21) | I75: =IF(OR(H21=0,H21=""),"",H75/H21) | K75: =IF(OR(J21=0,J21=""),"",J75/J21) | M75: =IF(OR(L21=0,L21=""),"",L75/L21)
A76: Vehicle Repairs and Maintenance | C76: =IF(OR(B21=0,B21=""),"",B76/B21) | E76: =IF(OR(D21=0,D21=""),"",D76/D21) | G76: =IF(OR(F21=0,F21=""),"",F76/F21) | I76: =IF(OR(H21=0,H21=""),"",H76/H21) | K76: =IF(OR(J21=0,J21=""),"",J76/J21) | M76: =IF(OR(L21=0,L21=""),"",L76/L21)
A77: Water | C77: =IF(OR(B21=0,B21=""),"",B77/B21) | E77: =IF(OR(D21=0,D21=""),"",D77/D21) | G77: =IF(OR(F21=0,F21=""),"",F77/F21) | I77: =IF(OR(H21=0,H21=""),"",H77/H21) | K77: =IF(OR(J21=0,J21=""),"",J77/J21) | M77: =IF(OR(L21=0,L21=""),"",L77/L21)
A78: Total Other Expenses | B78: =B48+B49+B50+B51+B52+B53+B54+B55+B56+B57+B58+B59+B60+B61+B62+B63+B64+B65+B66+B67+B68+B69+B70+B71+B72+B73+B74+B75+B76+B77 -> 0 | C78: =IF(OR(B21=0,B21=""),"",B78/B21) | D78: =D48+D49+D50+D51+D52+D53+D54+D55+D56+D57+D58+D59+D60+D61+D62+D63+D64+D65+D66+D67+D68+D69+D70+D71+D72+D73+D74+D75+D76+D77 -> 0 | E78: =IF(OR(D21=0,D21=""),"",D78/D21) | F78: =F48+F49+F50+F51+F52+F53+F54+F55+F56+F57+F58+F59+F60+F61+F62+F63+F64+F65+F66+F67+F68+F69+F70+F71+F72+F73+F74+F75+F76+F77 -> 0 | G78: =IF(OR(F21=0,F21=""),"",F78/F21) | H78: =H48+H49+H50+H51+H52+H53+H54+H55+H56+H57+H58+H59+H60+H61+H62+H63+H64+H65+H66+H67+H68+H69+H70+H71+H72+H73+H74+H75+H76+H77 -> 0 | I78: =IF(OR(H21=0,H21=""),"",H78/H21) | J78: =J48+J49+J50+J51+J52+J53+J54+J55+J56+J57+J58+J59+J60+J61+J62+J63+J64+J65+J66+J67+J68+J69+J70+J71+J72+J73+J74+J75+J76+J77 -> 0 | K78: =IF(OR(J21=0,J21=""),"",J78/J21) | L78: =L48+L49+L50+L51+L52+L53+L54+L55+L56+L57+L58+L59+L60+L61+L62+L63+L64+L65+L66+L67+L68+L69+L70+L71+L72+L73+L74+L75+L76+L77 -> 0 | M78: =IF(OR(L21=0,L21=""),"",L78/L21)
A79: Total Expenses | B79: =B46+B78 -> 0 | C79: =IF(OR(B21=0,B21=""),"",B79/B21) | D79: =D46+D78 -> 0 | E79: =IF(OR(D21=0,D21=""),"",D79/D21) | F79: =F46+F78 -> 0 | G79: =IF(OR(F21=0,F21=""),"",F79/F21) | H79: =H46+H78 -> 0 | I79: =IF(OR(H21=0,H21=""),"",H79/H21) | J79: =J46+J78 -> 0 | K79: =IF(OR(J21=0,J21=""),"",J79/J21) | L79: =L46+L78 -> 0 | M79: =IF(OR(L21=0,L21=""),"",L79/L21)
A80: Departmental Profit | B80: =B26-B78 -> 0 | C80: =IF(OR(B21=0,B21=""),"",B80/B21) | D80: =D26-D78 -> 0 | E80: =IF(OR(D21=0,D21=""),"",D80/D21) | F80: =F26-F78 -> 0 | G80: =IF(OR(F21=0,F21=""),"",F80/F21) | H80: =H26-H78 -> 0 | I80: =IF(OR(H21=0,H21=""),"",H80/H21) | J80: =J26-J78 -> 0 | K80: =IF(OR(J21=0,J21=""),"",J80/J21) | L80: =L26-L78 -> 0 | M80: =IF(OR(L21=0,L21=""),"",L80/L21)

Sheet Sub-Sch 3-2 - Health Club Spa
A1: HEALTH CLUB/SPA — SUB-SCHEDULE 3-2
A2: Property: | B2: ='Setup & Assumptions'!$B$4 -> Enter property name | H2: Period / Year: | J2: ='Setup & Assumptions'!$B$5 -> e.g. January 2026 / FY2026
B4: Current Period | H4: Year-To-Date
B5: Actual | D5: Forecast / Budget | F5: Prior Year | H5: Actual | J5: Forecast / Budget | L5: Prior Year
A6: Line Item | B6: $ | C6: % | D6: $ | E6: % | F6: $ | G6: % | H6: $ | I6: % | J6: $ | K6: % | L6: $ | M6: %
A7: Revenue
A8: Massage and Body Treatment Revenue | C8: =IF(OR(B18=0,B18=""),"",B8/B18) | E8: =IF(OR(D18=0,D18=""),"",D8/D18) | G8: =IF(OR(F18=0,F18=""),"",F8/F18) | I8: =IF(OR(H18=0,H18=""),"",H8/H18) | K8: =IF(OR(J18=0,J18=""),"",J8/J18) | M8: =IF(OR(L18=0,L18=""),"",L8/L18)
A9: Skin Care Revenue | C9: =IF(OR(B18=0,B18=""),"",B9/B18) | E9: =IF(OR(D18=0,D18=""),"",D9/D18) | G9: =IF(OR(F18=0,F18=""),"",F9/F18) | I9: =IF(OR(H18=0,H18=""),"",H9/H18) | K9: =IF(OR(J18=0,J18=""),"",J9/J18) | M9: =IF(OR(L18=0,L18=""),"",L9/L18)
A10: Hair Care Revenue | C10: =IF(OR(B18=0,B18=""),"",B10/B18) | E10: =IF(OR(D18=0,D18=""),"",D10/D18) | G10: =IF(OR(F18=0,F18=""),"",F10/F18) | I10: =IF(OR(H18=0,H18=""),"",H10/H18) | K10: =IF(OR(J18=0,J18=""),"",J10/J18) | M10: =IF(OR(L18=0,L18=""),"",L10/L18)
A11: Nail Care Revenue | C11: =IF(OR(B18=0,B18=""),"",B11/B18) | E11: =IF(OR(D18=0,D18=""),"",D11/D18) | G11: =IF(OR(F18=0,F18=""),"",F11/F18) | I11: =IF(OR(H18=0,H18=""),"",H11/H18) | K11: =IF(OR(J18=0,J18=""),"",J11/J18) | M11: =IF(OR(L18=0,L18=""),"",L11/L18)
A12: Fitness Revenue | C12: =IF(OR(B18=0,B18=""),"",B12/B18) | E12: =IF(OR(D18=0,D18=""),"",D12/D18) | G12: =IF(OR(F18=0,F18=""),"",F12/F18) | I12: =IF(OR(H18=0,H18=""),"",H12/H18) | K12: =IF(OR(J18=0,J18=""),"",J12/J18) | M12: =IF(OR(L18=0,L18=""),"",L12/L18)
A13: Health and Wellness Revenue | C13: =IF(OR(B18=0,B18=""),"",B13/B18) | E13: =IF(OR(D18=0,D18=""),"",D13/D18) | G13: =IF(OR(F18=0,F18=""),"",F13/F18) | I13: =IF(OR(H18=0,H18=""),"",H13/H18) | K13: =IF(OR(J18=0,J18=""),"",J13/J18) | M13: =IF(OR(L18=0,L18=""),"",L13/L18)
A14: Membership Fee Revenue | C14: =IF(OR(B18=0,B18=""),"",B14/B18) | E14: =IF(OR(D18=0,D18=""),"",D14/D18) | G14: =IF(OR(F18=0,F18=""),"",F14/F18) | I14: =IF(OR(H18=0,H18=""),"",H14/H18) | K14: =IF(OR(J18=0,J18=""),"",J14/J18) | M14: =IF(OR(L18=0,L18=""),"",L14/L18)
A15: Retail Revenue | C15: =IF(OR(B18=0,B18=""),"",B15/B18) | E15: =IF(OR(D18=0,D18=""),"",D15/D18) | G15: =IF(OR(F18=0,F18=""),"",F15/F18) | I15: =IF(OR(H18=0,H18=""),"",H15/H18) | K15: =IF(OR(J18=0,J18=""),"",J15/J18) | M15: =IF(OR(L18=0,L18=""),"",L15/L18)
A16: Other Revenue | C16: =IF(OR(B18=0,B18=""),"",B16/B18) | E16: =IF(OR(D18=0,D18=""),"",D16/D18) | G16: =IF(OR(F18=0,F18=""),"",F16/F18) | I16: =IF(OR(H18=0,H18=""),"",H16/H18) | K16: =IF(OR(J18=0,J18=""),"",J16/J18) | M16: =IF(OR(L18=0,L18=""),"",L16/L18)
A17: Less: Allowances | C17: =IF(OR(B18=0,B18=""),"",B17/B18) | E17: =IF(OR(D18=0,D18=""),"",D17/D18) | G17: =IF(OR(F18=0,F18=""),"",F17/F18) | I17: =IF(OR(H18=0,H18=""),"",H17/H18) | K17: =IF(OR(J18=0,J18=""),"",J17/J18) | M17: =IF(OR(L18=0,L18=""),"",L17/L18)
A18: Total Health Club Spa Revenue | B18: =B8+B9+B10+B11+B12+B13+B14+B15+B16-B17 -> 0 | C18: =IF(OR(B18=0,B18=""),"",B18/B18) | D18: =D8+D9+D10+D11+D12+D13+D14+D15+D16-D17 -> 0 | E18: =IF(OR(D18=0,D18=""),"",D18/D18) | F18: =F8+F9+F10+F11+F12+F13+F14+F15+F16-F17 -> 0 | G18: =IF(OR(F18=0,F18=""),"",F18/F18) | H18: =H8+H9+H10+H11+H12+H13+H14+H15+H16-H17 -> 0 | I18: =IF(OR(H18=0,H18=""),"",H18/H18) | J18: =J8+J9+J10+J11+J12+J13+J14+J15+J16-J17 -> 0 | K18: =IF(OR(J18=0,J18=""),"",J18/J18) | L18: =L8+L9+L10+L11+L12+L13+L14+L15+L16-L17 -> 0 | M18: =IF(OR(L18=0,L18=""),"",L18/L18)
A19: Cost of Sales | C19: =IF(OR(B18=0,B18=""),"",B19/B18) | E19: =IF(OR(D18=0,D18=""),"",D19/D18) | G19: =IF(OR(F18=0,F18=""),"",F19/F18) | I19: =IF(OR(H18=0,H18=""),"",H19/H18) | K19: =IF(OR(J18=0,J18=""),"",J19/J18) | M19: =IF(OR(L18=0,L18=""),"",L19/L18)
A20: Gross Profit | B20: =B18-B19 -> 0 | C20: =IF(OR(B18=0,B18=""),"",B20/B18) | D20: =D18-D19 -> 0 | E20: =IF(OR(D18=0,D18=""),"",D20/D18) | F20: =F18-F19 -> 0 | G20: =IF(OR(F18=0,F18=""),"",F20/F18) | H20: =H18-H19 -> 0 | I20: =IF(OR(H18=0,H18=""),"",H20/H18) | J20: =J18-J19 -> 0 | K20: =IF(OR(J18=0,J18=""),"",J20/J18) | L20: =L18-L19 -> 0 | M20: =IF(OR(L18=0,L18=""),"",L20/L18)
A21: Expenses
A22: Labor Costs and Related Expenses
A23: Salaries, Wages, Service Charges, Contracted Labor and Bonuses
A24: Salaries and Wages
A25: Management
A26: Non-Management
A27: Attendant/Housekeeping
A28: Fitness
A29: Reception/Retail
A30: Therapists/Technicians
A31: Sub-Total: Salaries and Wages | B31: =B25+B27+B28+B29+B30 -> 0 | D31: =D25+D27+D28+D29+D30 -> 0 | F31: =F25+F27+F28+F29+F30 -> 0 | H31: =H25+H27+H28+H29+H30 -> 0 | J31: =J25+J27+J28+J29+J30 -> 0 | L31: =L25+L27+L28+L29+L30 -> 0
A32: Service Charge Distribution
A33: Contracted, Leased and Outsourced Labor
A34: Bonuses and Incentives
A35: Total Salaries, Wages, Service Charges, Contracted Labor and Bonuses | B35: =B31+B32+B33+B34 -> 0 | C35: =IF(OR(B18=0,B18=""),"",B35/B18) | D35: =D31+D32+D33+D34 -> 0 | E35: =IF(OR(D18=0,D18=""),"",D35/D18) | F35: =F31+F32+F33+F34 -> 0 | G35: =IF(OR(F18=0,F18=""),"",F35/F18) | H35: =H31+H32+H33+H34 -> 0 | I35: =IF(OR(H18=0,H18=""),"",H35/H18) | J35: =J31+J32+J33+J34 -> 0 | K35: =IF(OR(J18=0,J18=""),"",J35/J18) | L35: =L31+L32+L33+L34 -> 0 | M35: =IF(OR(L18=0,L18=""),"",L35/L18)
A36: Payroll-Related Expenses
A37: Payroll Taxes | C37: =IF(OR(B18=0,B18=""),"",B37/B18) | E37: =IF(OR(D18=0,D18=""),"",D37/D18) | G37: =IF(OR(F18=0,F18=""),"",F37/F18) | I37: =IF(OR(H18=0,H18=""),"",H37/H18) | K37: =IF(OR(J18=0,J18=""),"",J37/J18) | M37: =IF(OR(L18=0,L18=""),"",L37/L18)
A38: Supplemental Pay | C38: =IF(OR(B18=0,B18=""),"",B38/B18) | E38: =IF(OR(D18=0,D18=""),"",D38/D18) | G38: =IF(OR(F18=0,F18=""),"",F38/F18) | I38: =IF(OR(H18=0,H18=""),"",H38/H18) | K38: =IF(OR(J18=0,J18=""),"",J38/J18) | M38: =IF(OR(L18=0,L18=""),"",L38/L18)
A39: Employee Benefits | C39: =IF(OR(B18=0,B18=""),"",B39/B18) | E39: =IF(OR(D18=0,D18=""),"",D39/D18) | G39: =IF(OR(F18=0,F18=""),"",F39/F18) | I39: =IF(OR(H18=0,H18=""),"",H39/H18) | K39: =IF(OR(J18=0,J18=""),"",J39/J18) | M39: =IF(OR(L18=0,L18=""),"",L39/L18)
A40: Total Payroll-Related Expenses | B40: =B37+B38+B39 -> 0 | C40: =IF(OR(B18=0,B18=""),"",B40/B18) | D40: =D37+D38+D39 -> 0 | E40: =IF(OR(D18=0,D18=""),"",D40/D18) | F40: =F37+F38+F39 -> 0 | G40: =IF(OR(F18=0,F18=""),"",F40/F18) | H40: =H37+H38+H39 -> 0 | I40: =IF(OR(H18=0,H18=""),"",H40/H18) | J40: =J37+J38+J39 -> 0 | K40: =IF(OR(J18=0,J18=""),"",J40/J18) | L40: =L37+L38+L39 -> 0 | M40: =IF(OR(L18=0,L18=""),"",L40/L18)
A41: Total Labor Costs and Related Expenses | B41: =B35+B40 -> 0 | C41: =IF(OR(B18=0,B18=""),"",B41/B18) | D41: =D35+D40 -> 0 | E41: =IF(OR(D18=0,D18=""),"",D41/D18) | F41: =F35+F40 -> 0 | G41: =IF(OR(F18=0,F18=""),"",F41/F18) | H41: =H35+H40 -> 0 | I41: =IF(OR(H18=0,H18=""),"",H41/H18) | J41: =J35+J40 -> 0 | K41: =IF(OR(J18=0,J18=""),"",J41/J18) | L41: =L35+L40 -> 0 | M41: =IF(OR(L18=0,L18=""),"",L41/L18)
A42: Other Expenses
A43: Ambience | C43: =IF(OR(B18=0,B18=""),"",B43/B18) | E43: =IF(OR(D18=0,D18=""),"",D43/D18) | G43: =IF(OR(F18=0,F18=""),"",F43/F18) | I43: =IF(OR(H18=0,H18=""),"",H43/H18) | K43: =IF(OR(J18=0,J18=""),"",J43/J18) | M43: =IF(OR(L18=0,L18=""),"",L43/L18)
A44: Athletic Supplies | C44: =IF(OR(B18=0,B18=""),"",B44/B18) | E44: =IF(OR(D18=0,D18=""),"",D44/D18) | G44: =IF(OR(F18=0,F18=""),"",F44/F18) | I44: =IF(OR(H18=0,H18=""),"",H44/H18) | K44: =IF(OR(J18=0,J18=""),"",J44/J18) | M44: =IF(OR(L18=0,L18=""),"",L44/L18)
A45: Cleaning Supplies | C45: =IF(OR(B18=0,B18=""),"",B45/B18) | E45: =IF(OR(D18=0,D18=""),"",D45/D18) | G45: =IF(OR(F18=0,F18=""),"",F45/F18) | I45: =IF(OR(H18=0,H18=""),"",H45/H18) | K45: =IF(OR(J18=0,J18=""),"",J45/J18) | M45: =IF(OR(L18=0,L18=""),"",L45/L18)
A46: Cluster Services | C46: =IF(OR(B18=0,B18=""),"",B46/B18) | E46: =IF(OR(D18=0,D18=""),"",D46/D18) | G46: =IF(OR(F18=0,F18=""),"",F46/F18) | I46: =IF(OR(H18=0,H18=""),"",H46/H18) | K46: =IF(OR(J18=0,J18=""),"",J46/J18) | M46: =IF(OR(L18=0,L18=""),"",L46/L18)
A47: Complimentary Services and Gifts | C47: =IF(OR(B18=0,B18=""),"",B47/B18) | E47: =IF(OR(D18=0,D18=""),"",D47/D18) | G47: =IF(OR(F18=0,F18=""),"",F47/F18) | I47: =IF(OR(H18=0,H18=""),"",H47/H18) | K47: =IF(OR(J18=0,J18=""),"",J47/J18) | M47: =IF(OR(L18=0,L18=""),"",L47/L18)
A48: Contract Services | C48: =IF(OR(B18=0,B18=""),"",B48/B18) | E48: =IF(OR(D18=0,D18=""),"",D48/D18) | G48: =IF(OR(F18=0,F18=""),"",F48/F18) | I48: =IF(OR(H18=0,H18=""),"",H48/H18) | K48: =IF(OR(J18=0,J18=""),"",J48/J18) | M48: =IF(OR(L18=0,L18=""),"",L48/L18)
A49: Corporate Office Reimbursables | C49: =IF(OR(B18=0,B18=""),"",B49/B18) | E49: =IF(OR(D18=0,D18=""),"",D49/D18) | G49: =IF(OR(F18=0,F18=""),"",F49/F18) | I49: =IF(OR(H18=0,H18=""),"",H49/H18) | K49: =IF(OR(J18=0,J18=""),"",J49/J18) | M49: =IF(OR(L18=0,L18=""),"",L49/L18)
A50: Decorations | C50: =IF(OR(B18=0,B18=""),"",B50/B18) | E50: =IF(OR(D18=0,D18=""),"",D50/D18) | G50: =IF(OR(F18=0,F18=""),"",F50/F18) | I50: =IF(OR(H18=0,H18=""),"",H50/H18) | K50: =IF(OR(J18=0,J18=""),"",J50/J18) | M50: =IF(OR(L18=0,L18=""),"",L50/L18)
A51: Dues and Subscriptions | C51: =IF(OR(B18=0,B18=""),"",B51/B18) | E51: =IF(OR(D18=0,D18=""),"",D51/D18) | G51: =IF(OR(F18=0,F18=""),"",F51/F18) | I51: =IF(OR(H18=0,H18=""),"",H51/H18) | K51: =IF(OR(J18=0,J18=""),"",J51/J18) | M51: =IF(OR(L18=0,L18=""),"",L51/L18)
A52: Entertainment - In-House | C52: =IF(OR(B18=0,B18=""),"",B52/B18) | E52: =IF(OR(D18=0,D18=""),"",D52/D18) | G52: =IF(OR(F18=0,F18=""),"",F52/F18) | I52: =IF(OR(H18=0,H18=""),"",H52/H18) | K52: =IF(OR(J18=0,J18=""),"",J52/J18) | M52: =IF(OR(L18=0,L18=""),"",L52/L18)
A53: Equipment Rental | C53: =IF(OR(B18=0,B18=""),"",B53/B18) | E53: =IF(OR(D18=0,D18=""),"",D53/D18) | G53: =IF(OR(F18=0,F18=""),"",F53/F18) | I53: =IF(OR(H18=0,H18=""),"",H53/H18) | K53: =IF(OR(J18=0,J18=""),"",J53/J18) | M53: =IF(OR(L18=0,L18=""),"",L53/L18)
A54: Health and Beauty Products | C54: =IF(OR(B18=0,B18=""),"",B54/B18) | E54: =IF(OR(D18=0,D18=""),"",D54/D18) | G54: =IF(OR(F18=0,F18=""),"",F54/F18) | I54: =IF(OR(H18=0,H18=""),"",H54/H18) | K54: =IF(OR(J18=0,J18=""),"",J54/J18) | M54: =IF(OR(L18=0,L18=""),"",L54/L18)
A55: Laundry and Dry Cleaning | C55: =IF(OR(B18=0,B18=""),"",B55/B18) | E55: =IF(OR(D18=0,D18=""),"",D55/D18) | G55: =IF(OR(F18=0,F18=""),"",F55/F18) | I55: =IF(OR(H18=0,H18=""),"",H55/H18) | K55: =IF(OR(J18=0,J18=""),"",J55/J18) | M55: =IF(OR(L18=0,L18=""),"",L55/L18)
A56: Licenses and Permits | C56: =IF(OR(B18=0,B18=""),"",B56/B18) | E56: =IF(OR(D18=0,D18=""),"",D56/D18) | G56: =IF(OR(F18=0,F18=""),"",F56/F18) | I56: =IF(OR(H18=0,H18=""),"",H56/H18) | K56: =IF(OR(J18=0,J18=""),"",J56/J18) | M56: =IF(OR(L18=0,L18=""),"",L56/L18)
A57: Linen | C57: =IF(OR(B18=0,B18=""),"",B57/B18) | E57: =IF(OR(D18=0,D18=""),"",D57/D18) | G57: =IF(OR(F18=0,F18=""),"",F57/F18) | I57: =IF(OR(H18=0,H18=""),"",H57/H18) | K57: =IF(OR(J18=0,J18=""),"",J57/J18) | M57: =IF(OR(L18=0,L18=""),"",L57/L18)
A58: Management Fees | C58: =IF(OR(B18=0,B18=""),"",B58/B18) | E58: =IF(OR(D18=0,D18=""),"",D58/D18) | G58: =IF(OR(F18=0,F18=""),"",F58/F18) | I58: =IF(OR(H18=0,H18=""),"",H58/H18) | K58: =IF(OR(J18=0,J18=""),"",J58/J18) | M58: =IF(OR(L18=0,L18=""),"",L58/L18)
A59: Miscellaneous | C59: =IF(OR(B18=0,B18=""),"",B59/B18) | E59: =IF(OR(D18=0,D18=""),"",D59/D18) | G59: =IF(OR(F18=0,F18=""),"",F59/F18) | I59: =IF(OR(H18=0,H18=""),"",H59/H18) | K59: =IF(OR(J18=0,J18=""),"",J59/J18) | M59: =IF(OR(L18=0,L18=""),"",L59/L18)
A60: Operating Supplies | C60: =IF(OR(B18=0,B18=""),"",B60/B18) | E60: =IF(OR(D18=0,D18=""),"",D60/D18) | G60: =IF(OR(F18=0,F18=""),"",F60/F18) | I60: =IF(OR(H18=0,H18=""),"",H60/H18) | K60: =IF(OR(J18=0,J18=""),"",J60/J18) | M60: =IF(OR(L18=0,L18=""),"",L60/L18)
A61: Printing and Stationery | C61: =IF(OR(B18=0,B18=""),"",B61/B18) | E61: =IF(OR(D18=0,D18=""),"",D61/D18) | G61: =IF(OR(F18=0,F18=""),"",F61/F18) | I61: =IF(OR(H18=0,H18=""),"",H61/H18) | K61: =IF(OR(J18=0,J18=""),"",J61/J18) | M61: =IF(OR(L18=0,L18=""),"",L61/L18)
A62: Reservations | C62: =IF(OR(B18=0,B18=""),"",B62/B18) | E62: =IF(OR(D18=0,D18=""),"",D62/D18) | G62: =IF(OR(F18=0,F18=""),"",F62/F18) | I62: =IF(OR(H18=0,H18=""),"",H62/H18) | K62: =IF(OR(J18=0,J18=""),"",J62/J18) | M62: =IF(OR(L18=0,L18=""),"",L62/L18)
A63: Royalty Fees | C63: =IF(OR(B18=0,B18=""),"",B63/B18) | E63: =IF(OR(D18=0,D18=""),"",D63/D18) | G63: =IF(OR(F18=0,F18=""),"",F63/F18) | I63: =IF(OR(H18=0,H18=""),"",H63/H18) | K63: =IF(OR(J18=0,J18=""),"",J63/J18) | M63: =IF(OR(L18=0,L18=""),"",L63/L18)
A64: Swimming Pool | C64: =IF(OR(B18=0,B18=""),"",B64/B18) | E64: =IF(OR(D18=0,D18=""),"",D64/D18) | G64: =IF(OR(F18=0,F18=""),"",F64/F18) | I64: =IF(OR(H18=0,H18=""),"",H64/H18) | K64: =IF(OR(J18=0,J18=""),"",J64/J18) | M64: =IF(OR(L18=0,L18=""),"",L64/L18)
A65: Training | C65: =IF(OR(B18=0,B18=""),"",B65/B18) | E65: =IF(OR(D18=0,D18=""),"",D65/D18) | G65: =IF(OR(F18=0,F18=""),"",F65/F18) | I65: =IF(OR(H18=0,H18=""),"",H65/H18) | K65: =IF(OR(J18=0,J18=""),"",J65/J18) | M65: =IF(OR(L18=0,L18=""),"",L65/L18)
A66: Travel - Meals and Entertainment | C66: =IF(OR(B18=0,B18=""),"",B66/B18) | E66: =IF(OR(D18=0,D18=""),"",D66/D18) | G66: =IF(OR(F18=0,F18=""),"",F66/F18) | I66: =IF(OR(H18=0,H18=""),"",H66/H18) | K66: =IF(OR(J18=0,J18=""),"",J66/J18) | M66: =IF(OR(L18=0,L18=""),"",L66/L18)
A67: Travel - Other | C67: =IF(OR(B18=0,B18=""),"",B67/B18) | E67: =IF(OR(D18=0,D18=""),"",D67/D18) | G67: =IF(OR(F18=0,F18=""),"",F67/F18) | I67: =IF(OR(H18=0,H18=""),"",H67/H18) | K67: =IF(OR(J18=0,J18=""),"",J67/J18) | M67: =IF(OR(L18=0,L18=""),"",L67/L18)
A68: Uniform Costs | C68: =IF(OR(B18=0,B18=""),"",B68/B18) | E68: =IF(OR(D18=0,D18=""),"",D68/D18) | G68: =IF(OR(F18=0,F18=""),"",F68/F18) | I68: =IF(OR(H18=0,H18=""),"",H68/H18) | K68: =IF(OR(J18=0,J18=""),"",J68/J18) | M68: =IF(OR(L18=0,L18=""),"",L68/L18)
A69: Uniform Laundry | C69: =IF(OR(B18=0,B18=""),"",B69/B18) | E69: =IF(OR(D18=0,D18=""),"",D69/D18) | G69: =IF(OR(F18=0,F18=""),"",F69/F18) | I69: =IF(OR(H18=0,H18=""),"",H69/H18) | K69: =IF(OR(J18=0,J18=""),"",J69/J18) | M69: =IF(OR(L18=0,L18=""),"",L69/L18)
A70: Total Other Expenses | B70: =B43+B44+B45+B46+B47+B48+B49+B50+B51+B52+B53+B54+B55+B56+B57+B58+B59+B60+B61+B62+B63+B64+B65+B66+B67+B68+B69 -> 0 | C70: =IF(OR(B18=0,B18=""),"",B70/B18) | D70: =D43+D44+D45+D46+D47+D48+D49+D50+D51+D52+D53+D54+D55+D56+D57+D58+D59+D60+D61+D62+D63+D64+D65+D66+D67+D68+D69 -> 0 | E70: =IF(OR(D18=0,D18=""),"",D70/D18) | F70: =F43+F44+F45+F46+F47+F48+F49+F50+F51+F52+F53+F54+F55+F56+F57+F58+F59+F60+F61+F62+F63+F64+F65+F66+F67+F68+F69 -> 0 | G70: =IF(OR(F18=0,F18=""),"",F70/F18) | H70: =H43+H44+H45+H46+H47+H48+H49+H50+H51+H52+H53+H54+H55+H56+H57+H58+H59+H60+H61+H62+H63+H64+H65+H66+H67+H68+H69 -> 0 | I70: =IF(OR(H18=0,H18=""),"",H70/H18) | J70: =J43+J44+J45+J46+J47+J48+J49+J50+J51+J52+J53+J54+J55+J56+J57+J58+J59+J60+J61+J62+J63+J64+J65+J66+J67+J68+J69 -> 0 | K70: =IF(OR(J18=0,J18=""),"",J70/J18) | L70: =L43+L44+L45+L46+L47+L48+L49+L50+L51+L52+L53+L54+L55+L56+L57+L58+L59+L60+L61+L62+L63+L64+L65+L66+L67+L68+L69 -> 0 | M70: =IF(OR(L18=0,L18=""),"",L70/L18)
A71: Total Expenses | B71: =B41+B70 -> 0 | C71: =IF(OR(B18=0,B18=""),"",B71/B18) | D71: =D41+D70 -> 0 | E71: =IF(OR(D18=0,D18=""),"",D71/D18) | F71: =F41+F70 -> 0 | G71: =IF(OR(F18=0,F18=""),"",F71/F18) | H71: =H41+H70 -> 0 | I71: =IF(OR(H18=0,H18=""),"",H71/H18) | J71: =J41+J70 -> 0 | K71: =IF(OR(J18=0,J18=""),"",J71/J18) | L71: =L41+L70 -> 0 | M71: =IF(OR(L18=0,L18=""),"",L71/L18)
A72: Departmental Profit | B72: =B20-B70 -> 0 | C72: =IF(OR(B18=0,B18=""),"",B72/B18) | D72: =D20-D70 -> 0 | E72: =IF(OR(D18=0,D18=""),"",D72/D18) | F72: =F20-F70 -> 0 | G72: =IF(OR(F18=0,F18=""),"",F72/F18) | H72: =H20-H70 -> 0 | I72: =IF(OR(H18=0,H18=""),"",H72/H18) | J72: =J20-J70 -> 0 | K72: =IF(OR(J18=0,J18=""),"",J72/J18) | L72: =L20-L70 -> 0 | M72: =IF(OR(L18=0,L18=""),"",L72/L18)

Sheet Sub-Sch 3-3 - Parking
A1: PARKING — SUB-SCHEDULE 3-3
A2: Property: | B2: ='Setup & Assumptions'!$B$4 -> Enter property name | H2: Period / Year: | J2: ='Setup & Assumptions'!$B$5 -> e.g. January 2026 / FY2026
B4: Current Period | H4: Year-To-Date
B5: Actual | D5: Forecast / Budget | F5: Prior Year | H5: Actual | J5: Forecast / Budget | L5: Prior Year
A6: Line Item | B6: $ | C6: % | D6: $ | E6: % | F6: $ | G6: % | H6: $ | I6: % | J6: $ | K6: % | L6: $ | M6: %
A7: Revenue
A8: Self-Parking Revenue | C8: =IF(OR(B12=0,B12=""),"",B8/B12) | E8: =IF(OR(D12=0,D12=""),"",D8/D12) | G8: =IF(OR(F12=0,F12=""),"",F8/F12) | I8: =IF(OR(H12=0,H12=""),"",H8/H12) | K8: =IF(OR(J12=0,J12=""),"",J8/J12) | M8: =IF(OR(L12=0,L12=""),"",L8/L12)
A9: Valet Parking Revenue | C9: =IF(OR(B12=0,B12=""),"",B9/B12) | E9: =IF(OR(D12=0,D12=""),"",D9/D12) | G9: =IF(OR(F12=0,F12=""),"",F9/F12) | I9: =IF(OR(H12=0,H12=""),"",H9/H12) | K9: =IF(OR(J12=0,J12=""),"",J9/J12) | M9: =IF(OR(L12=0,L12=""),"",L9/L12)
A10: Other Revenue | C10: =IF(OR(B12=0,B12=""),"",B10/B12) | E10: =IF(OR(D12=0,D12=""),"",D10/D12) | G10: =IF(OR(F12=0,F12=""),"",F10/F12) | I10: =IF(OR(H12=0,H12=""),"",H10/H12) | K10: =IF(OR(J12=0,J12=""),"",J10/J12) | M10: =IF(OR(L12=0,L12=""),"",L10/L12)
A11: Less: Allowances | C11: =IF(OR(B12=0,B12=""),"",B11/B12) | E11: =IF(OR(D12=0,D12=""),"",D11/D12) | G11: =IF(OR(F12=0,F12=""),"",F11/F12) | I11: =IF(OR(H12=0,H12=""),"",H11/H12) | K11: =IF(OR(J12=0,J12=""),"",J11/J12) | M11: =IF(OR(L12=0,L12=""),"",L11/L12)
A12: Total Parking Revenue | B12: =B8+B9+B10-B11 -> 0 | C12: =IF(OR(B12=0,B12=""),"",B12/B12) | D12: =D8+D9+D10-D11 -> 0 | E12: =IF(OR(D12=0,D12=""),"",D12/D12) | F12: =F8+F9+F10-F11 -> 0 | G12: =IF(OR(F12=0,F12=""),"",F12/F12) | H12: =H8+H9+H10-H11 -> 0 | I12: =IF(OR(H12=0,H12=""),"",H12/H12) | J12: =J8+J9+J10-J11 -> 0 | K12: =IF(OR(J12=0,J12=""),"",J12/J12) | L12: =L8+L9+L10-L11 -> 0 | M12: =IF(OR(L12=0,L12=""),"",L12/L12)
A13: Cost of Sales | C13: =IF(OR(B12=0,B12=""),"",B13/B12) | E13: =IF(OR(D12=0,D12=""),"",D13/D12) | G13: =IF(OR(F12=0,F12=""),"",F13/F12) | I13: =IF(OR(H12=0,H12=""),"",H13/H12) | K13: =IF(OR(J12=0,J12=""),"",J13/J12) | M13: =IF(OR(L12=0,L12=""),"",L13/L12)
A14: Gross Profit | B14: =B12-B13 -> 0 | C14: =IF(OR(B12=0,B12=""),"",B14/B12) | D14: =D12-D13 -> 0 | E14: =IF(OR(D12=0,D12=""),"",D14/D12) | F14: =F12-F13 -> 0 | G14: =IF(OR(F12=0,F12=""),"",F14/F12) | H14: =H12-H13 -> 0 | I14: =IF(OR(H12=0,H12=""),"",H14/H12) | J14: =J12-J13 -> 0 | K14: =IF(OR(J12=0,J12=""),"",J14/J12) | L14: =L12-L13 -> 0 | M14: =IF(OR(L12=0,L12=""),"",L14/L12)
A15: Expenses
A16: Labor Costs and Related Expenses
A17: Salaries, Wages, Service Charges, Contracted Labor and Bonuses
A18: Salaries and Wages
A19: Management
A20: Non-Management
A21: Sub-Total: Salaries and Wages | B21: =B19+B20 -> 0 | D21: =D19+D20 -> 0 | F21: =F19+F20 -> 0 | H21: =H19+H20 -> 0 | J21: =J19+J20 -> 0 | L21: =L19+L20 -> 0
A22: Service Charge Distribution
A23: Contracted, Leased and Outsourced Labor
A24: Bonuses and Incentives
A25: Total Salaries, Wages, Service Charges, Contracted Labor and Bonuses | B25: =B21+B22+B23+B24 -> 0 | C25: =IF(OR(B12=0,B12=""),"",B25/B12) | D25: =D21+D22+D23+D24 -> 0 | E25: =IF(OR(D12=0,D12=""),"",D25/D12) | F25: =F21+F22+F23+F24 -> 0 | G25: =IF(OR(F12=0,F12=""),"",F25/F12) | H25: =H21+H22+H23+H24 -> 0 | I25: =IF(OR(H12=0,H12=""),"",H25/H12) | J25: =J21+J22+J23+J24 -> 0 | K25: =IF(OR(J12=0,J12=""),"",J25/J12) | L25: =L21+L22+L23+L24 -> 0 | M25: =IF(OR(L12=0,L12=""),"",L25/L12)
A26: Payroll-Related Expenses
A27: Payroll Taxes | C27: =IF(OR(B12=0,B12=""),"",B27/B12) | E27: =IF(OR(D12=0,D12=""),"",D27/D12) | G27: =IF(OR(F12=0,F12=""),"",F27/F12) | I27: =IF(OR(H12=0,H12=""),"",H27/H12) | K27: =IF(OR(J12=0,J12=""),"",J27/J12) | M27: =IF(OR(L12=0,L12=""),"",L27/L12)
A28: Supplemental Pay | C28: =IF(OR(B12=0,B12=""),"",B28/B12) | E28: =IF(OR(D12=0,D12=""),"",D28/D12) | G28: =IF(OR(F12=0,F12=""),"",F28/F12) | I28: =IF(OR(H12=0,H12=""),"",H28/H12) | K28: =IF(OR(J12=0,J12=""),"",J28/J12) | M28: =IF(OR(L12=0,L12=""),"",L28/L12)
A29: Employee Benefits | C29: =IF(OR(B12=0,B12=""),"",B29/B12) | E29: =IF(OR(D12=0,D12=""),"",D29/D12) | G29: =IF(OR(F12=0,F12=""),"",F29/F12) | I29: =IF(OR(H12=0,H12=""),"",H29/H12) | K29: =IF(OR(J12=0,J12=""),"",J29/J12) | M29: =IF(OR(L12=0,L12=""),"",L29/L12)
A30: Total Payroll-Related Expenses | B30: =B27+B28+B29 -> 0 | C30: =IF(OR(B12=0,B12=""),"",B30/B12) | D30: =D27+D28+D29 -> 0 | E30: =IF(OR(D12=0,D12=""),"",D30/D12) | F30: =F27+F28+F29 -> 0 | G30: =IF(OR(F12=0,F12=""),"",F30/F12) | H30: =H27+H28+H29 -> 0 | I30: =IF(OR(H12=0,H12=""),"",H30/H12) | J30: =J27+J28+J29 -> 0 | K30: =IF(OR(J12=0,J12=""),"",J30/J12) | L30: =L27+L28+L29 -> 0 | M30: =IF(OR(L12=0,L12=""),"",L30/L12)
A31: Total Labor Costs and Related Expenses | B31: =B25+B30 -> 0 | C31: =IF(OR(B12=0,B12=""),"",B31/B12) | D31: =D25+D30 -> 0 | E31: =IF(OR(D12=0,D12=""),"",D31/D12) | F31: =F25+F30 -> 0 | G31: =IF(OR(F12=0,F12=""),"",F31/F12) | H31: =H25+H30 -> 0 | I31: =IF(OR(H12=0,H12=""),"",H31/H12) | J31: =J25+J30 -> 0 | K31: =IF(OR(J12=0,J12=""),"",J31/J12) | L31: =L25+L30 -> 0 | M31: =IF(OR(L12=0,L12=""),"",L31/L12)
A32: Other Expenses
A33: Cleaning Supplies | C33: =IF(OR(B12=0,B12=""),"",B33/B12) | E33: =IF(OR(D12=0,D12=""),"",D33/D12) | G33: =IF(OR(F12=0,F12=""),"",F33/F12) | I33: =IF(OR(H12=0,H12=""),"",H33/H12) | K33: =IF(OR(J12=0,J12=""),"",J33/J12) | M33: =IF(OR(L12=0,L12=""),"",L33/L12)
A34: Cluster Services | C34: =IF(OR(B12=0,B12=""),"",B34/B12) | E34: =IF(OR(D12=0,D12=""),"",D34/D12) | G34: =IF(OR(F12=0,F12=""),"",F34/F12) | I34: =IF(OR(H12=0,H12=""),"",H34/H12) | K34: =IF(OR(J12=0,J12=""),"",J34/J12) | M34: =IF(OR(L12=0,L12=""),"",L34/L12)
A35: Complimentary Services and Gifts | C35: =IF(OR(B12=0,B12=""),"",B35/B12) | E35: =IF(OR(D12=0,D12=""),"",D35/D12) | G35: =IF(OR(F12=0,F12=""),"",F35/F12) | I35: =IF(OR(H12=0,H12=""),"",H35/H12) | K35: =IF(OR(J12=0,J12=""),"",J35/J12) | M35: =IF(OR(L12=0,L12=""),"",L35/L12)
A36: Contract Services | C36: =IF(OR(B12=0,B12=""),"",B36/B12) | E36: =IF(OR(D12=0,D12=""),"",D36/D12) | G36: =IF(OR(F12=0,F12=""),"",F36/F12) | I36: =IF(OR(H12=0,H12=""),"",H36/H12) | K36: =IF(OR(J12=0,J12=""),"",J36/J12) | M36: =IF(OR(L12=0,L12=""),"",L36/L12)
A37: Corporate Office Reimbursables | C37: =IF(OR(B12=0,B12=""),"",B37/B12) | E37: =IF(OR(D12=0,D12=""),"",D37/D12) | G37: =IF(OR(F12=0,F12=""),"",F37/F12) | I37: =IF(OR(H12=0,H12=""),"",H37/H12) | K37: =IF(OR(J12=0,J12=""),"",J37/J12) | M37: =IF(OR(L12=0,L12=""),"",L37/L12)
A38: Decorations | C38: =IF(OR(B12=0,B12=""),"",B38/B12) | E38: =IF(OR(D12=0,D12=""),"",D38/D12) | G38: =IF(OR(F12=0,F12=""),"",F38/F12) | I38: =IF(OR(H12=0,H12=""),"",H38/H12) | K38: =IF(OR(J12=0,J12=""),"",J38/J12) | M38: =IF(OR(L12=0,L12=""),"",L38/L12)
A39: Dues and Subscriptions | C39: =IF(OR(B12=0,B12=""),"",B39/B12) | E39: =IF(OR(D12=0,D12=""),"",D39/D12) | G39: =IF(OR(F12=0,F12=""),"",F39/F12) | I39: =IF(OR(H12=0,H12=""),"",H39/H12) | K39: =IF(OR(J12=0,J12=""),"",J39/J12) | M39: =IF(OR(L12=0,L12=""),"",L39/L12)
A40: Entertainment - In-House | C40: =IF(OR(B12=0,B12=""),"",B40/B12) | E40: =IF(OR(D12=0,D12=""),"",D40/D12) | G40: =IF(OR(F12=0,F12=""),"",F40/F12) | I40: =IF(OR(H12=0,H12=""),"",H40/H12) | K40: =IF(OR(J12=0,J12=""),"",J40/J12) | M40: =IF(OR(L12=0,L12=""),"",L40/L12)
A41: Equipment Rental | C41: =IF(OR(B12=0,B12=""),"",B41/B12) | E41: =IF(OR(D12=0,D12=""),"",D41/D12) | G41: =IF(OR(F12=0,F12=""),"",F41/F12) | I41: =IF(OR(H12=0,H12=""),"",H41/H12) | K41: =IF(OR(J12=0,J12=""),"",J41/J12) | M41: =IF(OR(L12=0,L12=""),"",L41/L12)
A42: Laundry and Dry Cleaning | C42: =IF(OR(B12=0,B12=""),"",B42/B12) | E42: =IF(OR(D12=0,D12=""),"",D42/D12) | G42: =IF(OR(F12=0,F12=""),"",F42/F12) | I42: =IF(OR(H12=0,H12=""),"",H42/H12) | K42: =IF(OR(J12=0,J12=""),"",J42/J12) | M42: =IF(OR(L12=0,L12=""),"",L42/L12)
A43: Licenses and Permits | C43: =IF(OR(B12=0,B12=""),"",B43/B12) | E43: =IF(OR(D12=0,D12=""),"",D43/D12) | G43: =IF(OR(F12=0,F12=""),"",F43/F12) | I43: =IF(OR(H12=0,H12=""),"",H43/H12) | K43: =IF(OR(J12=0,J12=""),"",J43/J12) | M43: =IF(OR(L12=0,L12=""),"",L43/L12)
A44: Management Fees | C44: =IF(OR(B12=0,B12=""),"",B44/B12) | E44: =IF(OR(D12=0,D12=""),"",D44/D12) | G44: =IF(OR(F12=0,F12=""),"",F44/F12) | I44: =IF(OR(H12=0,H12=""),"",H44/H12) | K44: =IF(OR(J12=0,J12=""),"",J44/J12) | M44: =IF(OR(L12=0,L12=""),"",L44/L12)
A45: Miscellaneous | C45: =IF(OR(B12=0,B12=""),"",B45/B12) | E45: =IF(OR(D12=0,D12=""),"",D45/D12) | G45: =IF(OR(F12=0,F12=""),"",F45/F12) | I45: =IF(OR(H12=0,H12=""),"",H45/H12) | K45: =IF(OR(J12=0,J12=""),"",J45/J12) | M45: =IF(OR(L12=0,L12=""),"",L45/L12)
A46: Operating Supplies | C46: =IF(OR(B12=0,B12=""),"",B46/B12) | E46: =IF(OR(D12=0,D12=""),"",D46/D12) | G46: =IF(OR(F12=0,F12=""),"",F46/F12) | I46: =IF(OR(H12=0,H12=""),"",H46/H12) | K46: =IF(OR(J12=0,J12=""),"",J46/J12) | M46: =IF(OR(L12=0,L12=""),"",L46/L12)
A47: Printing and Stationery | C47: =IF(OR(B12=0,B12=""),"",B47/B12) | E47: =IF(OR(D12=0,D12=""),"",D47/D12) | G47: =IF(OR(F12=0,F12=""),"",F47/F12) | I47: =IF(OR(H12=0,H12=""),"",H47/H12) | K47: =IF(OR(J12=0,J12=""),"",J47/J12) | M47: =IF(OR(L12=0,L12=""),"",L47/L12)
A48: Rent | C48: =IF(OR(B12=0,B12=""),"",B48/B12) | E48: =IF(OR(D12=0,D12=""),"",D48/D12) | G48: =IF(OR(F12=0,F12=""),"",F48/F12) | I48: =IF(OR(H12=0,H12=""),"",H48/H12) | K48: =IF(OR(J12=0,J12=""),"",J48/J12) | M48: =IF(OR(L12=0,L12=""),"",L48/L12)
A49: Royalty Fees | C49: =IF(OR(B12=0,B12=""),"",B49/B12) | E49: =IF(OR(D12=0,D12=""),"",D49/D12) | G49: =IF(OR(F12=0,F12=""),"",F49/F12) | I49: =IF(OR(H12=0,H12=""),"",H49/H12) | K49: =IF(OR(J12=0,J12=""),"",J49/J12) | M49: =IF(OR(L12=0,L12=""),"",L49/L12)
A50: Training | C50: =IF(OR(B12=0,B12=""),"",B50/B12) | E50: =IF(OR(D12=0,D12=""),"",D50/D12) | G50: =IF(OR(F12=0,F12=""),"",F50/F12) | I50: =IF(OR(H12=0,H12=""),"",H50/H12) | K50: =IF(OR(J12=0,J12=""),"",J50/J12) | M50: =IF(OR(L12=0,L12=""),"",L50/L12)
A51: Travel - Meals and Entertainment | C51: =IF(OR(B12=0,B12=""),"",B51/B12) | E51: =IF(OR(D12=0,D12=""),"",D51/D12) | G51: =IF(OR(F12=0,F12=""),"",F51/F12) | I51: =IF(OR(H12=0,H12=""),"",H51/H12) | K51: =IF(OR(J12=0,J12=""),"",J51/J12) | M51: =IF(OR(L12=0,L12=""),"",L51/L12)
A52: Travel - Other | C52: =IF(OR(B12=0,B12=""),"",B52/B12) | E52: =IF(OR(D12=0,D12=""),"",D52/D12) | G52: =IF(OR(F12=0,F12=""),"",F52/F12) | I52: =IF(OR(H12=0,H12=""),"",H52/H12) | K52: =IF(OR(J12=0,J12=""),"",J52/J12) | M52: =IF(OR(L12=0,L12=""),"",L52/L12)
A53: Uniform Costs | C53: =IF(OR(B12=0,B12=""),"",B53/B12) | E53: =IF(OR(D12=0,D12=""),"",D53/D12) | G53: =IF(OR(F12=0,F12=""),"",F53/F12) | I53: =IF(OR(H12=0,H12=""),"",H53/H12) | K53: =IF(OR(J12=0,J12=""),"",J53/J12) | M53: =IF(OR(L12=0,L12=""),"",L53/L12)
A54: Uniform Laundry | C54: =IF(OR(B12=0,B12=""),"",B54/B12) | E54: =IF(OR(D12=0,D12=""),"",D54/D12) | G54: =IF(OR(F12=0,F12=""),"",F54/F12) | I54: =IF(OR(H12=0,H12=""),"",H54/H12) | K54: =IF(OR(J12=0,J12=""),"",J54/J12) | M54: =IF(OR(L12=0,L12=""),"",L54/L12)
A55: Total Other Expenses | B55: =B33+B34+B35+B36+B37+B38+B39+B40+B41+B42+B43+B44+B45+B46+B47+B48+B49+B50+B51+B52+B53+B54 -> 0 | C55: =IF(OR(B12=0,B12=""),"",B55/B12) | D55: =D33+D34+D35+D36+D37+D38+D39+D40+D41+D42+D43+D44+D45+D46+D47+D48+D49+D50+D51+D52+D53+D54 -> 0 | E55: =IF(OR(D12=0,D12=""),"",D55/D12) | F55: =F33+F34+F35+F36+F37+F38+F39+F40+F41+F42+F43+F44+F45+F46+F47+F48+F49+F50+F51+F52+F53+F54 -> 0 | G55: =IF(OR(F12=0,F12=""),"",F55/F12) | H55: =H33+H34+H35+H36+H37+H38+H39+H40+H41+H42+H43+H44+H45+H46+H47+H48+H49+H50+H51+H52+H53+H54 -> 0 | I55: =IF(OR(H12=0,H12=""),"",H55/H12) | J55: =J33+J34+J35+J36+J37+J38+J39+J40+J41+J42+J43+J44+J45+J46+J47+J48+J49+J50+J51+J52+J53+J54 -> 0 | K55: =IF(OR(J12=0,J12=""),"",J55/J12) | L55: =L33+L34+L35+L36+L37+L38+L39+L40+L41+L42+L43+L44+L45+L46+L47+L48+L49+L50+L51+L52+L53+L54 -> 0 | M55: =IF(OR(L12=0,L12=""),"",L55/L12)
A56: Total Expenses | B56: =B31+B55 -> 0 | C56: =IF(OR(B12=0,B12=""),"",B56/B12) | D56: =D31+D55 -> 0 | E56: =IF(OR(D12=0,D12=""),"",D56/D12) | F56: =F31+F55 -> 0 | G56: =IF(OR(F12=0,F12=""),"",F56/F12) | H56: =H31+H55 -> 0 | I56: =IF(OR(H12=0,H12=""),"",H56/H12) | J56: =J31+J55 -> 0 | K56: =IF(OR(J12=0,J12=""),"",J56/J12) | L56: =L31+L55 -> 0 | M56: =IF(OR(L12=0,L12=""),"",L56/L12)
A57: Departmental Profit | B57: =B14-B55 -> 0 | C57: =IF(OR(B12=0,B12=""),"",B57/B12) | D57: =D14-D55 -> 0 | E57: =IF(OR(D12=0,D12=""),"",D57/D12) | F57: =F14-F55 -> 0 | G57: =IF(OR(F12=0,F12=""),"",F57/F12) | H57: =H14-H55 -> 0 | I57: =IF(OR(H12=0,H12=""),"",H57/H12) | J57: =J14-J55 -> 0 | K57: =IF(OR(J12=0,J12=""),"",J57/J12) | L57: =L14-L55 -> 0 | M57: =IF(OR(L12=0,L12=""),"",L57/L12)

Sheet Sub-Sch 3-x - Generic
A1: OTHER OPERATED DEPARTMENTS — SUB-SCHEDULE 3-x (Generic)
A2: Property: | B2: ='Setup & Assumptions'!$B$4 -> Enter property name | H2: Period / Year: | J2: ='Setup & Assumptions'!$B$5 -> e.g. January 2026 / FY2026
A3: Generic template for any Other Operated Department (Marina, Guest Laundry, Business Center, Retail Store, etc.). Rename revenue/expense lines as warranted; sub-totals roll into Schedule 3.
B4: Current Period | H4: Year-To-Date
B5: Actual | D5: Forecast / Budget | F5: Prior Year | H5: Actual | J5: Forecast / Budget | L5: Prior Year
A6: Line Item | B6: $ | C6: % | D6: $ | E6: % | F6: $ | G6: % | H6: $ | I6: % | J6: $ | K6: % | L6: $ | M6: %
A7: Revenue
A8: Revenue | C8: =IF(OR(B10=0,B10=""),"",B8/B10) | E8: =IF(OR(D10=0,D10=""),"",D8/D10) | G8: =IF(OR(F10=0,F10=""),"",F8/F10) | I8: =IF(OR(H10=0,H10=""),"",H8/H10) | K8: =IF(OR(J10=0,J10=""),"",J8/J10) | M8: =IF(OR(L10=0,L10=""),"",L8/L10)
A9: Less: Allowances | C9: =IF(OR(B10=0,B10=""),"",B9/B10) | E9: =IF(OR(D10=0,D10=""),"",D9/D10) | G9: =IF(OR(F10=0,F10=""),"",F9/F10) | I9: =IF(OR(H10=0,H10=""),"",H9/H10) | K9: =IF(OR(J10=0,J10=""),"",J9/J10) | M9: =IF(OR(L10=0,L10=""),"",L9/L10)
A10: Total Generic Revenue | B10: =B8-B9 -> 0 | C10: =IF(OR(B10=0,B10=""),"",B10/B10) | D10: =D8-D9 -> 0 | E10: =IF(OR(D10=0,D10=""),"",D10/D10) | F10: =F8-F9 -> 0 | G10: =IF(OR(F10=0,F10=""),"",F10/F10) | H10: =H8-H9 -> 0 | I10: =IF(OR(H10=0,H10=""),"",H10/H10) | J10: =J8-J9 -> 0 | K10: =IF(OR(J10=0,J10=""),"",J10/J10) | L10: =L8-L9 -> 0 | M10: =IF(OR(L10=0,L10=""),"",L10/L10)
A11: Cost of Sales | C11: =IF(OR(B10=0,B10=""),"",B11/B10) | E11: =IF(OR(D10=0,D10=""),"",D11/D10) | G11: =IF(OR(F10=0,F10=""),"",F11/F10) | I11: =IF(OR(H10=0,H10=""),"",H11/H10) | K11: =IF(OR(J10=0,J10=""),"",J11/J10) | M11: =IF(OR(L10=0,L10=""),"",L11/L10)
A12: Gross Profit | B12: =B10-B11 -> 0 | C12: =IF(OR(B10=0,B10=""),"",B12/B10) | D12: =D10-D11 -> 0 | E12: =IF(OR(D10=0,D10=""),"",D12/D10) | F12: =F10-F11 -> 0 | G12: =IF(OR(F10=0,F10=""),"",F12/F10) | H12: =H10-H11 -> 0 | I12: =IF(OR(H10=0,H10=""),"",H12/H10) | J12: =J10-J11 -> 0 | K12: =IF(OR(J10=0,J10=""),"",J12/J10) | L12: =L10-L11 -> 0 | M12: =IF(OR(L10=0,L10=""),"",L12/L10)
A13: Expenses
A14: Labor Costs and Related Expenses
A15: Salaries, Wages, Service Charges, Contracted Labor and Bonuses
A16: Salaries and Wages
A17: Management
A18: Non-Management
A19: Sub-Total: Salaries and Wages | B19: =B17+B18 -> 0 | D19: =D17+D18 -> 0 | F19: =F17+F18 -> 0 | H19: =H17+H18 -> 0 | J19: =J17+J18 -> 0 | L19: =L17+L18 -> 0
A20: Service Charge Distribution
A21: Contracted, Leased and Outsourced Labor
A22: Bonuses and Incentives
A23: Total Salaries, Wages, Service Charges, Contracted Labor and Bonuses | B23: =B19+B20+B21+B22 -> 0 | C23: =IF(OR(B10=0,B10=""),"",B23/B10) | D23: =D19+D20+D21+D22 -> 0 | E23: =IF(OR(D10=0,D10=""),"",D23/D10) | F23: =F19+F20+F21+F22 -> 0 | G23: =IF(OR(F10=0,F10=""),"",F23/F10) | H23: =H19+H20+H21+H22 -> 0 | I23: =IF(OR(H10=0,H10=""),"",H23/H10) | J23: =J19+J20+J21+J22 -> 0 | K23: =IF(OR(J10=0,J10=""),"",J23/J10) | L23: =L19+L20+L21+L22 -> 0 | M23: =IF(OR(L10=0,L10=""),"",L23/L10)
A24: Payroll-Related Expenses
A25: Payroll Taxes | C25: =IF(OR(B10=0,B10=""),"",B25/B10) | E25: =IF(OR(D10=0,D10=""),"",D25/D10) | G25: =IF(OR(F10=0,F10=""),"",F25/F10) | I25: =IF(OR(H10=0,H10=""),"",H25/H10) | K25: =IF(OR(J10=0,J10=""),"",J25/J10) | M25: =IF(OR(L10=0,L10=""),"",L25/L10)
A26: Supplemental Pay | C26: =IF(OR(B10=0,B10=""),"",B26/B10) | E26: =IF(OR(D10=0,D10=""),"",D26/D10) | G26: =IF(OR(F10=0,F10=""),"",F26/F10) | I26: =IF(OR(H10=0,H10=""),"",H26/H10) | K26: =IF(OR(J10=0,J10=""),"",J26/J10) | M26: =IF(OR(L10=0,L10=""),"",L26/L10)
A27: Employee Benefits | C27: =IF(OR(B10=0,B10=""),"",B27/B10) | E27: =IF(OR(D10=0,D10=""),"",D27/D10) | G27: =IF(OR(F10=0,F10=""),"",F27/F10) | I27: =IF(OR(H10=0,H10=""),"",H27/H10) | K27: =IF(OR(J10=0,J10=""),"",J27/J10) | M27: =IF(OR(L10=0,L10=""),"",L27/L10)
A28: Total Payroll-Related Expenses | B28: =B25+B26+B27 -> 0 | C28: =IF(OR(B10=0,B10=""),"",B28/B10) | D28: =D25+D26+D27 -> 0 | E28: =IF(OR(D10=0,D10=""),"",D28/D10) | F28: =F25+F26+F27 -> 0 | G28: =IF(OR(F10=0,F10=""),"",F28/F10) | H28: =H25+H26+H27 -> 0 | I28: =IF(OR(H10=0,H10=""),"",H28/H10) | J28: =J25+J26+J27 -> 0 | K28: =IF(OR(J10=0,J10=""),"",J28/J10) | L28: =L25+L26+L27 -> 0 | M28: =IF(OR(L10=0,L10=""),"",L28/L10)
A29: Total Labor Costs and Related Expenses | B29: =B23+B28 -> 0 | C29: =IF(OR(B10=0,B10=""),"",B29/B10) | D29: =D23+D28 -> 0 | E29: =IF(OR(D10=0,D10=""),"",D29/D10) | F29: =F23+F28 -> 0 | G29: =IF(OR(F10=0,F10=""),"",F29/F10) | H29: =H23+H28 -> 0 | I29: =IF(OR(H10=0,H10=""),"",H29/H10) | J29: =J23+J28 -> 0 | K29: =IF(OR(J10=0,J10=""),"",J29/J10) | L29: =L23+L28 -> 0 | M29: =IF(OR(L10=0,L10=""),"",L29/L10)
A30: Other Expenses
A31: Cleaning Supplies | C31: =IF(OR(B10=0,B10=""),"",B31/B10) | E31: =IF(OR(D10=0,D10=""),"",D31/D10) | G31: =IF(OR(F10=0,F10=""),"",F31/F10) | I31: =IF(OR(H10=0,H10=""),"",H31/H10) | K31: =IF(OR(J10=0,J10=""),"",J31/J10) | M31: =IF(OR(L10=0,L10=""),"",L31/L10)
A32: Cluster Services | C32: =IF(OR(B10=0,B10=""),"",B32/B10) | E32: =IF(OR(D10=0,D10=""),"",D32/D10) | G32: =IF(OR(F10=0,F10=""),"",F32/F10) | I32: =IF(OR(H10=0,H10=""),"",H32/H10) | K32: =IF(OR(J10=0,J10=""),"",J32/J10) | M32: =IF(OR(L10=0,L10=""),"",L32/L10)
A33: Complimentary Services and Gifts | C33: =IF(OR(B10=0,B10=""),"",B33/B10) | E33: =IF(OR(D10=0,D10=""),"",D33/D10) | G33: =IF(OR(F10=0,F10=""),"",F33/F10) | I33: =IF(OR(H10=0,H10=""),"",H33/H10) | K33: =IF(OR(J10=0,J10=""),"",J33/J10) | M33: =IF(OR(L10=0,L10=""),"",L33/L10)
A34: Contract Services | C34: =IF(OR(B10=0,B10=""),"",B34/B10) | E34: =IF(OR(D10=0,D10=""),"",D34/D10) | G34: =IF(OR(F10=0,F10=""),"",F34/F10) | I34: =IF(OR(H10=0,H10=""),"",H34/H10) | K34: =IF(OR(J10=0,J10=""),"",J34/J10) | M34: =IF(OR(L10=0,L10=""),"",L34/L10)
A35: Corporate Office Reimbursables | C35: =IF(OR(B10=0,B10=""),"",B35/B10) | E35: =IF(OR(D10=0,D10=""),"",D35/D10) | G35: =IF(OR(F10=0,F10=""),"",F35/F10) | I35: =IF(OR(H10=0,H10=""),"",H35/H10) | K35: =IF(OR(J10=0,J10=""),"",J35/J10) | M35: =IF(OR(L10=0,L10=""),"",L35/L10)
A36: Decorations | C36: =IF(OR(B10=0,B10=""),"",B36/B10) | E36: =IF(OR(D10=0,D10=""),"",D36/D10) | G36: =IF(OR(F10=0,F10=""),"",F36/F10) | I36: =IF(OR(H10=0,H10=""),"",H36/H10) | K36: =IF(OR(J10=0,J10=""),"",J36/J10) | M36: =IF(OR(L10=0,L10=""),"",L36/L10)
A37: Dues and Subscriptions | C37: =IF(OR(B10=0,B10=""),"",B37/B10) | E37: =IF(OR(D10=0,D10=""),"",D37/D10) | G37: =IF(OR(F10=0,F10=""),"",F37/F10) | I37: =IF(OR(H10=0,H10=""),"",H37/H10) | K37: =IF(OR(J10=0,J10=""),"",J37/J10) | M37: =IF(OR(L10=0,L10=""),"",L37/L10)
A38: Entertainment - In-House | C38: =IF(OR(B10=0,B10=""),"",B38/B10) | E38: =IF(OR(D10=0,D10=""),"",D38/D10) | G38: =IF(OR(F10=0,F10=""),"",F38/F10) | I38: =IF(OR(H10=0,H10=""),"",H38/H10) | K38: =IF(OR(J10=0,J10=""),"",J38/J10) | M38: =IF(OR(L10=0,L10=""),"",L38/L10)
A39: Equipment Rental | C39: =IF(OR(B10=0,B10=""),"",B39/B10) | E39: =IF(OR(D10=0,D10=""),"",D39/D10) | G39: =IF(OR(F10=0,F10=""),"",F39/F10) | I39: =IF(OR(H10=0,H10=""),"",H39/H10) | K39: =IF(OR(J10=0,J10=""),"",J39/J10) | M39: =IF(OR(L10=0,L10=""),"",L39/L10)
A40: Laundry and Dry Cleaning | C40: =IF(OR(B10=0,B10=""),"",B40/B10) | E40: =IF(OR(D10=0,D10=""),"",D40/D10) | G40: =IF(OR(F10=0,F10=""),"",F40/F10) | I40: =IF(OR(H10=0,H10=""),"",H40/H10) | K40: =IF(OR(J10=0,J10=""),"",J40/J10) | M40: =IF(OR(L10=0,L10=""),"",L40/L10)
A41: Licenses and Permits | C41: =IF(OR(B10=0,B10=""),"",B41/B10) | E41: =IF(OR(D10=0,D10=""),"",D41/D10) | G41: =IF(OR(F10=0,F10=""),"",F41/F10) | I41: =IF(OR(H10=0,H10=""),"",H41/H10) | K41: =IF(OR(J10=0,J10=""),"",J41/J10) | M41: =IF(OR(L10=0,L10=""),"",L41/L10)
A42: Linen | C42: =IF(OR(B10=0,B10=""),"",B42/B10) | E42: =IF(OR(D10=0,D10=""),"",D42/D10) | G42: =IF(OR(F10=0,F10=""),"",F42/F10) | I42: =IF(OR(H10=0,H10=""),"",H42/H10) | K42: =IF(OR(J10=0,J10=""),"",J42/J10) | M42: =IF(OR(L10=0,L10=""),"",L42/L10)
A43: Management Fees | C43: =IF(OR(B10=0,B10=""),"",B43/B10) | E43: =IF(OR(D10=0,D10=""),"",D43/D10) | G43: =IF(OR(F10=0,F10=""),"",F43/F10) | I43: =IF(OR(H10=0,H10=""),"",H43/H10) | K43: =IF(OR(J10=0,J10=""),"",J43/J10) | M43: =IF(OR(L10=0,L10=""),"",L43/L10)
A44: Miscellaneous | C44: =IF(OR(B10=0,B10=""),"",B44/B10) | E44: =IF(OR(D10=0,D10=""),"",D44/D10) | G44: =IF(OR(F10=0,F10=""),"",F44/F10) | I44: =IF(OR(H10=0,H10=""),"",H44/H10) | K44: =IF(OR(J10=0,J10=""),"",J44/J10) | M44: =IF(OR(L10=0,L10=""),"",L44/L10)
A45: Operating Supplies | C45: =IF(OR(B10=0,B10=""),"",B45/B10) | E45: =IF(OR(D10=0,D10=""),"",D45/D10) | G45: =IF(OR(F10=0,F10=""),"",F45/F10) | I45: =IF(OR(H10=0,H10=""),"",H45/H10) | K45: =IF(OR(J10=0,J10=""),"",J45/J10) | M45: =IF(OR(L10=0,L10=""),"",L45/L10)
A46: Printing and Stationery | C46: =IF(OR(B10=0,B10=""),"",B46/B10) | E46: =IF(OR(D10=0,D10=""),"",D46/D10) | G46: =IF(OR(F10=0,F10=""),"",F46/F10) | I46: =IF(OR(H10=0,H10=""),"",H46/H10) | K46: =IF(OR(J10=0,J10=""),"",J46/J10) | M46: =IF(OR(L10=0,L10=""),"",L46/L10)
A47: Royalty Fees | C47: =IF(OR(B10=0,B10=""),"",B47/B10) | E47: =IF(OR(D10=0,D10=""),"",D47/D10) | G47: =IF(OR(F10=0,F10=""),"",F47/F10) | I47: =IF(OR(H10=0,H10=""),"",H47/H10) | K47: =IF(OR(J10=0,J10=""),"",J47/J10) | M47: =IF(OR(L10=0,L10=""),"",L47/L10)
A48: Training | C48: =IF(OR(B10=0,B10=""),"",B48/B10) | E48: =IF(OR(D10=0,D10=""),"",D48/D10) | G48: =IF(OR(F10=0,F10=""),"",F48/F10) | I48: =IF(OR(H10=0,H10=""),"",H48/H10) | K48: =IF(OR(J10=0,J10=""),"",J48/J10) | M48: =IF(OR(L10=0,L10=""),"",L48/L10)
A49: Travel - Meals and Entertainment | C49: =IF(OR(B10=0,B10=""),"",B49/B10) | E49: =IF(OR(D10=0,D10=""),"",D49/D10) | G49: =IF(OR(F10=0,F10=""),"",F49/F10) | I49: =IF(OR(H10=0,H10=""),"",H49/H10) | K49: =IF(OR(J10=0,J10=""),"",J49/J10) | M49: =IF(OR(L10=0,L10=""),"",L49/L10)
A50: Travel - Other | C50: =IF(OR(B10=0,B10=""),"",B50/B10) | E50: =IF(OR(D10=0,D10=""),"",D50/D10) | G50: =IF(OR(F10=0,F10=""),"",F50/F10) | I50: =IF(OR(H10=0,H10=""),"",H50/H10) | K50: =IF(OR(J10=0,J10=""),"",J50/J10) | M50: =IF(OR(L10=0,L10=""),"",L50/L10)
A51: Uniform Costs | C51: =IF(OR(B10=0,B10=""),"",B51/B10) | E51: =IF(OR(D10=0,D10=""),"",D51/D10) | G51: =IF(OR(F10=0,F10=""),"",F51/F10) | I51: =IF(OR(H10=0,H10=""),"",H51/H10) | K51: =IF(OR(J10=0,J10=""),"",J51/J10) | M51: =IF(OR(L10=0,L10=""),"",L51/L10)
A52: Uniform Laundry | C52: =IF(OR(B10=0,B10=""),"",B52/B10) | E52: =IF(OR(D10=0,D10=""),"",D52/D10) | G52: =IF(OR(F10=0,F10=""),"",F52/F10) | I52: =IF(OR(H10=0,H10=""),"",H52/H10) | K52: =IF(OR(J10=0,J10=""),"",J52/J10) | M52: =IF(OR(L10=0,L10=""),"",L52/L10)
A53: Total Other Expenses | B53: =B31+B32+B33+B34+B35+B36+B37+B38+B39+B40+B41+B42+B43+B44+B45+B46+B47+B48+B49+B50+B51+B52 -> 0 | C53: =IF(OR(B10=0,B10=""),"",B53/B10) | D53: =D31+D32+D33+D34+D35+D36+D37+D38+D39+D40+D41+D42+D43+D44+D45+D46+D47+D48+D49+D50+D51+D52 -> 0 | E53: =IF(OR(D10=0,D10=""),"",D53/D10) | F53: =F31+F32+F33+F34+F35+F36+F37+F38+F39+F40+F41+F42+F43+F44+F45+F46+F47+F48+F49+F50+F51+F52 -> 0 | G53: =IF(OR(F10=0,F10=""),"",F53/F10) | H53: =H31+H32+H33+H34+H35+H36+H37+H38+H39+H40+H41+H42+H43+H44+H45+H46+H47+H48+H49+H50+H51+H52 -> 0 | I53: =IF(OR(H10=0,H10=""),"",H53/H10) | J53: =J31+J32+J33+J34+J35+J36+J37+J38+J39+J40+J41+J42+J43+J44+J45+J46+J47+J48+J49+J50+J51+J52 -> 0 | K53: =IF(OR(J10=0,J10=""),"",J53/J10) | L53: =L31+L32+L33+L34+L35+L36+L37+L38+L39+L40+L41+L42+L43+L44+L45+L46+L47+L48+L49+L50+L51+L52 -> 0 | M53: =IF(OR(L10=0,L10=""),"",L53/L10)
A54: Total Expenses | B54: =B29+B53 -> 0 | C54: =IF(OR(B10=0,B10=""),"",B54/B10) | D54: =D29+D53 -> 0 | E54: =IF(OR(D10=0,D10=""),"",D54/D10) | F54: =F29+F53 -> 0 | G54: =IF(OR(F10=0,F10=""),"",F54/F10) | H54: =H29+H53 -> 0 | I54: =IF(OR(H10=0,H10=""),"",H54/H10) | J54: =J29+J53 -> 0 | K54: =IF(OR(J10=0,J10=""),"",J54/J10) | L54: =L29+L53 -> 0 | M54: =IF(OR(L10=0,L10=""),"",L54/L10)
A55: Departmental Profit | B55: =B12-B53 -> 0 | C55: =IF(OR(B10=0,B10=""),"",B55/B10) | D55: =D12-D53 -> 0 | E55: =IF(OR(D10=0,D10=""),"",D55/D10) | F55: =F12-F53 -> 0 | G55: =IF(OR(F10=0,F10=""),"",F55/F10) | H55: =H12-H53 -> 0 | I55: =IF(OR(H10=0,H10=""),"",H55/H10) | J55: =J12-J53 -> 0 | K55: =IF(OR(J10=0,J10=""),"",J55/J10) | L55: =L12-L53 -> 0 | M55: =IF(OR(L10=0,L10=""),"",L55/L10)

Sheet Sub-Sch 3-xx - Minor Op Depts
A1: MINOR OPERATED DEPARTMENTS — SUB-SCHEDULE 3-xx
A2: Property: | B2: ='Setup & Assumptions'!$B$4 -> Enter property name | H2: Period / Year: | J2: ='Setup & Assumptions'!$B$5 -> e.g. January 2026 / FY2026
A3: Examples: Vending, Retail Kiosk, Video Games, In-Room Movies, Guest Laundry, Guest Communications, Services and CAM, Occasional F&B.
B4: Current Period | H4: Year-To-Date
B5: Actual | D5: Forecast / Budget | F5: Prior Year | H5: Actual | J5: Forecast / Budget | L5: Prior Year
A6: Line Item | B6: $ | C6: % | D6: $ | E6: % | F6: $ | G6: % | H6: $ | I6: % | J6: $ | K6: % | L6: $ | M6: %
A7: Departmental Revenue
A8: Minor Operated Department 1 | C8: =IF(OR(B13=0,B13=""),"",B8/B13) | E8: =IF(OR(D13=0,D13=""),"",D8/D13) | G8: =IF(OR(F13=0,F13=""),"",F8/F13) | I8: =IF(OR(H13=0,H13=""),"",H8/H13) | K8: =IF(OR(J13=0,J13=""),"",J8/J13) | M8: =IF(OR(L13=0,L13=""),"",L8/L13)
A9: Minor Operated Department 2 | C9: =IF(OR(B13=0,B13=""),"",B9/B13) | E9: =IF(OR(D13=0,D13=""),"",D9/D13) | G9: =IF(OR(F13=0,F13=""),"",F9/F13) | I9: =IF(OR(H13=0,H13=""),"",H9/H13) | K9: =IF(OR(J13=0,J13=""),"",J9/J13) | M9: =IF(OR(L13=0,L13=""),"",L9/L13)
A10: Minor Operated Department 3 | C10: =IF(OR(B13=0,B13=""),"",B10/B13) | E10: =IF(OR(D13=0,D13=""),"",D10/D13) | G10: =IF(OR(F13=0,F13=""),"",F10/F13) | I10: =IF(OR(H13=0,H13=""),"",H10/H13) | K10: =IF(OR(J13=0,J13=""),"",J10/J13) | M10: =IF(OR(L13=0,L13=""),"",L10/L13)
A11: Minor Operated Department 4 | C11: =IF(OR(B13=0,B13=""),"",B11/B13) | E11: =IF(OR(D13=0,D13=""),"",D11/D13) | G11: =IF(OR(F13=0,F13=""),"",F11/F13) | I11: =IF(OR(H13=0,H13=""),"",H11/H13) | K11: =IF(OR(J13=0,J13=""),"",J11/J13) | M11: =IF(OR(L13=0,L13=""),"",L11/L13)
A12: Less: Allowances | C12: =IF(OR(B13=0,B13=""),"",B12/B13) | E12: =IF(OR(D13=0,D13=""),"",D12/D13) | G12: =IF(OR(F13=0,F13=""),"",F12/F13) | I12: =IF(OR(H13=0,H13=""),"",H12/H13) | K12: =IF(OR(J13=0,J13=""),"",J12/J13) | M12: =IF(OR(L13=0,L13=""),"",L12/L13)
A13: Total Departmental Revenue | B13: =B8+B9+B10+B11-B12 -> 0 | C13: =IF(OR(B13=0,B13=""),"",B13/B13) | D13: =D8+D9+D10+D11-D12 -> 0 | E13: =IF(OR(D13=0,D13=""),"",D13/D13) | F13: =F8+F9+F10+F11-F12 -> 0 | G13: =IF(OR(F13=0,F13=""),"",F13/F13) | H13: =H8+H9+H10+H11-H12 -> 0 | I13: =IF(OR(H13=0,H13=""),"",H13/H13) | J13: =J8+J9+J10+J11-J12 -> 0 | K13: =IF(OR(J13=0,J13=""),"",J13/J13) | L13: =L8+L9+L10+L11-L12 -> 0 | M13: =IF(OR(L13=0,L13=""),"",L13/L13)
A14: Departmental Expenses (Cost of Sales + Total Expenses)
A15: Minor Operated Department 1 | C15: =IF(OR(B13=0,B13=""),"",B15/B13) | E15: =IF(OR(D13=0,D13=""),"",D15/D13) | G15: =IF(OR(F13=0,F13=""),"",F15/F13) | I15: =IF(OR(H13=0,H13=""),"",H15/H13) | K15: =IF(OR(J13=0,J13=""),"",J15/J13) | M15: =IF(OR(L13=0,L13=""),"",L15/L13)
A16: Minor Operated Department 2 | C16: =IF(OR(B13=0,B13=""),"",B16/B13) | E16: =IF(OR(D13=0,D13=""),"",D16/D13) | G16: =IF(OR(F13=0,F13=""),"",F16/F13) | I16: =IF(OR(H13=0,H13=""),"",H16/H13) | K16: =IF(OR(J13=0,J13=""),"",J16/J13) | M16: =IF(OR(L13=0,L13=""),"",L16/L13)
A17: Minor Operated Department 3 | C17: =IF(OR(B13=0,B13=""),"",B17/B13) | E17: =IF(OR(D13=0,D13=""),"",D17/D13) | G17: =IF(OR(F13=0,F13=""),"",F17/F13) | I17: =IF(OR(H13=0,H13=""),"",H17/H13) | K17: =IF(OR(J13=0,J13=""),"",J17/J13) | M17: =IF(OR(L13=0,L13=""),"",L17/L13)
A18: Minor Operated Department 4 | C18: =IF(OR(B13=0,B13=""),"",B18/B13) | E18: =IF(OR(D13=0,D13=""),"",D18/D13) | G18: =IF(OR(F13=0,F13=""),"",F18/F13) | I18: =IF(OR(H13=0,H13=""),"",H18/H13) | K18: =IF(OR(J13=0,J13=""),"",J18/J13) | M18: =IF(OR(L13=0,L13=""),"",L18/L13)
A19: Total Minor Operated Departmental Expenses | B19: =B15+B16+B17+B18 -> 0 | C19: =IF(OR(B13=0,B13=""),"",B19/B13) | D19: =D15+D16+D17+D18 -> 0 | E19: =IF(OR(D13=0,D13=""),"",D19/D13) | F19: =F15+F16+F17+F18 -> 0 | G19: =IF(OR(F13=0,F13=""),"",F19/F13) | H19: =H15+H16+H17+H18 -> 0 | I19: =IF(OR(H13=0,H13=""),"",H19/H13) | J19: =J15+J16+J17+J18 -> 0 | K19: =IF(OR(J13=0,J13=""),"",J19/J13) | L19: =L15+L16+L17+L18 -> 0 | M19: =IF(OR(L13=0,L13=""),"",L19/L13)
A20: Departmental Profit
A21: Minor Operated Department 1 | B21: =B8-B15 -> 0 | C21: =IF(OR(B13=0,B13=""),"",B21/B13) | D21: =D8-D15 -> 0 | E21: =IF(OR(D13=0,D13=""),"",D21/D13) | F21: =F8-F15 -> 0 | G21: =IF(OR(F13=0,F13=""),"",F21/F13) | H21: =H8-H15 -> 0 | I21: =IF(OR(H13=0,H13=""),"",H21/H13) | J21: =J8-J15 -> 0 | K21: =IF(OR(J13=0,J13=""),"",J21/J13) | L21: =L8-L15 -> 0 | M21: =IF(OR(L13=0,L13=""),"",L21/L13)
A22: Minor Operated Department 2 | B22: =B9-B16 -> 0 | C22: =IF(OR(B13=0,B13=""),"",B22/B13) | D22: =D9-D16 -> 0 | E22: =IF(OR(D13=0,D13=""),"",D22/D13) | F22: =F9-F16 -> 0 | G22: =IF(OR(F13=0,F13=""),"",F22/F13) | H22: =H9-H16 -> 0 | I22: =IF(OR(H13=0,H13=""),"",H22/H13) | J22: =J9-J16 -> 0 | K22: =IF(OR(J13=0,J13=""),"",J22/J13) | L22: =L9-L16 -> 0 | M22: =IF(OR(L13=0,L13=""),"",L22/L13)
A23: Minor Operated Department 3 | B23: =B10-B17 -> 0 | C23: =IF(OR(B13=0,B13=""),"",B23/B13) | D23: =D10-D17 -> 0 | E23: =IF(OR(D13=0,D13=""),"",D23/D13) | F23: =F10-F17 -> 0 | G23: =IF(OR(F13=0,F13=""),"",F23/F13) | H23: =H10-H17 -> 0 | I23: =IF(OR(H13=0,H13=""),"",H23/H13) | J23: =J10-J17 -> 0 | K23: =IF(OR(J13=0,J13=""),"",J23/J13) | L23: =L10-L17 -> 0 | M23: =IF(OR(L13=0,L13=""),"",L23/L13)
A24: Minor Operated Department 4 | B24: =B11-B18 -> 0 | C24: =IF(OR(B13=0,B13=""),"",B24/B13) | D24: =D11-D18 -> 0 | E24: =IF(OR(D13=0,D13=""),"",D24/D13) | F24: =F11-F18 -> 0 | G24: =IF(OR(F13=0,F13=""),"",F24/F13) | H24: =H11-H18 -> 0 | I24: =IF(OR(H13=0,H13=""),"",H24/H13) | J24: =J11-J18 -> 0 | K24: =IF(OR(J13=0,J13=""),"",J24/J13) | L24: =L11-L18 -> 0 | M24: =IF(OR(L13=0,L13=""),"",L24/L13)
A25: Total Minor Operated Department Profit | B25: =B13-B19 -> 0 | C25: =IF(OR(B13=0,B13=""),"",B25/B13) | D25: =D13-D19 -> 0 | E25: =IF(OR(D13=0,D13=""),"",D25/D13) | F25: =F13-F19 -> 0 | G25: =IF(OR(F13=0,F13=""),"",F25/F13) | H25: =H13-H19 -> 0 | I25: =IF(OR(H13=0,H13=""),"",H25/H13) | J25: =J13-J19 -> 0 | K25: =IF(OR(J13=0,J13=""),"",J25/J13) | L25: =L13-L19 -> 0 | M25: =IF(OR(L13=0,L13=""),"",L25/L13)

Sheet Schedule 4 - Misc Income
A1: MISCELLANEOUS INCOME — SCHEDULE 4
A2: Property: | B2: ='Setup & Assumptions'!$B$4 -> Enter property name | H2: Period / Year: | J2: ='Setup & Assumptions'!$B$5 -> e.g. January 2026 / FY2026
B4: Current Period | H4: Year-To-Date
B5: Actual | D5: Forecast / Budget | F5: Prior Year | H5: Actual | J5: Forecast / Budget | L5: Prior Year
A6: Line Item | B6: $ | C6: % | D6: $ | E6: % | F6: $ | G6: % | H6: $ | I6: % | J6: $ | K6: % | L6: $ | M6: %
A7: Miscellaneous Income
A8: Attrition Fees | C8: =IF(OR('Summary Op Stmt (Operators)'!$B$20=0,'Summary Op Stmt (Operators)'!$B$20=""),"",B8/'Summary Op Stmt (Operators)'!$B$20) | E8: =IF(OR('Summary Op Stmt (Operators)'!$D$20=0,'Summary Op Stmt (Operators)'!$D$20=""),"",D8/'Summary Op Stmt (Operators)'!$D$20) | G8: =IF(OR('Summary Op Stmt (Operators)'!$F$20=0,'Summary Op Stmt (Operators)'!$F$20=""),"",F8/'Summary Op Stmt (Operators)'!$F$20) | I8: =IF(OR('Summary Op Stmt (Operators)'!$H$20=0,'Summary Op Stmt (Operators)'!$H$20=""),"",H8/'Summary Op Stmt (Operators)'!$H$20) | K8: =IF(OR('Summary Op Stmt (Operators)'!$J$20=0,'Summary Op Stmt (Operators)'!$J$20=""),"",J8/'Summary Op Stmt (Operators)'!$J$20) | M8: =IF(OR('Summary Op Stmt (Operators)'!$L$20=0,'Summary Op Stmt (Operators)'!$L$20=""),"",L8/'Summary Op Stmt (Operators)'!$L$20)
A9: Cancellation Fees | C9: =IF(OR('Summary Op Stmt (Operators)'!$B$20=0,'Summary Op Stmt (Operators)'!$B$20=""),"",B9/'Summary Op Stmt (Operators)'!$B$20) | E9: =IF(OR('Summary Op Stmt (Operators)'!$D$20=0,'Summary Op Stmt (Operators)'!$D$20=""),"",D9/'Summary Op Stmt (Operators)'!$D$20) | G9: =IF(OR('Summary Op Stmt (Operators)'!$F$20=0,'Summary Op Stmt (Operators)'!$F$20=""),"",F9/'Summary Op Stmt (Operators)'!$F$20) | I9: =IF(OR('Summary Op Stmt (Operators)'!$H$20=0,'Summary Op Stmt (Operators)'!$H$20=""),"",H9/'Summary Op Stmt (Operators)'!$H$20) | K9: =IF(OR('Summary Op Stmt (Operators)'!$J$20=0,'Summary Op Stmt (Operators)'!$J$20=""),"",J9/'Summary Op Stmt (Operators)'!$J$20) | M9: =IF(OR('Summary Op Stmt (Operators)'!$L$20=0,'Summary Op Stmt (Operators)'!$L$20=""),"",L9/'Summary Op Stmt (Operators)'!$L$20)
A10: Cash Discounts Earned | C10: =IF(OR('Summary Op Stmt (Operators)'!$B$20=0,'Summary Op Stmt (Operators)'!$B$20=""),"",B10/'Summary Op Stmt (Operators)'!$B$20) | E10: =IF(OR('Summary Op Stmt (Operators)'!$D$20=0,'Summary Op Stmt (Operators)'!$D$20=""),"",D10/'Summary Op Stmt (Operators)'!$D$20) | G10: =IF(OR('Summary Op Stmt (Operators)'!$F$20=0,'Summary Op Stmt (Operators)'!$F$20=""),"",F10/'Summary Op Stmt (Operators)'!$F$20) | I10: =IF(OR('Summary Op Stmt (Operators)'!$H$20=0,'Summary Op Stmt (Operators)'!$H$20=""),"",H10/'Summary Op Stmt (Operators)'!$H$20) | K10: =IF(OR('Summary Op Stmt (Operators)'!$J$20=0,'Summary Op Stmt (Operators)'!$J$20=""),"",J10/'Summary Op Stmt (Operators)'!$J$20) | M10: =IF(OR('Summary Op Stmt (Operators)'!$L$20=0,'Summary Op Stmt (Operators)'!$L$20=""),"",L10/'Summary Op Stmt (Operators)'!$L$20)
A11: Commissions | C11: =IF(OR('Summary Op Stmt (Operators)'!$B$20=0,'Summary Op Stmt (Operators)'!$B$20=""),"",B11/'Summary Op Stmt (Operators)'!$B$20) | E11: =IF(OR('Summary Op Stmt (Operators)'!$D$20=0,'Summary Op Stmt (Operators)'!$D$20=""),"",D11/'Summary Op Stmt (Operators)'!$D$20) | G11: =IF(OR('Summary Op Stmt (Operators)'!$F$20=0,'Summary Op Stmt (Operators)'!$F$20=""),"",F11/'Summary Op Stmt (Operators)'!$F$20) | I11: =IF(OR('Summary Op Stmt (Operators)'!$H$20=0,'Summary Op Stmt (Operators)'!$H$20=""),"",H11/'Summary Op Stmt (Operators)'!$H$20) | K11: =IF(OR('Summary Op Stmt (Operators)'!$J$20=0,'Summary Op Stmt (Operators)'!$J$20=""),"",J11/'Summary Op Stmt (Operators)'!$J$20) | M11: =IF(OR('Summary Op Stmt (Operators)'!$L$20=0,'Summary Op Stmt (Operators)'!$L$20=""),"",L11/'Summary Op Stmt (Operators)'!$L$20)
A12: Guest-Related Foreign Currency Transaction Gains (Losses) | C12: =IF(OR('Summary Op Stmt (Operators)'!$B$20=0,'Summary Op Stmt (Operators)'!$B$20=""),"",B12/'Summary Op Stmt (Operators)'!$B$20) | E12: =IF(OR('Summary Op Stmt (Operators)'!$D$20=0,'Summary Op Stmt (Operators)'!$D$20=""),"",D12/'Summary Op Stmt (Operators)'!$D$20) | G12: =IF(OR('Summary Op Stmt (Operators)'!$F$20=0,'Summary Op Stmt (Operators)'!$F$20=""),"",F12/'Summary Op Stmt (Operators)'!$F$20) | I12: =IF(OR('Summary Op Stmt (Operators)'!$H$20=0,'Summary Op Stmt (Operators)'!$H$20=""),"",H12/'Summary Op Stmt (Operators)'!$H$20) | K12: =IF(OR('Summary Op Stmt (Operators)'!$J$20=0,'Summary Op Stmt (Operators)'!$J$20=""),"",J12/'Summary Op Stmt (Operators)'!$J$20) | M12: =IF(OR('Summary Op Stmt (Operators)'!$L$20=0,'Summary Op Stmt (Operators)'!$L$20=""),"",L12/'Summary Op Stmt (Operators)'!$L$20)
A13: Guest Laundry and Dry Cleaning | C13: =IF(OR('Summary Op Stmt (Operators)'!$B$20=0,'Summary Op Stmt (Operators)'!$B$20=""),"",B13/'Summary Op Stmt (Operators)'!$B$20) | E13: =IF(OR('Summary Op Stmt (Operators)'!$D$20=0,'Summary Op Stmt (Operators)'!$D$20=""),"",D13/'Summary Op Stmt (Operators)'!$D$20) | G13: =IF(OR('Summary Op Stmt (Operators)'!$F$20=0,'Summary Op Stmt (Operators)'!$F$20=""),"",F13/'Summary Op Stmt (Operators)'!$F$20) | I13: =IF(OR('Summary Op Stmt (Operators)'!$H$20=0,'Summary Op Stmt (Operators)'!$H$20=""),"",H13/'Summary Op Stmt (Operators)'!$H$20) | K13: =IF(OR('Summary Op Stmt (Operators)'!$J$20=0,'Summary Op Stmt (Operators)'!$J$20=""),"",J13/'Summary Op Stmt (Operators)'!$J$20) | M13: =IF(OR('Summary Op Stmt (Operators)'!$L$20=0,'Summary Op Stmt (Operators)'!$L$20=""),"",L13/'Summary Op Stmt (Operators)'!$L$20)
A14: Interest Income | C14: =IF(OR('Summary Op Stmt (Operators)'!$B$20=0,'Summary Op Stmt (Operators)'!$B$20=""),"",B14/'Summary Op Stmt (Operators)'!$B$20) | E14: =IF(OR('Summary Op Stmt (Operators)'!$D$20=0,'Summary Op Stmt (Operators)'!$D$20=""),"",D14/'Summary Op Stmt (Operators)'!$D$20) | G14: =IF(OR('Summary Op Stmt (Operators)'!$F$20=0,'Summary Op Stmt (Operators)'!$F$20=""),"",F14/'Summary Op Stmt (Operators)'!$F$20) | I14: =IF(OR('Summary Op Stmt (Operators)'!$H$20=0,'Summary Op Stmt (Operators)'!$H$20=""),"",H14/'Summary Op Stmt (Operators)'!$H$20) | K14: =IF(OR('Summary Op Stmt (Operators)'!$J$20=0,'Summary Op Stmt (Operators)'!$J$20=""),"",J14/'Summary Op Stmt (Operators)'!$J$20) | M14: =IF(OR('Summary Op Stmt (Operators)'!$L$20=0,'Summary Op Stmt (Operators)'!$L$20=""),"",L14/'Summary Op Stmt (Operators)'!$L$20)
A15: Net Revenue from Renting Mixed-Ownership Units | C15: =IF(OR('Summary Op Stmt (Operators)'!$B$20=0,'Summary Op Stmt (Operators)'!$B$20=""),"",B15/'Summary Op Stmt (Operators)'!$B$20) | E15: =IF(OR('Summary Op Stmt (Operators)'!$D$20=0,'Summary Op Stmt (Operators)'!$D$20=""),"",D15/'Summary Op Stmt (Operators)'!$D$20) | G15: =IF(OR('Summary Op Stmt (Operators)'!$F$20=0,'Summary Op Stmt (Operators)'!$F$20=""),"",F15/'Summary Op Stmt (Operators)'!$F$20) | I15: =IF(OR('Summary Op Stmt (Operators)'!$H$20=0,'Summary Op Stmt (Operators)'!$H$20=""),"",H15/'Summary Op Stmt (Operators)'!$H$20) | K15: =IF(OR('Summary Op Stmt (Operators)'!$J$20=0,'Summary Op Stmt (Operators)'!$J$20=""),"",J15/'Summary Op Stmt (Operators)'!$J$20) | M15: =IF(OR('Summary Op Stmt (Operators)'!$L$20=0,'Summary Op Stmt (Operators)'!$L$20=""),"",L15/'Summary Op Stmt (Operators)'!$L$20)
A16: Other Breakage | C16: =IF(OR('Summary Op Stmt (Operators)'!$B$20=0,'Summary Op Stmt (Operators)'!$B$20=""),"",B16/'Summary Op Stmt (Operators)'!$B$20) | E16: =IF(OR('Summary Op Stmt (Operators)'!$D$20=0,'Summary Op Stmt (Operators)'!$D$20=""),"",D16/'Summary Op Stmt (Operators)'!$D$20) | G16: =IF(OR('Summary Op Stmt (Operators)'!$F$20=0,'Summary Op Stmt (Operators)'!$F$20=""),"",F16/'Summary Op Stmt (Operators)'!$F$20) | I16: =IF(OR('Summary Op Stmt (Operators)'!$H$20=0,'Summary Op Stmt (Operators)'!$H$20=""),"",H16/'Summary Op Stmt (Operators)'!$H$20) | K16: =IF(OR('Summary Op Stmt (Operators)'!$J$20=0,'Summary Op Stmt (Operators)'!$J$20=""),"",J16/'Summary Op Stmt (Operators)'!$J$20) | M16: =IF(OR('Summary Op Stmt (Operators)'!$L$20=0,'Summary Op Stmt (Operators)'!$L$20=""),"",L16/'Summary Op Stmt (Operators)'!$L$20)
A17: Package Breakage | C17: =IF(OR('Summary Op Stmt (Operators)'!$B$20=0,'Summary Op Stmt (Operators)'!$B$20=""),"",B17/'Summary Op Stmt (Operators)'!$B$20) | E17: =IF(OR('Summary Op Stmt (Operators)'!$D$20=0,'Summary Op Stmt (Operators)'!$D$20=""),"",D17/'Summary Op Stmt (Operators)'!$D$20) | G17: =IF(OR('Summary Op Stmt (Operators)'!$F$20=0,'Summary Op Stmt (Operators)'!$F$20=""),"",F17/'Summary Op Stmt (Operators)'!$F$20) | I17: =IF(OR('Summary Op Stmt (Operators)'!$H$20=0,'Summary Op Stmt (Operators)'!$H$20=""),"",H17/'Summary Op Stmt (Operators)'!$H$20) | K17: =IF(OR('Summary Op Stmt (Operators)'!$J$20=0,'Summary Op Stmt (Operators)'!$J$20=""),"",J17/'Summary Op Stmt (Operators)'!$J$20) | M17: =IF(OR('Summary Op Stmt (Operators)'!$L$20=0,'Summary Op Stmt (Operators)'!$L$20=""),"",L17/'Summary Op Stmt (Operators)'!$L$20)
A18: Proceeds from Business Interruption Insurance | C18: =IF(OR('Summary Op Stmt (Operators)'!$B$20=0,'Summary Op Stmt (Operators)'!$B$20=""),"",B18/'Summary Op Stmt (Operators)'!$B$20) | E18: =IF(OR('Summary Op Stmt (Operators)'!$D$20=0,'Summary Op Stmt (Operators)'!$D$20=""),"",D18/'Summary Op Stmt (Operators)'!$D$20) | G18: =IF(OR('Summary Op Stmt (Operators)'!$F$20=0,'Summary Op Stmt (Operators)'!$F$20=""),"",F18/'Summary Op Stmt (Operators)'!$F$20) | I18: =IF(OR('Summary Op Stmt (Operators)'!$H$20=0,'Summary Op Stmt (Operators)'!$H$20=""),"",H18/'Summary Op Stmt (Operators)'!$H$20) | K18: =IF(OR('Summary Op Stmt (Operators)'!$J$20=0,'Summary Op Stmt (Operators)'!$J$20=""),"",J18/'Summary Op Stmt (Operators)'!$J$20) | M18: =IF(OR('Summary Op Stmt (Operators)'!$L$20=0,'Summary Op Stmt (Operators)'!$L$20=""),"",L18/'Summary Op Stmt (Operators)'!$L$20)
A19: Resort Fees | C19: =IF(OR('Summary Op Stmt (Operators)'!$B$20=0,'Summary Op Stmt (Operators)'!$B$20=""),"",B19/'Summary Op Stmt (Operators)'!$B$20) | E19: =IF(OR('Summary Op Stmt (Operators)'!$D$20=0,'Summary Op Stmt (Operators)'!$D$20=""),"",D19/'Summary Op Stmt (Operators)'!$D$20) | G19: =IF(OR('Summary Op Stmt (Operators)'!$F$20=0,'Summary Op Stmt (Operators)'!$F$20=""),"",F19/'Summary Op Stmt (Operators)'!$F$20) | I19: =IF(OR('Summary Op Stmt (Operators)'!$H$20=0,'Summary Op Stmt (Operators)'!$H$20=""),"",H19/'Summary Op Stmt (Operators)'!$H$20) | K19: =IF(OR('Summary Op Stmt (Operators)'!$J$20=0,'Summary Op Stmt (Operators)'!$J$20=""),"",J19/'Summary Op Stmt (Operators)'!$J$20) | M19: =IF(OR('Summary Op Stmt (Operators)'!$L$20=0,'Summary Op Stmt (Operators)'!$L$20=""),"",L19/'Summary Op Stmt (Operators)'!$L$20)
... A21: Other | C21: =IF(OR('Summary Op Stmt (Operators)'!$B$20=0,'Summary Op Stmt (Operators)'!$B$20=""),"",B21/'Summary Op Stmt (Operators)'!$B$20) | E21: =IF(OR('Summary Op Stmt (Operators)'!$D$20=0,'Summary Op Stmt (Operators)'!$D$20=""),"",D21/'Summary Op Stmt (Operators)'!$D$20) | G21: =IF(OR('Summary Op Stmt (Operators)'!$F$20=0,'Summary Op Stmt (Operators)'!$F$20=""),"",F21/'Summary Op Stmt (Operators)'!$F$20) | I21: =IF(OR('Summary Op Stmt (Operators)'!$H$20=0,'Summary Op Stmt (Operators)'!$H$20=""),"",H21/'Summary Op Stmt (Operators)'!$H$20) | K21: =IF(OR('Summary Op Stmt (Operators)'!$J$20=0,'Summary Op Stmt (Operators)'!$J$20=""),"",J21/'Summary Op Stmt (Operators)'!$J$20) | M21: =IF(OR('Summary Op Stmt (Operators)'!$L$20=0,'Summary Op Stmt (Operators)'!$L$20=""),"",L21/'Summary Op Stmt (Operators)'!$L$20)
A22: Total Miscellaneous Income | B22: =B8+B9+B10+B11+B12+B13+B14+B15+B16+B17+B18+B19+B20+B21 -> 0 | C22: =IF(OR('Summary Op Stmt (Operators)'!$B$20=0,'Summary Op Stmt (Operators)'!$B$20=""),"",B22/'Summary Op Stmt (Operators)'!$B$20) | D22: =D8+D9+D10+D11+D12+D13+D14+D15+D16+D17+D18+D19+D20+D21 -> 0 | E22: =IF(OR('Summary Op Stmt (Operators)'!$D$20=0,'Summary Op Stmt (Operators)'!$D$20=""),"",D22/'Summary Op Stmt (Operators)'!$D$20) | F22: =F8+F9+F10+F11+F12+F13+F14+F15+F16+F17+F18+F19+F20+F21 -> 0 | G22: =IF(OR('Summary Op Stmt (Operators)'!$F$20=0,'Summary Op Stmt (Operators)'!$F$20=""),"",F22/'Summary Op Stmt (Operators)'!$F$20) | H22: =H8+H9+H10+H11+H12+H13+H14+H15+H16+H17+H18+H19+H20+H21 -> 0 | I22: =IF(OR('Summary Op Stmt (Operators)'!$H$20=0,'Summary Op Stmt (Operators)'!$H$20=""),"",H22/'Summary Op Stmt (Operators)'!$H$20) | J22: =J8+J9+J10+J11+J12+J13+J14+J15+J16+J17+J18+J19+J20+J21 -> 0 | K22: =IF(OR('Summary Op Stmt (Operators)'!$J$20=0,'Summary Op Stmt (Operators)'!$J$20=""),"",J22/'Summary Op Stmt (Operators)'!$J$20) | L22: =L8+L9+L10+L11+L12+L13+L14+L15+L16+L17+L18+L19+L20+L21 -> 0 | M22: =IF(OR('Summary Op Stmt (Operators)'!$L$20=0,'Summary Op Stmt (Operators)'!$L$20=""),"",L22/'Summary Op Stmt (Operators)'!$L$20)

Sheet Schedule 5 - Admin & General
A1: ADMINISTRATIVE AND GENERAL — SCHEDULE 5
A2: Property: | B2: ='Setup & Assumptions'!$B$4 -> Enter property name | H2: Period / Year: | J2: ='Setup & Assumptions'!$B$5 -> e.g. January 2026 / FY2026
B4: Current Period | H4: Year-To-Date
B5: Actual | D5: Forecast / Budget | F5: Prior Year | H5: Actual | J5: Forecast / Budget | L5: Prior Year
A6: Line Item | B6: $ | C6: % | D6: $ | E6: % | F6: $ | G6: % | H6: $ | I6: % | J6: $ | K6: % | L6: $ | M6: %
A7: Expenses
A8: Labor Costs and Related Expenses
A9: Salaries, Wages, Service Charges, Contracted Labor and Bonuses
A10: Salaries and Wages
A11: Management
A12: Non-Management
A13: Accounting
A14: General Support
A15: Human Resources
A16: Purchasing/Receiving
A17: Security
A18: Sub-Total: Salaries and Wages | B18: =B11+B13+B14+B15+B16+B17 -> 0 | D18: =D11+D13+D14+D15+D16+D17 -> 0 | F18: =F11+F13+F14+F15+F16+F17 -> 0 | H18: =H11+H13+H14+H15+H16+H17 -> 0 | J18: =J11+J13+J14+J15+J16+J17 -> 0 | L18: =L11+L13+L14+L15+L16+L17 -> 0
A19: Service Charge Distribution
A20: Contracted, Leased and Outsourced Labor
A21: Bonuses and Incentives
A22: Total Salaries, Wages, Service Charges, Contracted Labor and Bonuses | B22: =B18+B19+B20+B21 -> 0 | C22: =IF(OR('Summary Op Stmt (Operators)'!$B$20=0,'Summary Op Stmt (Operators)'!$B$20=""),"",B22/'Summary Op Stmt (Operators)'!$B$20) | D22: =D18+D19+D20+D21 -> 0 | E22: =IF(OR('Summary Op Stmt (Operators)'!$D$20=0,'Summary Op Stmt (Operators)'!$D$20=""),"",D22/'Summary Op Stmt (Operators)'!$D$20) | F22: =F18+F19+F20+F21 -> 0 | G22: =IF(OR('Summary Op Stmt (Operators)'!$F$20=0,'Summary Op Stmt (Operators)'!$F$20=""),"",F22/'Summary Op Stmt (Operators)'!$F$20) | H22: =H18+H19+H20+H21 -> 0 | I22: =IF(OR('Summary Op Stmt (Operators)'!$H$20=0,'Summary Op Stmt (Operators)'!$H$20=""),"",H22/'Summary Op Stmt (Operators)'!$H$20) | J22: =J18+J19+J20+J21 -> 0 | K22: =IF(OR('Summary Op Stmt (Operators)'!$J$20=0,'Summary Op Stmt (Operators)'!$J$20=""),"",J22/'Summary Op Stmt (Operators)'!$J$20) | L22: =L18+L19+L20+L21 -> 0 | M22: =IF(OR('Summary Op Stmt (Operators)'!$L$20=0,'Summary Op Stmt (Operators)'!$L$20=""),"",L22/'Summary Op Stmt (Operators)'!$L$20)
A23: Payroll-Related Expenses
A24: Payroll Taxes | C24: =IF(OR('Summary Op Stmt (Operators)'!$B$20=0,'Summary Op Stmt (Operators)'!$B$20=""),"",B24/'Summary Op Stmt (Operators)'!$B$20) | E24: =IF(OR('Summary Op Stmt (Operators)'!$D$20=0,'Summary Op Stmt (Operators)'!$D$20=""),"",D24/'Summary Op Stmt (Operators)'!$D$20) | G24: =IF(OR('Summary Op Stmt (Operators)'!$F$20=0,'Summary Op Stmt (Operators)'!$F$20=""),"",F24/'Summary Op Stmt (Operators)'!$F$20) | I24: =IF(OR('Summary Op Stmt (Operators)'!$H$20=0,'Summary Op Stmt (Operators)'!$H$20=""),"",H24/'Summary Op Stmt (Operators)'!$H$20) | K24: =IF(OR('Summary Op Stmt (Operators)'!$J$20=0,'Summary Op Stmt (Operators)'!$J$20=""),"",J24/'Summary Op Stmt (Operators)'!$J$20) | M24: =IF(OR('Summary Op Stmt (Operators)'!$L$20=0,'Summary Op Stmt (Operators)'!$L$20=""),"",L24/'Summary Op Stmt (Operators)'!$L$20)
A25: Supplemental Pay | C25: =IF(OR('Summary Op Stmt (Operators)'!$B$20=0,'Summary Op Stmt (Operators)'!$B$20=""),"",B25/'Summary Op Stmt (Operators)'!$B$20) | E25: =IF(OR('Summary Op Stmt (Operators)'!$D$20=0,'Summary Op Stmt (Operators)'!$D$20=""),"",D25/'Summary Op Stmt (Operators)'!$D$20) | G25: =IF(OR('Summary Op Stmt (Operators)'!$F$20=0,'Summary Op Stmt (Operators)'!$F$20=""),"",F25/'Summary Op Stmt (Operators)'!$F$20) | I25: =IF(OR('Summary Op Stmt (Operators)'!$H$20=0,'Summary Op Stmt (Operators)'!$H$20=""),"",H25/'Summary Op Stmt (Operators)'!$H$20) | K25: =IF(OR('Summary Op Stmt (Operators)'!$J$20=0,'Summary Op Stmt (Operators)'!$J$20=""),"",J25/'Summary Op Stmt (Operators)'!$J$20) | M25: =IF(OR('Summary Op Stmt (Operators)'!$L$20=0,'Summary Op Stmt (Operators)'!$L$20=""),"",L25/'Summary Op Stmt (Operators)'!$L$20)
A26: Employee Benefits | C26: =IF(OR('Summary Op Stmt (Operators)'!$B$20=0,'Summary Op Stmt (Operators)'!$B$20=""),"",B26/'Summary Op Stmt (Operators)'!$B$20) | E26: =IF(OR('Summary Op Stmt (Operators)'!$D$20=0,'Summary Op Stmt (Operators)'!$D$20=""),"",D26/'Summary Op Stmt (Operators)'!$D$20) | G26: =IF(OR('Summary Op Stmt (Operators)'!$F$20=0,'Summary Op Stmt (Operators)'!$F$20=""),"",F26/'Summary Op Stmt (Operators)'!$F$20) | I26: =IF(OR('Summary Op Stmt (Operators)'!$H$20=0,'Summary Op Stmt (Operators)'!$H$20=""),"",H26/'Summary Op Stmt (Operators)'!$H$20) | K26: =IF(OR('Summary Op Stmt (Operators)'!$J$20=0,'Summary Op Stmt (Operators)'!$J$20=""),"",J26/'Summary Op Stmt (Operators)'!$J$20) | M26: =IF(OR('Summary Op Stmt (Operators)'!$L$20=0,'Summary Op Stmt (Operators)'!$L$20=""),"",L26/'Summary Op Stmt (Operators)'!$L$20)
A27: Total Payroll-Related Expenses | B27: =B24+B25+B26 -> 0 | C27: =IF(OR('Summary Op Stmt (Operators)'!$B$20=0,'Summary Op Stmt (Operators)'!$B$20=""),"",B27/'Summary Op Stmt (Operators)'!$B$20) | D27: =D24+D25+D26 -> 0 | E27: =IF(OR('Summary Op Stmt (Operators)'!$D$20=0,'Summary Op Stmt (Operators)'!$D$20=""),"",D27/'Summary Op Stmt (Operators)'!$D$20) | F27: =F24+F25+F26 -> 0 | G27: =IF(OR('Summary Op Stmt (Operators)'!$F$20=0,'Summary Op Stmt (Operators)'!$F$20=""),"",F27/'Summary Op Stmt (Operators)'!$F$20) | H27: =H24+H25+H26 -> 0 | I27: =IF(OR('Summary Op Stmt (Operators)'!$H$20=0,'Summary Op Stmt (Operators)'!$H$20=""),"",H27/'Summary Op Stmt (Operators)'!$H$20) | J27: =J24+J25+J26 -> 0 | K27: =IF(OR('Summary Op Stmt (Operators)'!$J$20=0,'Summary Op Stmt (Operators)'!$J$20=""),"",J27/'Summary Op Stmt (Operators)'!$J$20) | L27: =L24+L25+L26 -> 0 | M27: =IF(OR('Summary Op Stmt (Operators)'!$L$20=0,'Summary Op Stmt (Operators)'!$L$20=""),"",L27/'Summary Op Stmt (Operators)'!$L$20)
A28: Total Labor Costs and Related Expenses | B28: =B22+B27 -> 0 | C28: =IF(OR('Summary Op Stmt (Operators)'!$B$20=0,'Summary Op Stmt (Operators)'!$B$20=""),"",B28/'Summary Op Stmt (Operators)'!$B$20) | D28: =D22+D27 -> 0 | E28: =IF(OR('Summary Op Stmt (Operators)'!$D$20=0,'Summary Op Stmt (Operators)'!$D$20=""),"",D28/'Summary Op Stmt (Operators)'!$D$20) | F28: =F22+F27 -> 0 | G28: =IF(OR('Summary Op Stmt (Operators)'!$F$20=0,'Summary Op Stmt (Operators)'!$F$20=""),"",F28/'Summary Op Stmt (Operators)'!$F$20) | H28: =H22+H27 -> 0 | I28: =IF(OR('Summary Op Stmt (Operators)'!$H$20=0,'Summary Op Stmt (Operators)'!$H$20=""),"",H28/'Summary Op Stmt (Operators)'!$H$20) | J28: =J22+J27 -> 0 | K28: =IF(OR('Summary Op Stmt (Operators)'!$J$20=0,'Summary Op Stmt (Operators)'!$J$20=""),"",J28/'Summary Op Stmt (Operators)'!$J$20) | L28: =L22+L27 -> 0 | M28: =IF(OR('Summary Op Stmt (Operators)'!$L$20=0,'Summary Op Stmt (Operators)'!$L$20=""),"",L28/'Summary Op Stmt (Operators)'!$L$20)
A29: Other Expenses
